Workbook

Sheet Executive_Summary
A1: Nova Consumer Products - CFO Monthly Sales MIS
A2: ="Actuals "&Monthly_MIS!A9&" to "&Monthly_MIS!B4&" | INR | Synthetic data | Controls: "&Control_Checks!C3 -> Actuals 2025-01 to 2026-09 | INR | Synthetic data | Controls: ALL 51 CHECKS PASS
A3: ="Budget: original Sales_Budget is "&TEXT(Budget_Integrity!B5,"0.0")&"x actual revenue and is NOT used. Illustrative variance only against SYNTHETIC v2 (unapproved) - see Budget_vs_Actual_v2 / Budget_Integrity." -> Budget: original Sales_Budget is 7.1x actual revenue and is NOT used. Illustrative variance only against SYNTHETIC v2 (unapproved) - see Budget_vs_Actual_v2 / Budget_Integrity.
A4: Headline KPI | B4: Value | C4: Comment
A5: Net revenue (all actual months) | B5: =Monthly_MIS!E30 -> 42593025 | C5: Actual-status invoices only
A6: COGS | B6: =Monthly_MIS!F30 -> 27380595
A7: Gross profit | B7: =Monthly_MIS!G30 -> 15212430
A8: Gross profit % | B8: =Monthly_MIS!H30 -> 0.35715777
A9: ="YTD revenue "&Monthly_MIS!B5 -> YTD revenue 2026 | B9: =Monthly_MIS!E34 -> 18093974 | C9: Jan to latest actual month
A10: YTD revenue change vs prior-year YTD | B10: =Monthly_MIS!E37 -> -0.017839831 | C10: Like-for-like months
A11: YTD GP % change vs prior-year YTD | B11: =Monthly_MIS!H37 -> -0.11061348 | C11: Percentage points
A12: Control checks | B12: =Control_Checks!C3 -> ALL 51 CHECKS PASS | C12: See Control_Checks
A14: CFO commentary (128 words)
A15: OBSERVED (actuals Jan-2025 to Sep-2026, 21 months): Net revenue INR 4.26 crore, gross profit INR 1.52 crore, margin 35.7%. YTD Sep-2026 revenue INR 1.81 crore, -1.8% vs prior-year YTD; margin 35.7% vs 35.8%. Monthly revenue (INR 18.4-22.6 lakh) and margin (34.8%-36.6%) show no clear trend. Each product sells in one region only, so region and product effects overlap: North's -15.0% YTD is Body Lotion (-24.2%) against Soap 4-pack (+3.7%); South's lowest margin (33.1%) reflects Detergent 1kg (32.6%) and Biscuits 500g (34.0%).
A16: UNVERIFIED CAUSES: Drivers of these movements (pricing, promotions, distribution, input costs, mix) cannot be established from this data. Returns, rebates and GST are excluded. The original budget is not comparable (about 7x actuals; 42% sits in cells with no sales), so no approved budget variance is reported.
A17: Commentary is generated at build time from verified results and checked (150-word limit, every number traceable to the fact pack); it is static text. KPI tiles above are live formulas.
A19: Metric availability
A20: Metric | B20: Status | C20: Reason / note
A21: Monthly net revenue, COGS, gross profit, GP % | B21: Available | C21: Derived from Sales_Transactions (Actual rows).
A22: Region-wise and product-wise performance | B22: Available | C22: Region via Customer_Master; product/category via Product_Master.
A23: Gross sales, trade discounts, returns, rebates | B23: UNAVAILABLE | C23: Source revenue is already net (Units x Net_Price); no gross-to-net, returns or rebate fields exist. List_Price vs Net_Price gap is implied only, not a reported discount.
A24: GST / intercompany adjustments | B24: UNAVAILABLE | C24: Source README states revenue excludes GST and intercompany sales; no such data supplied.
A25: Budget variance (revenue / gross profit) | B25: ILLUSTRATIVE ONLY | C25: Original budget is not comparable (see Budget_Integrity). Variance exists only against a SYNTHETIC calibrated v2 budget that is unapproved - see Budget_vs_Actual_v2.
A26: Product-level budget | B26: UNAVAILABLE | C26: Budget is by Month x Region x Category only.
A27: Region vs product attribution | B27: LIMITED | C27: Each product sells in one region only in this source, so regional and product effects overlap.
A28: Operating profit / EBITDA | B28: OUT OF DAY-1 SCOPE | C28: Opex exists in source but no allocation basis to sales dimensions was provided.

Sheet Monthly_MIS
A1: Monthly Sales & Profitability MIS - Actuals only
A2: Nova Consumer Products (synthetic). INR. Net revenue excludes GST, returns, rebates and intercompany (per source README). Forecast and budget are excluded.
A4: Latest actual month (from Calendar) | B4: =LOOKUP(2,1/(Calendar!$E$2:$E$25="Actual"),Calendar!$A$2:$A$25) -> 2026-09
A5: Latest actual year | B5: =VALUE(LEFT(B4,4)) -> 2026
A6: Latest actual month no. | B6: =VALUE(RIGHT(B4,2)) -> 9
A8: Month | B8: Year | C8: Invoices | D8: Units | E8: Net Revenue (INR) | F8: COGS (INR) | G8: Gross Profit (INR) | H8: GP % | I8: MoM Revenue % | J8: YoY Revenue % | K8: YoY GP % change (pp) | L8: Check: raw-source revenue | M8: Check: raw-source COGS
A9: 2025-01 | B9: =INDEX(Calendar!$B$2:$B$25,MATCH(A9,Calendar!$A$2:$A$25,0)) -> 2025 | C9: =COUNTIFS(Calc_Actuals!$J$2:$J$865,B9,Calc_Actuals!$K$2:$K$865,VALUE(RIGHT(A9,2)),Calc_Actuals!$C$2:$C$865,"Actual") -> 36 | D9: =SUMIFS(Calc_Actuals!$M$2:$M$865,Calc_Actuals!$J$2:$J$865,B9,Calc_Actuals!$K$2:$K$865,VALUE(RIGHT(A9,2)),Calc_Actuals!$C$2:$C$865,"Actual") -> 11217 | E9: =SUMIFS(Calc_Actuals!$N$2:$N$865,Calc_Actuals!$J$2:$J$865,B9,Calc_Actuals!$K$2:$K$865,VALUE(RIGHT(A9,2)),Calc_Actuals!$C$2:$C$865,"Actual") -> 2235970.6 | F9: =SUMIFS(Calc_Actuals!$O$2:$O$865,Calc_Actuals!$J$2:$J$865,B9,Calc_Actuals!$K$2:$K$865,VALUE(RIGHT(A9,2)),Calc_Actuals!$C$2:$C$865,"Actual") -> 1450589 | G9: =E9-F9 -> 785381.64 | H9: =IF(E9=0,"n/a",G9/E9) -> 0.35124864 | I9: n/a | J9: n/a | K9: n/a | L9: =SUMPRODUCT((Sales_Transactions!$B$2:$B$865=A9)*(Sales_Transactions!$C$2:$C$865="Actual")*Sales_Transactions!$I$2:$I$865) -> 2235970.6 | M9: =SUMPRODUCT((Sales_Transactions!$B$2:$B$865=A9)*(Sales_Transactions!$C$2:$C$865="Actual")*Sales_Transactions!$J$2:$J$865) -> 1450589
A10: 2025-02 | B10: =INDEX(Calendar!$B$2:$B$25,MATCH(A10,Calendar!$A$2:$A$25,0)) -> 2025 | C10: =COUNTIFS(Calc_Actuals!$J$2:$J$865,B10,Calc_Actuals!$K$2:$K$865,VALUE(RIGHT(A10,2)),Calc_Actuals!$C$2:$C$865,"Actual") -> 36 | D10: =SUMIFS(Calc_Actuals!$M$2:$M$865,Calc_Actuals!$J$2:$J$865,B10,Calc_Actuals!$K$2:$K$865,VALUE(RIGHT(A10,2)),Calc_Actuals!$C$2:$C$865,"Actual") -> 10456 | E10: =SUMIFS(Calc_Actuals!$N$2:$N$865,Calc_Actuals!$J$2:$J$865,B10,Calc_Actuals!$K$2:$K$865,VALUE(RIGHT(A10,2)),Calc_Actuals!$C$2:$C$865,"Actual") -> 2186134.6 | F10: =SUMIFS(Calc_Actuals!$O$2:$O$865,Calc_Actuals!$J$2:$J$865,B10,Calc_Actuals!$K$2:$K$865,VALUE(RIGHT(A10,2)),Calc_Actuals!$C$2:$C$865,"Actual") -> 1399128.2 | G10: =E10-F10 -> 787006.33 | H10: =IF(E10=0,"n/a",G10/E10) -> 0.35999903 | I10: =E10/E9-1 -> -0.022288343 | J10: n/a | K10: n/a | L10: =SUMPRODUCT((Sales_Transactions!$B$2:$B$865=A10)*(Sales_Transactions!$C$2:$C$865="Actual")*Sales_Transactions!$I$2:$I$865) -> 2186134.6 | M10: =SUMPRODUCT((Sales_Transactions!$B$2:$B$865=A10)*(Sales_Transactions!$C$2:$C$865="Actual")*Sales_Transactions!$J$2:$J$865) -> 1399128.2
A11: 2025-03 | B11: =INDEX(Calendar!$B$2:$B$25,MATCH(A11,Calendar!$A$2:$A$25,0)) -> 2025 | C11: =COUNTIFS(Calc_Actuals!$J$2:$J$865,B11,Calc_Actuals!$K$2:$K$865,VALUE(RIGHT(A11,2)),Calc_Actuals!$C$2:$C$865,"Actual") -> 36 | D11: =SUMIFS(Calc_Actuals!$M$2:$M$865,Calc_Actuals!$J$2:$J$865,B11,Calc_Actuals!$K$2:$K$865,VALUE(RIGHT(A11,2)),Calc_Actuals!$C$2:$C$865,"Actual") -> 9508 | E11: =SUMIFS(Calc_Actuals!$N$2:$N$865,Calc_Actuals!$J$2:$J$865,B11,Calc_Actuals!$K$2:$K$865,VALUE(RIGHT(A11,2)),Calc_Actuals!$C$2:$C$865,"Actual") -> 1892456.3 | F11: =SUMIFS(Calc_Actuals!$O$2:$O$865,Calc_Actuals!$J$2:$J$865,B11,Calc_Actuals!$K$2:$K$865,VALUE(RIGHT(A11,2)),Calc_Actuals!$C$2:$C$865,"Actual") -> 1233925.1 | G11: =E11-F11 -> 658531.2 | H11: =IF(E11=0,"n/a",G11/E11) -> 0.34797696 | I11: =E11/E10-1 -> -0.13433677 | J11: n/a | K11: n/a | L11: =SUMPRODUCT((Sales_Transactions!$B$2:$B$865=A11)*(Sales_Transactions!$C$2:$C$865="Actual")*Sales_Transactions!$I$2:$I$865) -> 1892456.3 | M11: =SUMPRODUCT((Sales_Transactions!$B$2:$B$865=A11)*(Sales_Transactions!$C$2:$C$865="Actual")*Sales_Transactions!$J$2:$J$865) -> 1233925.1
A12: 2025-04 | B12: =INDEX(Calendar!$B$2:$B$25,MATCH(A12,Calendar!$A$2:$A$25,0)) -> 2025 | C12: =COUNTIFS(Calc_Actuals!$J$2:$J$865,B12,Calc_Actuals!$K$2:$K$865,VALUE(RIGHT(A12,2)),Calc_Actuals!$C$2:$C$865,"Actual") -> 36 | D12: =SUMIFS(Calc_Actuals!$M$2:$M$865,Calc_Actuals!$J$2:$J$865,B12,Calc_Actuals!$K$2:$K$865,VALUE(RIGHT(A12,2)),Calc_Actuals!$C$2:$C$865,"Actual") -> 9553 | E12: =SUMIFS(Calc_Actuals!$N$2:$N$865,Calc_Actuals!$J$2:$J$865,B12,Calc_Actuals!$K$2:$K$865,VALUE(RIGHT(A12,2)),Calc_Actuals!$C$2:$C$865,"Actual") -> 2046367.5 | F12: =SUMIFS(Calc_Actuals!$O$2:$O$865,Calc_Actuals!$J$2:$J$865,B12,Calc_Actuals!$K$2:$K$865,VALUE(RIGHT(A12,2)),Calc_Actuals!$C$2:$C$865,"Actual") -> 1304778.8 | G12: =E12-F12 -> 741588.7 | H12: =IF(E12=0,"n/a",G12/E12) -> 0.36239273 | I12: =E12/E11-1 -> 0.081328794 | J12: n/a | K12: n/a | L12: =SUMPRODUCT((Sales_Transactions!$B$2:$B$865=A12)*(Sales_Transactions!$C$2:$C$865="Actual")*Sales_Transactions!$I$2:$I$865) -> 2046367.5 | M12: =SUMPRODUCT((Sales_Transactions!$B$2:$B$865=A12)*(Sales_Transactions!$C$2:$C$865="Actual")*Sales_Transactions!$J$2:$J$865) -> 1304778.8
A13: 2025-05 | B13: =INDEX(Calendar!$B$2:$B$25,MATCH(A13,Calendar!$A$2:$A$25,0)) -> 2025 | C13: =COUNTIFS(Calc_Actuals!$J$2:$J$865,B13,Calc_Actuals!$K$2:$K$865,VALUE(RIGHT(A13,2)),Calc_Actuals!$C$2:$C$865,"Actual") -> 36 | D13: =SUMIFS(Calc_Actuals!$M$2:$M$865,Calc_Actuals!$J$2:$J$865,B13,Calc_Actuals!$K$2:$K$865,VALUE(RIGHT(A13,2)),Calc_Actuals!$C$2:$C$865,"Actual") -> 9461 | E13: =SUMIFS(Calc_Actuals!$N$2:$N$865,Calc_Actuals!$J$2:$J$865,B13,Calc_Actuals!$K$2:$K$865,VALUE(RIGHT(A13,2)),Calc_Actuals!$C$2:$C$865,"Actual") -> 1854769 | F13: =SUMIFS(Calc_Actuals!$O$2:$O$865,Calc_Actuals!$J$2:$J$865,B13,Calc_Actuals!$K$2:$K$865,VALUE(RIGHT(A13,2)),Calc_Actuals!$C$2:$C$865,"Actual") -> 1176459.1 | G13: =E13-F13 -> 678309.89 | H13: =IF(E13=0,"n/a",G13/E13) -> 0.36571125 | I13: =E13/E12-1 -> -0.093628588 | J13: n/a | K13: n/a | L13: =SUMPRODUCT((Sales_Transactions!$B$2:$B$865=A13)*(Sales_Transactions!$C$2:$C$865="Actual")*Sales_Transactions!$I$2:$I$865) -> 1854769 | M13: =SUMPRODUCT((Sales_Transactions!$B$2:$B$865=A13)*(Sales_Transactions!$C$2:$C$865="Actual")*Sales_Transactions!$J$2:$J$865) -> 1176459.1
A14: 2025-06 | B14: =INDEX(Calendar!$B$2:$B$25,MATCH(A14,Calendar!$A$2:$A$25,0)) -> 2025 | C14: =COUNTIFS(Calc_Actuals!$J$2:$J$865,B14,Calc_Actuals!$K$2:$K$865,VALUE(RIGHT(A14,2)),Calc_Actuals!$C$2:$C$865,"Actual") -> 36 | D14: =SUMIFS(Calc_Actuals!$M$2:$M$865,Calc_Actuals!$J$2:$J$865,B14,Calc_Actuals!$K$2:$K$865,VALUE(RIGHT(A14,2)),Calc_Actuals!$C$2:$C$865,"Actual") -> 10213 | E14: =SUMIFS(Calc_Actuals!$N$2:$N$865,Calc_Actuals!$J$2:$J$865,B14,Calc_Actuals!$K$2:$K$865,VALUE(RIGHT(A14,2)),Calc_Actuals!$C$2:$C$865,"Actual") -> 2022308.5 | F14: =SUMIFS(Calc_Actuals!$O$2:$O$865,Calc_Actuals!$J$2:$J$865,B14,Calc_Actuals!$K$2:$K$865,VALUE(RIGHT(A14,2)),Calc_Actuals!$C$2:$C$865,"Actual") -> 1307599.9 | G14: =E14-F14 -> 714708.53 | H14: =IF(E14=0,"n/a",G14/E14) -> 0.35341222 | I14: =E14/E13-1 -> 0.090329027 | J14: n/a | K14: n/a | L14: =SUMPRODUCT((Sales_Transactions!$B$2:$B$865=A14)*(Sales_Transactions!$C$2:$C$865="Actual")*Sales_Transactions!$I$2:$I$865) -> 2022308.5 | M14: =SUMPRODUCT((Sales_Transactions!$B$2:$B$865=A14)*(Sales_Transactions!$C$2:$C$865="Actual")*Sales_Transactions!$J$2:$J$865) -> 1307599.9
A15: 2025-07 | B15: =INDEX(Calendar!$B$2:$B$25,MATCH(A15,Calendar!$A$2:$A$25,0)) -> 2025 | C15: =COUNTIFS(Calc_Actuals!$J$2:$J$865,B15,Calc_Actuals!$K$2:$K$865,VALUE(RIGHT(A15,2)),Calc_Actuals!$C$2:$C$865,"Actual") -> 36 | D15: =SUMIFS(Calc_Actuals!$M$2:$M$865,Calc_Actuals!$J$2:$J$865,B15,Calc_Actuals!$K$2:$K$865,VALUE(RIGHT(A15,2)),Calc_Actuals!$C$2:$C$865,"Actual") -> 10255 | E15: =SUMIFS(Calc_Actuals!$N$2:$N$865,Calc_Actuals!$J$2:$J$865,B15,Calc_Actuals!$K$2:$K$865,VALUE(RIGHT(A15,2)),Calc_Actuals!$C$2:$C$865,"Actual") -> 2118994.9 | F15: =SUMIFS(Calc_Actuals!$O$2:$O$865,Calc_Actuals!$J$2:$J$865,B15,Calc_Actuals!$K$2:$K$865,VALUE(RIGHT(A15,2)),Calc_Actuals!$C$2:$C$865,"Actual") -> 1359634 | G15: =E15-F15 -> 759360.9 | H15: =IF(E15=0,"n/a",G15/E15) -> 0.358359 | I15: =E15/E14-1 -> 0.047809941 | J15: n/a | K15: n/a | L15: =SUMPRODUCT((Sales_Transactions!$B$2:$B$865=A15)*(Sales_Transactions!$C$2:$C$865="Actual")*Sales_Transactions!$I$2:$I$865) -> 2118994.9 | M15: =SUMPRODUCT((Sales_Transactions!$B$2:$B$865=A15)*(Sales_Transactions!$C$2:$C$865="Actual")*Sales_Transactions!$J$2:$J$865) -> 1359634
A16: 2025-08 | B16: =INDEX(Calendar!$B$2:$B$25,MATCH(A16,Calendar!$A$2:$A$25,0)) -> 2025 | C16: =COUNTIFS(Calc_Actuals!$J$2:$J$865,B16,Calc_Actuals!$K$2:$K$865,VALUE(RIGHT(A16,2)),Calc_Actuals!$C$2:$C$865,"Actual") -> 36 | D16: =SUMIFS(Calc_Actuals!$M$2:$M$865,Calc_Actuals!$J$2:$J$865,B16,Calc_Actuals!$K$2:$K$865,VALUE(RIGHT(A16,2)),Calc_Actuals!$C$2:$C$865,"Actual") -> 10467 | E16: =SUMIFS(Calc_Actuals!$N$2:$N$865,Calc_Actuals!$J$2:$J$865,B16,Calc_Actuals!$K$2:$K$865,VALUE(RIGHT(A16,2)),Calc_Actuals!$C$2:$C$865,"Actual") -> 2077890.7 | F16: =SUMIFS(Calc_Actuals!$O$2:$O$865,Calc_Actuals!$J$2:$J$865,B16,Calc_Actuals!$K$2:$K$865,VALUE(RIGHT(A16,2)),Calc_Actuals!$C$2:$C$865,"Actual") -> 1330203.5 | G16: =E16-F16 -> 747687.24 | H16: =IF(E16=0,"n/a",G16/E16) -> 0.35982991 | I16: =E16/E15-1 -> -0.019397975 | J16: n/a | K16: n/a | L16: =SUMPRODUCT((Sales_Transactions!$B$2:$B$865=A16)*(Sales_Transactions!$C$2:$C$865="Actual")*Sales_Transactions!$I$2:$I$865) -> 2077890.7 | M16: =SUMPRODUCT((Sales_Transactions!$B$2:$B$865=A16)*(Sales_Transactions!$C$2:$C$865="Actual")*Sales_Transactions!$J$2:$J$865) -> 1330203.5
A17: 2025-09 | B17: =INDEX(Calendar!$B$2:$B$25,MATCH(A17,Calendar!$A$2:$A$25,0)) -> 2025 | C17: =COUNTIFS(Calc_Actuals!$J$2:$J$865,B17,Calc_Actuals!$K$2:$K$865,VALUE(RIGHT(A17,2)),Calc_Actuals!$C$2:$C$865,"Actual") -> 36 | D17: =SUMIFS(Calc_Actuals!$M$2:$M$865,Calc_Actuals!$J$2:$J$865,B17,Calc_Actuals!$K$2:$K$865,VALUE(RIGHT(A17,2)),Calc_Actuals!$C$2:$C$865,"Actual") -> 9666 | E17: =SUMIFS(Calc_Actuals!$N$2:$N$865,Calc_Actuals!$J$2:$J$865,B17,Calc_Actuals!$K$2:$K$865,VALUE(RIGHT(A17,2)),Calc_Actuals!$C$2:$C$865,"Actual") -> 1987738.3 | F17: =SUMIFS(Calc_Actuals!$O$2:$O$865,Calc_Actuals!$J$2:$J$865,B17,Calc_Actuals!$K$2:$K$865,VALUE(RIGHT(A17,2)),Calc_Actuals!$C$2:$C$865,"Actual") -> 1261139.1 | G17: =E17-F17 -> 726599.29 | H17: =IF(E17=0,"n/a",G17/E17) -> 0.36554071 | I17: =E17/E16-1 -> -0.043386488 | J17: n/a | K17: n/a | L17: =SUMPRODUCT((Sales_Transactions!$B$2:$B$865=A17)*(Sales_Transactions!$C$2:$C$865="Actual")*Sales_Transactions!$I$2:$I$865) -> 1987738.3 | M17: =SUMPRODUCT((Sales_Transactions!$B$2:$B$865=A17)*(Sales_Transactions!$C$2:$C$865="Actual")*Sales_Transactions!$J$2:$J$865) -> 1261139.1
A18: 2025-10 | B18: =INDEX(Calendar!$B$2:$B$25,MATCH(A18,Calendar!$A$2:$A$25,0)) -> 2025 | C18: =COUNTIFS(Calc_Actuals!$J$2:$J$865,B18,Calc_Actuals!$K$2:$K$865,VALUE(RIGHT(A18,2)),Calc_Actuals!$C$2:$C$865,"Actual") -> 36 | D18: =SUMIFS(Calc_Actuals!$M$2:$M$865,Calc_Actuals!$J$2:$J$865,B18,Calc_Actuals!$K$2:$K$865,VALUE(RIGHT(A18,2)),Calc_Actuals!$C$2:$C$865,"Actual") -> 9279 | E18: =SUMIFS(Calc_Actuals!$N$2:$N$865,Calc_Actuals!$J$2:$J$865,B18,Calc_Actuals!$K$2:$K$865,VALUE(RIGHT(A18,2)),Calc_Actuals!$C$2:$C$865,"Actual") -> 1869248.2 | F18: =SUMIFS(Calc_Actuals!$O$2:$O$865,Calc_Actuals!$J$2:$J$865,B18,Calc_Actuals!$K$2:$K$865,VALUE(RIGHT(A18,2)),Calc_Actuals!$C$2:$C$865,"Actual") -> 1205962.6 | G18: =E18-F18 -> 663285.56 | H18: =IF(E18=0,"n/a",G18/E18) -> 0.35484082 | I18: =E18/E17-1 -> -0.059610547 | J18: n/a | K18: n/a | L18: =SUMPRODUCT((Sales_Transactions!$B$2:$B$865=A18)*(Sales_Transactions!$C$2:$C$865="Actual")*Sales_Transactions!$I$2:$I$865) -> 1869248.2 | M18: =SUMPRODUCT((Sales_Transactions!$B$2:$B$865=A18)*(Sales_Transactions!$C$2:$C$865="Actual")*Sales_Transactions!$J$2:$J$865) -> 1205962.6
A19: 2025-11 | B19: =INDEX(Calendar!$B$2:$B$25,MATCH(A19,Calendar!$A$2:$A$25,0)) -> 2025 | C19: =COUNTIFS(Calc_Actuals!$J$2:$J$865,B19,Calc_Actuals!$K$2:$K$865,VALUE(RIGHT(A19,2)),Calc_Actuals!$C$2:$C$865,"Actual") -> 36 | D19: =SUMIFS(Calc_Actuals!$M$2:$M$865,Calc_Actuals!$J$2:$J$865,B19,Calc_Actuals!$K$2:$K$865,VALUE(RIGHT(A19,2)),Calc_Actuals!$C$2:$C$865,"Actual") -> 9797 | E19: =SUMIFS(Calc_Actuals!$N$2:$N$865,Calc_Actuals!$J$2:$J$865,B19,Calc_Actuals!$K$2:$K$865,VALUE(RIGHT(A19,2)),Calc_Actuals!$C$2:$C$865,"Actual") -> 2011362.9 | F19: =SUMIFS(Calc_Actuals!$O$2:$O$865,Calc_Actuals!$J$2:$J$865,B19,Calc_Actuals!$K$2:$K$865,VALUE(RIGHT(A19,2)),Calc_Actuals!$C$2:$C$865,"Actual") -> 1312045 | G19: =E19-F19 -> 699317.88 | H19: =IF(E19=0,"n/a",G19/E19) -> 0.34768359 | I19: =E19/E18-1 -> 0.076027759 | J19: n/a | K19: n/a | L19: =SUMPRODUCT((Sales_Transactions!$B$2:$B$865=A19)*(Sales_Transactions!$C$2:$C$865="Actual")*Sales_Transactions!$I$2:$I$865) -> 2011362.9 | M19: =SUMPRODUCT((Sales_Transactions!$B$2:$B$865=A19)*(Sales_Transactions!$C$2:$C$865="Actual")*Sales_Transactions!$J$2:$J$865) -> 1312045
A20: 2025-12 | B20: =INDEX(Calendar!$B$2:$B$25,MATCH(A20,Calendar!$A$2:$A$25,0)) -> 2025 | C20: =COUNTIFS(Calc_Actuals!$J$2:$J$865,B20,Calc_Actuals!$K$2:$K$865,VALUE(RIGHT(A20,2)),Calc_Actuals!$C$2:$C$865,"Actual") -> 36 | D20: =SUMIFS(Calc_Actuals!$M$2:$M$865,Calc_Actuals!$J$2:$J$865,B20,Calc_Actuals!$K$2:$K$865,VALUE(RIGHT(A20,2)),Calc_Actuals!$C$2:$C$865,"Actual") -> 10675 | E20: =SUMIFS(Calc_Actuals!$N$2:$N$865,Calc_Actuals!$J$2:$J$865,B20,Calc_Actuals!$K$2:$K$865,VALUE(RIGHT(A20,2)),Calc_Actuals!$C$2:$C$865,"Actual") -> 2195809.8 | F20: =SUMIFS(Calc_Actuals!$O$2:$O$865,Calc_Actuals!$J$2:$J$865,B20,Calc_Actuals!$K$2:$K$865,VALUE(RIGHT(A20,2)),Calc_Actuals!$C$2:$C$865,"Actual") -> 1406588.1 | G20: =E20-F20 -> 789221.75 | H20: =IF(E20=0,"n/a",G20/E20) -> 0.35942172 | I20: =E20/E19-1 -> 0.091702451 | J20: n/a | K20: n/a | L20: =SUMPRODUCT((Sales_Transactions!$B$2:$B$865=A20)*(Sales_Transactions!$C$2:$C$865="Actual")*Sales_Transactions!$I$2:$I$865) -> 2195809.8 | M20: =SUMPRODUCT((Sales_Transactions!$B$2:$B$865=A20)*(Sales_Transactions!$C$2:$C$865="Actual")*Sales_Transactions!$J$2:$J$865) -> 1406588.1
A21: 2026-01 | B21: =INDEX(Calendar!$B$2:$B$25,MATCH(A21,Calendar!$A$2:$A$25,0)) -> 2026 | C21: =COUNTIFS(Calc_Actuals!$J$2:$J$865,B21,Calc_Actuals!$K$2:$K$865,VALUE(RIGHT(A21,2)),Calc_Actuals!$C$2:$C$865,"Actual") -> 36 | D21: =SUMIFS(Calc_Actuals!$M$2:$M$865,Calc_Actuals!$J$2:$J$865,B21,Calc_Actuals!$K$2:$K$865,VALUE(RIGHT(A21,2)),Calc_Actuals!$C$2:$C$865,"Actual") -> 9570 | E21: =SUMIFS(Calc_Actuals!$N$2:$N$865,Calc_Actuals!$J$2:$J$865,B21,Calc_Actuals!$K$2:$K$865,VALUE(RIGHT(A21,2)),Calc_Actuals!$C$2:$C$865,"Actual") -> 1873462.9 | F21: =SUMIFS(Calc_Actuals!$O$2:$O$865,Calc_Actuals!$J$2:$J$865,B21,Calc_Actuals!$K$2:$K$865,VALUE(RIGHT(A21,2)),Calc_Actuals!$C$2:$C$865,"Actual") -> 1205508.1 | G21: =E21-F21 -> 667954.83 | H21: =IF(E21=0,"n/a",G21/E21) -> 0.35653485 | I21: =E21/E20-1 -> -0.14680091 | J21: =E21/E9-1 -> -0.16212543 | K21: =(H21-H9)*100 -> 0.52862134 | L21: =SUMPRODUCT((Sales_Transactions!$B$2:$B$865=A21)*(Sales_Transactions!$C$2:$C$865="Actual")*Sales_Transactions!$I$2:$I$865) -> 1873462.9 | M21: =SUMPRODUCT((Sales_Transactions!$B$2:$B$865=A21)*(Sales_Transactions!$C$2:$C$865="Actual")*Sales_Transactions!$J$2:$J$865) -> 1205508.1
A22: 2026-02 | B22: =INDEX(Calendar!$B$2:$B$25,MATCH(A22,Calendar!$A$2:$A$25,0)) -> 2026 | C22: =COUNTIFS(Calc_Actuals!$J$2:$J$865,B22,Calc_Actuals!$K$2:$K$865,VALUE(RIGHT(A22,2)),Calc_Actuals!$C$2:$C$865,"Actual") -> 36 | D22: =SUMIFS(Calc_Actuals!$M$2:$M$865,Calc_Actuals!$J$2:$J$865,B22,Calc_Actuals!$K$2:$K$865,VALUE(RIGHT(A22,2)),Calc_Actuals!$C$2:$C$865,"Actual") -> 9703 | E22: =SUMIFS(Calc_Actuals!$N$2:$N$865,Calc_Actuals!$J$2:$J$865,B22,Calc_Actuals!$K$2:$K$865,VALUE(RIGHT(A22,2)),Calc_Actuals!$C$2:$C$865,"Actual") -> 2004732 | F22: =SUMIFS(Calc_Actuals!$O$2:$O$865,Calc_Actuals!$J$2:$J$865,B22,Calc_Actuals!$K$2:$K$865,VALUE(RIGHT(A22,2)),Calc_Actuals!$C$2:$C$865,"Actual") -> 1285728.7 | G22: =E22-F22 -> 719003.36 | H22: =IF(E22=0,"n/a",G22/E22) -> 0.3586531 | I22: =E22/E21-1 -> 0.070067609 | J22: =E22/E10-1 -> -0.082978675 | K22: =(H22-H10)*100 -> -0.13459293 | L22: =SUMPRODUCT((Sales_Transactions!$B$2:$B$865=A22)*(Sales_Transactions!$C$2:$C$865="Actual")*Sales_Transactions!$I$2:$I$865) -> 2004732 | M22: =SUMPRODUCT((Sales_Transactions!$B$2:$B$865=A22)*(Sales_Transactions!$C$2:$C$865="Actual")*Sales_Transactions!$J$2:$J$865) -> 1285728.7
A23: 2026-03 | B23: =INDEX(Calendar!$B$2:$B$25,MATCH(A23,Calendar!$A$2:$A$25,0)) -> 2026 | C23: =COUNTIFS(Calc_Actuals!$J$2:$J$865,B23,Calc_Actuals!$K$2:$K$865,VALUE(RIGHT(A23,2)),Calc_Actuals!$C$2:$C$865,"Actual") -> 36 | D23: =SUMIFS(Calc_Actuals!$M$2:$M$865,Calc_Actuals!$J$2:$J$865,B23,Calc_Actuals!$K$2:$K$865,VALUE(RIGHT(A23,2)),Calc_Actuals!$C$2:$C$865,"Actual") -> 9712 | E23: =SUMIFS(Calc_Actuals!$N$2:$N$865,Calc_Actuals!$J$2:$J$865,B23,Calc_Actuals!$K$2:$K$865,VALUE(RIGHT(A23,2)),Calc_Actuals!$C$2:$C$865,"Actual") -> 1984215.8 | F23: =SUMIFS(Calc_Actuals!$O$2:$O$865,Calc_Actuals!$J$2:$J$865,B23,Calc_Actuals!$K$2:$K$865,VALUE(RIGHT(A23,2)),Calc_Actuals!$C$2:$C$865,"Actual") -> 1276181.4 | G23: =E23-F23 -> 708034.31 | H23: =IF(E23=0,"n/a",G23/E23) -> 0.35683333 | I23: =E23/E22-1 -> -0.010233916 | J23: =E23/E11-1 -> 0.048486958 | K23: =(H23-H11)*100 -> 0.88563631 | L23: =SUMPRODUCT((Sales_Transactions!$B$2:$B$865=A23)*(Sales_Transactions!$C$2:$C$865="Actual")*Sales_Transactions!$I$2:$I$865) -> 1984215.8 | M23: =SUMPRODUCT((Sales_Transactions!$B$2:$B$865=A23)*(Sales_Transactions!$C$2:$C$865="Actual")*Sales_Transactions!$J$2:$J$865) -> 1276181.4
A24: 2026-04 | B24: =INDEX(Calendar!$B$2:$B$25,MATCH(A24,Calendar!$A$2:$A$25,0)) -> 2026 | C24: =COUNTIFS(Calc_Actuals!$J$2:$J$865,B24,Calc_Actuals!$K$2:$K$865,VALUE(RIGHT(A24,2)),Calc_Actuals!$C$2:$C$865,"Actual") -> 36 | D24: =SUMIFS(Calc_Actuals!$M$2:$M$865,Calc_Actuals!$J$2:$J$865,B24,Calc_Actuals!$K$2:$K$865,VALUE(RIGHT(A24,2)),Calc_Actuals!$C$2:$C$865,"Actual") -> 9917 | E24: =SUMIFS(Calc_Actuals!$N$2:$N$865,Calc_Actuals!$J$2:$J$865,B24,Calc_Actuals!$K$2:$K$865,VALUE(RIGHT(A24,2)),Calc_Actuals!$C$2:$C$865,"Actual") -> 1938660.2 | F24: =SUMIFS(Calc_Actuals!$O$2:$O$865,Calc_Actuals!$J$2:$J$865,B24,Calc_Actuals!$K$2:$K$865,VALUE(RIGHT(A24,2)),Calc_Actuals!$C$2:$C$865,"Actual") -> 1254810.8 | G24: =E24-F24 -> 683849.4 | H24: =IF(E24=0,"n/a",G24/E24) -> 0.3527433 | I24: =E24/E23-1 -> -0.022958965 | J24: =E24/E12-1 -> -0.0526334 | K24: =(H24-H12)*100 -> -0.96494294 | L24: =SUMPRODUCT((Sales_Transactions!$B$2:$B$865=A24)*(Sales_Transactions!$C$2:$C$865="Actual")*Sales_Transactions!$I$2:$I$865) -> 1938660.2 | M24: =SUMPRODUCT((Sales_Transactions!$B$2:$B$865=A24)*(Sales_Transactions!$C$2:$C$865="Actual")*Sales_Transactions!$J$2:$J$865) -> 1254810.8
A25: 2026-05 | B25: =INDEX(Calendar!$B$2:$B$25,MATCH(A25,Calendar!$A$2:$A$25,0)) -> 2026 | C25: =COUNTIFS(Calc_Actuals!$J$2:$J$865,B25,Calc_Actuals!$K$2:$K$865,VALUE(RIGHT(A25,2)),Calc_Actuals!$C$2:$C$865,"Actual") -> 36 | D25: =SUMIFS(Calc_Actuals!$M$2:$M$865,Calc_Actuals!$J$2:$J$865,B25,Calc_Actuals!$K$2:$K$865,VALUE(RIGHT(A25,2)),Calc_Actuals!$C$2:$C$865,"Actual") -> 10484 | E25: =SUMIFS(Calc_Actuals!$N$2:$N$865,Calc_Actuals!$J$2:$J$865,B25,Calc_Actuals!$K$2:$K$865,VALUE(RIGHT(A25,2)),Calc_Actuals!$C$2:$C$865,"Actual") -> 2190614.6 | F25: =SUMIFS(Calc_Actuals!$O$2:$O$865,Calc_Actuals!$J$2:$J$865,B25,Calc_Actuals!$K$2:$K$865,VALUE(RIGHT(A25,2)),Calc_Actuals!$C$2:$C$865,"Actual") -> 1410747.9 | G25: =E25-F25 -> 779866.74 | H25: =IF(E25=0,"n/a",G25/E25) -> 0.35600363 | I25: =E25/E24-1 -> 0.12996314 | J25: =E25/E13-1 -> 0.18107138 | K25: =(H25-H13)*100 -> -0.9707623 | L25: =SUMPRODUCT((Sales_Transactions!$B$2:$B$865=A25)*(Sales_Transactions!$C$2:$C$865="Actual")*Sales_Transactions!$I$2:$I$865) -> 2190614.6 | M25: =SUMPRODUCT((Sales_Transactions!$B$2:$B$865=A25)*(Sales_Transactions!$C$2:$C$865="Actual")*Sales_Transactions!$J$2:$J$865) -> 1410747.9
A26: 2026-06 | B26: =INDEX(Calendar!$B$2:$B$25,MATCH(A26,Calendar!$A$2:$A$25,0)) -> 2026 | C26: =COUNTIFS(Calc_Actuals!$J$2:$J$865,B26,Calc_Actuals!$K$2:$K$865,VALUE(RIGHT(A26,2)),Calc_Actuals!$C$2:$C$865,"Actual") -> 36 | D26: =SUMIFS(Calc_Actuals!$M$2:$M$865,Calc_Actuals!$J$2:$J$865,B26,Calc_Actuals!$K$2:$K$865,VALUE(RIGHT(A26,2)),Calc_Actuals!$C$2:$C$865,"Actual") -> 9992 | E26: =SUMIFS(Calc_Actuals!$N$2:$N$865,Calc_Actuals!$J$2:$J$865,B26,Calc_Actuals!$K$2:$K$865,VALUE(RIGHT(A26,2)),Calc_Actuals!$C$2:$C$865,"Actual") -> 1949299 | F26: =SUMIFS(Calc_Actuals!$O$2:$O$865,Calc_Actuals!$J$2:$J$865,B26,Calc_Actuals!$K$2:$K$865,VALUE(RIGHT(A26,2)),Calc_Actuals!$C$2:$C$865,"Actual") -> 1269183.1 | G26: =E26-F26 -> 680115.93 | H26: =IF(E26=0,"n/a",G26/E26) -> 0.34890282 | I26: =E26/E25-1 -> -0.11015883 | J26: =E26/E14-1 -> -0.036102029 | K26: =(H26-H14)*100 -> -0.45094013 | L26: =SUMPRODUCT((Sales_Transactions!$B$2:$B$865=A26)*(Sales_Transactions!$C$2:$C$865="Actual")*Sales_Transactions!$I$2:$I$865) -> 1949299 | M26: =SUMPRODUCT((Sales_Transactions!$B$2:$B$865=A26)*(Sales_Transactions!$C$2:$C$865="Actual")*Sales_Transactions!$J$2:$J$865) -> 1269183.1
A27: 2026-07 | B27: =INDEX(Calendar!$B$2:$B$25,MATCH(A27,Calendar!$A$2:$A$25,0)) -> 2026 | C27: =COUNTIFS(Calc_Actuals!$J$2:$J$865,B27,Calc_Actuals!$K$2:$K$865,VALUE(RIGHT(A27,2)),Calc_Actuals!$C$2:$C$865,"Actual") -> 36 | D27: =SUMIFS(Calc_Actuals!$M$2:$M$865,Calc_Actuals!$J$2:$J$865,B27,Calc_Actuals!$K$2:$K$865,VALUE(RIGHT(A27,2)),Calc_Actuals!$C$2:$C$865,"Actual") -> 11177 | E27: =SUMIFS(Calc_Actuals!$N$2:$N$865,Calc_Actuals!$J$2:$J$865,B27,Calc_Actuals!$K$2:$K$865,VALUE(RIGHT(A27,2)),Calc_Actuals!$C$2:$C$865,"Actual") -> 2260040.8 | F27: =SUMIFS(Calc_Actuals!$O$2:$O$865,Calc_Actuals!$J$2:$J$865,B27,Calc_Actuals!$K$2:$K$865,VALUE(RIGHT(A27,2)),Calc_Actuals!$C$2:$C$865,"Actual") -> 1444160 | G27: =E27-F27 -> 815880.81 | H27: =IF(E27=0,"n/a",G27/E27) -> 0.36100269 | I27: =E27/E26-1 -> 0.15941205 | J27: =E27/E15-1 -> 0.066562623 | K27: =(H27-H15)*100 -> 0.26436943 | L27: =SUMPRODUCT((Sales_Transactions!$B$2:$B$865=A27)*(Sales_Transactions!$C$2:$C$865="Actual")*Sales_Transactions!$I$2:$I$865) -> 2260040.8 | M27: =SUMPRODUCT((Sales_Transactions!$B$2:$B$865=A27)*(Sales_Transactions!$C$2:$C$865="Actual")*Sales_Transactions!$J$2:$J$865) -> 1444160
A28: 2026-08 | B28: =INDEX(Calendar!$B$2:$B$25,MATCH(A28,Calendar!$A$2:$A$25,0)) -> 2026 | C28: =COUNTIFS(Calc_Actuals!$J$2:$J$865,B28,Calc_Actuals!$K$2:$K$865,VALUE(RIGHT(A28,2)),Calc_Actuals!$C$2:$C$865,"Actual") -> 36 | D28: =SUMIFS(Calc_Actuals!$M$2:$M$865,Calc_Actuals!$J$2:$J$865,B28,Calc_Actuals!$K$2:$K$865,VALUE(RIGHT(A28,2)),Calc_Actuals!$C$2:$C$865,"Actual") -> 10141 | E28: =SUMIFS(Calc_Actuals!$N$2:$N$865,Calc_Actuals!$J$2:$J$865,B28,Calc_Actuals!$K$2:$K$865,VALUE(RIGHT(A28,2)),Calc_Actuals!$C$2:$C$865,"Actual") -> 2055159.1 | F28: =SUMIFS(Calc_Actuals!$O$2:$O$865,Calc_Actuals!$J$2:$J$865,B28,Calc_Actuals!$K$2:$K$865,VALUE(RIGHT(A28,2)),Calc_Actuals!$C$2:$C$865,"Actual") -> 1317378.5 | G28: =E28-F28 -> 737780.56 | H28: =IF(E28=0,"n/a",G28/E28) -> 0.35898952 | I28: =E28/E27-1 -> -0.090653992 | J28: =E28/E16-1 -> -0.010939772 | K28: =(H28-H16)*100 -> -0.084039837 | L28: =SUMPRODUCT((Sales_Transactions!$B$2:$B$865=A28)*(Sales_Transactions!$C$2:$C$865="Actual")*Sales_Transactions!$I$2:$I$865) -> 2055159.1 | M28: =SUMPRODUCT((Sales_Transactions!$B$2:$B$865=A28)*(Sales_Transactions!$C$2:$C$865="Actual")*Sales_Transactions!$J$2:$J$865) -> 1317378.5
A29: 2026-09 | B29: =INDEX(Calendar!$B$2:$B$25,MATCH(A29,Calendar!$A$2:$A$25,0)) -> 2026 | C29: =COUNTIFS(Calc_Actuals!$J$2:$J$865,B29,Calc_Actuals!$K$2:$K$865,VALUE(RIGHT(A29,2)),Calc_Actuals!$C$2:$C$865,"Actual") -> 36 | D29: =SUMIFS(Calc_Actuals!$M$2:$M$865,Calc_Actuals!$J$2:$J$865,B29,Calc_Actuals!$K$2:$K$865,VALUE(RIGHT(A29,2)),Calc_Actuals!$C$2:$C$865,"Actual") -> 9534 | E29: =SUMIFS(Calc_Actuals!$N$2:$N$865,Calc_Actuals!$J$2:$J$865,B29,Calc_Actuals!$K$2:$K$865,VALUE(RIGHT(A29,2)),Calc_Actuals!$C$2:$C$865,"Actual") -> 1837789.4 | F29: =SUMIFS(Calc_Actuals!$O$2:$O$865,Calc_Actuals!$J$2:$J$865,B29,Calc_Actuals!$K$2:$K$865,VALUE(RIGHT(A29,2)),Calc_Actuals!$C$2:$C$865,"Actual") -> 1168844.2 | G29: =E29-F29 -> 668945.26 | H29: =IF(E29=0,"n/a",G29/E29) -> 0.36399451 | I29: =E29/E28-1 -> -0.10576779 | J29: =E29/E17-1 -> -0.075436941 | K29: =(H29-H17)*100 -> -0.15462066 | L29: =SUMPRODUCT((Sales_Transactions!$B$2:$B$865=A29)*(Sales_Transactions!$C$2:$C$865="Actual")*Sales_Transactions!$I$2:$I$865) -> 1837789.4 | M29: =SUMPRODUCT((Sales_Transactions!$B$2:$B$865=A29)*(Sales_Transactions!$C$2:$C$865="Actual")*Sales_Transactions!$J$2:$J$865) -> 1168844.2
A30: Total (actuals) | C30: =SUM(C9:C29) -> 756 | D30: =SUM(D9:D29) -> 210777 | E30: =SUM(E9:E29) -> 42593025 | F30: =SUM(F9:F29) -> 27380595 | G30: =SUM(G9:G29) -> 15212430 | H30: =G30/E30 -> 0.35715777 | L30: =SUM(L9:L29) -> 42593025 | M30: =SUM(M9:M29) -> 27380595
A32: Like-for-like period summary (actuals)
A33: Period | E33: Net Revenue (INR) | F33: COGS (INR) | G33: Gross Profit (INR) | H33: GP %
A34: ="YTD "&B5&" (Jan-"&TEXT(DATE(B5,B6,1),"mmm")&")" -> YTD 2026 (Jan-Sep) | E34: =SUMIFS(Calc_Actuals!$N$2:$N$865,Calc_Actuals!$C$2:$C$865,"Actual",Calc_Actuals!$J$2:$J$865,$B$5,Calc_Actuals!$K$2:$K$865,"<="&$B$6) -> 18093974 | F34: =SUMIFS(Calc_Actuals!$O$2:$O$865,Calc_Actuals!$C$2:$C$865,"Actual",Calc_Actuals!$J$2:$J$865,$B$5,Calc_Actuals!$K$2:$K$865,"<="&$B$6) -> 11632543 | G34: =E34-F34 -> 6461431.2 | H34: =IF(E34=0,"n/a",G34/E34) -> 0.35710404
A35: ="YTD "&(B5-1)&" (Jan-"&TEXT(DATE(B5,B6,1),"mmm")&")" -> YTD 2025 (Jan-Sep) | E35: =SUMIFS(Calc_Actuals!$N$2:$N$865,Calc_Actuals!$C$2:$C$865,"Actual",Calc_Actuals!$J$2:$J$865,($B$5-1),Calc_Actuals!$K$2:$K$865,"<="&$B$6) -> 18422630 | F35: =SUMIFS(Calc_Actuals!$O$2:$O$865,Calc_Actuals!$C$2:$C$865,"Actual",Calc_Actuals!$J$2:$J$865,($B$5-1),Calc_Actuals!$K$2:$K$865,"<="&$B$6) -> 11823457 | G35: =E35-F35 -> 6599173.7 | H35: =IF(E35=0,"n/a",G35/E35) -> 0.35821018
A36: ="Full year "&(B5-1) -> Full year 2025 | E36: =SUMIFS(Calc_Actuals!$N$2:$N$865,Calc_Actuals!$C$2:$C$865,"Actual",Calc_Actuals!$J$2:$J$865,($B$5-1)) -> 24499051 | F36: =SUMIFS(Calc_Actuals!$O$2:$O$865,Calc_Actuals!$C$2:$C$865,"Actual",Calc_Actuals!$J$2:$J$865,($B$5-1)) -> 15748053 | G36: =E36-F36 -> 8750998.9 | H36: =IF(E36=0,"n/a",G36/E36) -> 0.35719746
A37: YTD change (current vs prior) | E37: =IF(E35=0,"n/a",E34/E35-1) -> -0.017839831 | F37: =IF(F35=0,"n/a",F34/F35-1) -> -0.016147063 | G37: =IF(G35=0,"n/a",G34/G35-1) -> -0.020872692 | H37: =(H34-H35)*100 -> -0.11061348

Sheet Region_Performance
A1: Region-wise Performance - Actuals
A2: Actuals only. INR. Totals reconcile to Monthly_MIS (see Control_Checks). YTD = Jan to latest actual month; prior-year YTD is like-for-like.
A5: Region | B5: Net Revenue (INR) | C5: COGS (INR) | D5: Gross Profit (INR) | E5: GP % | F5: Revenue share | G5: YTD Revenue (current) | H5: YTD Revenue (prior) | I5: YTD Rev YoY % | J5: YTD GP % (current) | K5: YTD GP % (prior) | L5: GP % change (pp)
A6: East | B6: =SUMIFS(Calc_Actuals!$N$2:$N$865,Calc_Actuals!$F$2:$F$865,$A6,Calc_Actuals!$C$2:$C$865,"Actual") -> 10080346 | C6: =SUMIFS(Calc_Actuals!$O$2:$O$865,Calc_Actuals!$F$2:$F$865,$A6,Calc_Actuals!$C$2:$C$865,"Actual") -> 6410602.7 | D6: =B6-C6 -> 3669743 | E6: =IF(B6=0,"n/a",D6/B6) -> 0.36404932 | F6: =B6/B$10 -> 0.23666658 | G6: =SUMIFS(Calc_Actuals!$N$2:$N$865,Calc_Actuals!$F$2:$F$865,$A6,Calc_Actuals!$C$2:$C$865,"Actual",Calc_Actuals!$J$2:$J$865,Monthly_MIS!$B$5,Calc_Actuals!$K$2:$K$865,"<="&Monthly_MIS!$B$6) -> 4494059.7 | H6: =SUMIFS(Calc_Actuals!$N$2:$N$865,Calc_Actuals!$F$2:$F$865,$A6,Calc_Actuals!$C$2:$C$865,"Actual",Calc_Actuals!$J$2:$J$865,(Monthly_MIS!$B$5-1),Calc_Actuals!$K$2:$K$865,"<="&Monthly_MIS!$B$6) -> 4089303.9 | I6: =IF(H6=0,"n/a",G6/H6-1) -> 0.098979147 | J6: =IF(G6=0,"n/a",(SUMIFS(Calc_Actuals!$N$2:$N$865,Calc_Actuals!$F$2:$F$865,$A6,Calc_Actuals!$C$2:$C$865,"Actual",Calc_Actuals!$J$2:$J$865,Monthly_MIS!$B$5,Calc_Actuals!$K$2:$K$865,"<="&Monthly_MIS!$B$6)-SUMIFS(Calc_Actuals!$O$2:$O$865,Calc_Actuals!$F$2:$F$865,$A6,Calc_Actuals!$C$2:$C$865,"Actual",Calc_Actuals!$J$2:$J$865,Monthly_MIS!$B$5,Calc_Actuals!$K$2:$K$865,"<="&Monthly_MIS!$B$6))/G6) -> 0.3666296 | K6: =IF(H6=0,"n/a",(SUMIFS(Calc_Actuals!$N$2:$N$865,Calc_Actuals!$F$2:$F$865,$A6,Calc_Actuals!$C$2:$C$865,"Actual",Calc_Actuals!$J$2:$J$865,(Monthly_MIS!$B$5-1),Calc_Actuals!$K$2:$K$865,"<="&Monthly_MIS!$B$6)-SUMIFS(Calc_Actuals!$O$2:$O$865,Calc_Actuals!$F$2:$F$865,$A6,Calc_Actuals!$C$2:$C$865,"Actual",Calc_Actuals!$J$2:$J$865,(Monthly_MIS!$B$5-1),Calc_Actuals!$K$2:$K$865,"<="&Monthly_MIS!$B$6))/H6) -> 0.36185307 | L6: =IFERROR((J6-K6)*100,"n/a") -> 0.47765291
A7: North | B7: =SUMIFS(Calc_Actuals!$N$2:$N$865,Calc_Actuals!$F$2:$F$865,$A7,Calc_Actuals!$C$2:$C$865,"Actual") -> 12412351 | C7: =SUMIFS(Calc_Actuals!$O$2:$O$865,Calc_Actuals!$F$2:$F$865,$A7,Calc_Actuals!$C$2:$C$865,"Actual") -> 7869163.6 | D7: =B7-C7 -> 4543187.4 | E7: =IF(B7=0,"n/a",D7/B7) -> 0.3660215 | F7: =B7/B$10 -> 0.29141745 | G7: =SUMIFS(Calc_Actuals!$N$2:$N$865,Calc_Actuals!$F$2:$F$865,$A7,Calc_Actuals!$C$2:$C$865,"Actual",Calc_Actuals!$J$2:$J$865,Monthly_MIS!$B$5,Calc_Actuals!$K$2:$K$865,"<="&Monthly_MIS!$B$6) -> 4914886 | H7: =SUMIFS(Calc_Actuals!$N$2:$N$865,Calc_Actuals!$F$2:$F$865,$A7,Calc_Actuals!$C$2:$C$865,"Actual",Calc_Actuals!$J$2:$J$865,(Monthly_MIS!$B$5-1),Calc_Actuals!$K$2:$K$865,"<="&Monthly_MIS!$B$6) -> 5782011.6 | I7: =IF(H7=0,"n/a",G7/H7-1) -> -0.14996954 | J7: =IF(G7=0,"n/a",(SUMIFS(Calc_Actuals!$N$2:$N$865,Calc_Actuals!$F$2:$F$865,$A7,Calc_Actuals!$C$2:$C$865,"Actual",Calc_Actuals!$J$2:$J$865,Monthly_MIS!$B$5,Calc_Actuals!$K$2:$K$865,"<="&Monthly_MIS!$B$6)-SUMIFS(Calc_Actuals!$O$2:$O$865,Calc_Actuals!$F$2:$F$865,$A7,Calc_Actuals!$C$2:$C$865,"Actual",Calc_Actuals!$J$2:$J$865,Monthly_MIS!$B$5,Calc_Actuals!$K$2:$K$865,"<="&Monthly_MIS!$B$6))/G7) -> 0.36529582 | K7: =IF(H7=0,"n/a",(SUMIFS(Calc_Actuals!$N$2:$N$865,Calc_Actuals!$F$2:$F$865,$A7,Calc_Actuals!$C$2:$C$865,"Actual",Calc_Actuals!$J$2:$J$865,(Monthly_MIS!$B$5-1),Calc_Actuals!$K$2:$K$865,"<="&Monthly_MIS!$B$6)-SUMIFS(Calc_Actuals!$O$2:$O$865,Calc_Actuals!$F$2:$F$865,$A7,Calc_Actuals!$C$2:$C$865,"Actual",Calc_Actuals!$J$2:$J$865,(Monthly_MIS!$B$5-1),Calc_Actuals!$K$2:$K$865,"<="&Monthly_MIS!$B$6))/H7) -> 0.36990068 | L7: =IFERROR((J7-K7)*100,"n/a") -> -0.46048608
A8: South | B8: =SUMIFS(Calc_Actuals!$N$2:$N$865,Calc_Actuals!$F$2:$F$865,$A8,Calc_Actuals!$C$2:$C$865,"Actual") -> 8028818.4 | C8: =SUMIFS(Calc_Actuals!$O$2:$O$865,Calc_Actuals!$F$2:$F$865,$A8,Calc_Actuals!$C$2:$C$865,"Actual") -> 5375054 | D8: =B8-C8 -> 2653764.5 | E8: =IF(B8=0,"n/a",D8/B8) -> 0.33052989 | F8: =B8/B$10 -> 0.18850078 | G8: =SUMIFS(Calc_Actuals!$N$2:$N$865,Calc_Actuals!$F$2:$F$865,$A8,Calc_Actuals!$C$2:$C$865,"Actual",Calc_Actuals!$J$2:$J$865,Monthly_MIS!$B$5,Calc_Actuals!$K$2:$K$865,"<="&Monthly_MIS!$B$6) -> 3394026.8 | H8: =SUMIFS(Calc_Actuals!$N$2:$N$865,Calc_Actuals!$F$2:$F$865,$A8,Calc_Actuals!$C$2:$C$865,"Actual",Calc_Actuals!$J$2:$J$865,(Monthly_MIS!$B$5-1),Calc_Actuals!$K$2:$K$865,"<="&Monthly_MIS!$B$6) -> 3438531.2 | I8: =IF(H8=0,"n/a",G8/H8-1) -> -0.012942858 | J8: =IF(G8=0,"n/a",(SUMIFS(Calc_Actuals!$N$2:$N$865,Calc_Actuals!$F$2:$F$865,$A8,Calc_Actuals!$C$2:$C$865,"Actual",Calc_Actuals!$J$2:$J$865,Monthly_MIS!$B$5,Calc_Actuals!$K$2:$K$865,"<="&Monthly_MIS!$B$6)-SUMIFS(Calc_Actuals!$O$2:$O$865,Calc_Actuals!$F$2:$F$865,$A8,Calc_Actuals!$C$2:$C$865,"Actual",Calc_Actuals!$J$2:$J$865,Monthly_MIS!$B$5,Calc_Actuals!$K$2:$K$865,"<="&Monthly_MIS!$B$6))/G8) -> 0.33542824 | K8: =IF(H8=0,"n/a",(SUMIFS(Calc_Actuals!$N$2:$N$865,Calc_Actuals!$F$2:$F$865,$A8,Calc_Actuals!$C$2:$C$865,"Actual",Calc_Actuals!$J$2:$J$865,(Monthly_MIS!$B$5-1),Calc_Actuals!$K$2:$K$865,"<="&Monthly_MIS!$B$6)-SUMIFS(Calc_Actuals!$O$2:$O$865,Calc_Actuals!$F$2:$F$865,$A8,Calc_Actuals!$C$2:$C$865,"Actual",Calc_Actuals!$J$2:$J$865,(Monthly_MIS!$B$5-1),Calc_Actuals!$K$2:$K$865,"<="&Monthly_MIS!$B$6))/H8) -> 0.32679113 | L8: =IFERROR((J8-K8)*100,"n/a") -> 0.86371178
A9: West | B9: =SUMIFS(Calc_Actuals!$N$2:$N$865,Calc_Actuals!$F$2:$F$865,$A9,Calc_Actuals!$C$2:$C$865,"Actual") -> 12071510 | C9: =SUMIFS(Calc_Actuals!$O$2:$O$865,Calc_Actuals!$F$2:$F$865,$A9,Calc_Actuals!$C$2:$C$865,"Actual") -> 7725774.9 | D9: =B9-C9 -> 4345735.3 | E9: =IF(B9=0,"n/a",D9/B9) -> 0.3599993 | F9: =B9/B$10 -> 0.28341519 | G9: =SUMIFS(Calc_Actuals!$N$2:$N$865,Calc_Actuals!$F$2:$F$865,$A9,Calc_Actuals!$C$2:$C$865,"Actual",Calc_Actuals!$J$2:$J$865,Monthly_MIS!$B$5,Calc_Actuals!$K$2:$K$865,"<="&Monthly_MIS!$B$6) -> 5291001.4 | H9: =SUMIFS(Calc_Actuals!$N$2:$N$865,Calc_Actuals!$F$2:$F$865,$A9,Calc_Actuals!$C$2:$C$865,"Actual",Calc_Actuals!$J$2:$J$865,(Monthly_MIS!$B$5-1),Calc_Actuals!$K$2:$K$865,"<="&Monthly_MIS!$B$6) -> 5112783.8 | I9: =IF(H9=0,"n/a",G9/H9-1) -> 0.034857255 | J9: =IF(G9=0,"n/a",(SUMIFS(Calc_Actuals!$N$2:$N$865,Calc_Actuals!$F$2:$F$865,$A9,Calc_Actuals!$C$2:$C$865,"Actual",Calc_Actuals!$J$2:$J$865,Monthly_MIS!$B$5,Calc_Actuals!$K$2:$K$865,"<="&Monthly_MIS!$B$6)-SUMIFS(Calc_Actuals!$O$2:$O$865,Calc_Actuals!$F$2:$F$865,$A9,Calc_Actuals!$C$2:$C$865,"Actual",Calc_Actuals!$J$2:$J$865,Monthly_MIS!$B$5,Calc_Actuals!$K$2:$K$865,"<="&Monthly_MIS!$B$6))/G9) -> 0.35530819 | K9: =IF(H9=0,"n/a",(SUMIFS(Calc_Actuals!$N$2:$N$865,Calc_Actuals!$F$2:$F$865,$A9,Calc_Actuals!$C$2:$C$865,"Actual",Calc_Actuals!$J$2:$J$865,(Monthly_MIS!$B$5-1),Calc_Actuals!$K$2:$K$865,"<="&Monthly_MIS!$B$6)-SUMIFS(Calc_Actuals!$O$2:$O$865,Calc_Actuals!$F$2:$F$865,$A9,Calc_Actuals!$C$2:$C$865,"Actual",Calc_Actuals!$J$2:$J$865,(Monthly_MIS!$B$5-1),Calc_Actuals!$K$2:$K$865,"<="&Monthly_MIS!$B$6))/H9) -> 0.36320626 | L9: =IFERROR((J9-K9)*100,"n/a") -> -0.78980608
A10: Total | B10: =SUM(B6:B9) -> 42593025 | C10: =SUM(C6:C9) -> 27380595 | D10: =SUM(D6:D9) -> 15212430 | E10: =D10/B10 -> 0.35715777 | F10: =SUM(F6:F9) -> 1 | G10: =SUM(G6:G9) -> 18093974 | H10: =SUM(H6:H9) -> 18422630 | I10: =G10/H10-1 -> -0.017839831 | J10: =Monthly_MIS!H34 -> 0.35710404 | K10: =Monthly_MIS!H35 -> 0.35821018 | L10: =(J10-K10)*100 -> -0.11061348
A12: Monthly net revenue by region (INR, actuals)
A13: Region | B13: 2025-01 | C13: 2025-02 | D13: 2025-03 | E13: 2025-04 | F13: 2025-05 | G13: 2025-06 | H13: 2025-07 | I13: 2025-08 | J13: 2025-09 | K13: 2025-10 | L13: 2025-11 | M13: 2025-12 | N13: 2026-01 | O13: 2026-02 | P13: 2026-03 | Q13: 2026-04 | R13: 2026-05 | S13: 2026-06 | T13: 2026-07 | U13: 2026-08 | V13: 2026-09 | W13: Total
A14: East | B14: =SUMIFS(Calc_Actuals!$N$2:$N$865,Calc_Actuals!$F$2:$F$865,$A14,Calc_Actuals!$J$2:$J$865,VALUE(LEFT(B$13,4)),Calc_Actuals!$K$2:$K$865,VALUE(RIGHT(B$13,2)),Calc_Actuals!$C$2:$C$865,"Actual") -> 426907.65 | C14: =SUMIFS(Calc_Actuals!$N$2:$N$865,Calc_Actuals!$F$2:$F$865,$A14,Calc_Actuals!$J$2:$J$865,VALUE(LEFT(C$13,4)),Calc_Actuals!$K$2:$K$865,VALUE(RIGHT(C$13,2)),Calc_Actuals!$C$2:$C$865,"Actual") -> 535847.41 | D14: =SUMIFS(Calc_Actuals!$N$2:$N$865,Calc_Actuals!$F$2:$F$865,$A14,Calc_Actuals!$J$2:$J$865,VALUE(LEFT(D$13,4)),Calc_Actuals!$K$2:$K$865,VALUE(RIGHT(D$13,2)),Calc_Actuals!$C$2:$C$865,"Actual") -> 406990.53 | E14: =SUMIFS(Calc_Actuals!$N$2:$N$865,Calc_Actuals!$F$2:$F$865,$A14,Calc_Actuals!$J$2:$J$865,VALUE(LEFT(E$13,4)),Calc_Actuals!$K$2:$K$865,VALUE(RIGHT(E$13,2)),Calc_Actuals!$C$2:$C$865,"Actual") -> 454416.94 | F14: =SUMIFS(Calc_Actuals!$N$2:$N$865,Calc_Actuals!$F$2:$F$865,$A14,Calc_Actuals!$J$2:$J$865,VALUE(LEFT(F$13,4)),Calc_Actuals!$K$2:$K$865,VALUE(RIGHT(F$13,2)),Calc_Actuals!$C$2:$C$865,"Actual") -> 327736.2 | G14: =SUMIFS(Calc_Actuals!$N$2:$N$865,Calc_Actuals!$F$2:$F$865,$A14,Calc_Actuals!$J$2:$J$865,VALUE(LEFT(G$13,4)),Calc_Actuals!$K$2:$K$865,VALUE(RIGHT(G$13,2)),Calc_Actuals!$C$2:$C$865,"Actual") -> 582555.78 | H14: =SUMIFS(Calc_Actuals!$N$2:$N$865,Calc_Actuals!$F$2:$F$865,$A14,Calc_Actuals!$J$2:$J$865,VALUE(LEFT(H$13,4)),Calc_Actuals!$K$2:$K$865,VALUE(RIGHT(H$13,2)),Calc_Actuals!$C$2:$C$865,"Actual") -> 517879.3 | I14: =SUMIFS(Calc_Actuals!$N$2:$N$865,Calc_Actuals!$F$2:$F$865,$A14,Calc_Actuals!$J$2:$J$865,VALUE(LEFT(I$13,4)),Calc_Actuals!$K$2:$K$865,VALUE(RIGHT(I$13,2)),Calc_Actuals!$C$2:$C$865,"Actual") -> 404593.08 | ... V14: =SUMIFS(Calc_Actuals!$N$2:$N$865,Calc_Actuals!$F$2:$F$865,$A14,Calc_Actuals!$J$2:$J$865,VALUE(LEFT(V$13,4)),Calc_Actuals!$K$2:$K$865,VALUE(RIGHT(V$13,2)),Calc_Actuals!$C$2:$C$865,"Actual") -> 498877.72 | W14: =SUM(B14:V14) -> 10080346
A15: North | B15: =SUMIFS(Calc_Actuals!$N$2:$N$865,Calc_Actuals!$F$2:$F$865,$A15,Calc_Actuals!$J$2:$J$865,VALUE(LEFT(B$13,4)),Calc_Actuals!$K$2:$K$865,VALUE(RIGHT(B$13,2)),Calc_Actuals!$C$2:$C$865,"Actual") -> 745665.04 | C15: =SUMIFS(Calc_Actuals!$N$2:$N$865,Calc_Actuals!$F$2:$F$865,$A15,Calc_Actuals!$J$2:$J$865,VALUE(LEFT(C$13,4)),Calc_Actuals!$K$2:$K$865,VALUE(RIGHT(C$13,2)),Calc_Actuals!$C$2:$C$865,"Actual") -> 615537.71 | D15: =SUMIFS(Calc_Actuals!$N$2:$N$865,Calc_Actuals!$F$2:$F$865,$A15,Calc_Actuals!$J$2:$J$865,VALUE(LEFT(D$13,4)),Calc_Actuals!$K$2:$K$865,VALUE(RIGHT(D$13,2)),Calc_Actuals!$C$2:$C$865,"Actual") -> 628432.07 | E15: =SUMIFS(Calc_Actuals!$N$2:$N$865,Calc_Actuals!$F$2:$F$865,$A15,Calc_Actuals!$J$2:$J$865,VALUE(LEFT(E$13,4)),Calc_Actuals!$K$2:$K$865,VALUE(RIGHT(E$13,2)),Calc_Actuals!$C$2:$C$865,"Actual") -> 741614.98 | F15: =SUMIFS(Calc_Actuals!$N$2:$N$865,Calc_Actuals!$F$2:$F$865,$A15,Calc_Actuals!$J$2:$J$865,VALUE(LEFT(F$13,4)),Calc_Actuals!$K$2:$K$865,VALUE(RIGHT(F$13,2)),Calc_Actuals!$C$2:$C$865,"Actual") -> 589779.17 | G15: =SUMIFS(Calc_Actuals!$N$2:$N$865,Calc_Actuals!$F$2:$F$865,$A15,Calc_Actuals!$J$2:$J$865,VALUE(LEFT(G$13,4)),Calc_Actuals!$K$2:$K$865,VALUE(RIGHT(G$13,2)),Calc_Actuals!$C$2:$C$865,"Actual") -> 491732.37 | H15: =SUMIFS(Calc_Actuals!$N$2:$N$865,Calc_Actuals!$F$2:$F$865,$A15,Calc_Actuals!$J$2:$J$865,VALUE(LEFT(H$13,4)),Calc_Actuals!$K$2:$K$865,VALUE(RIGHT(H$13,2)),Calc_Actuals!$C$2:$C$865,"Actual") -> 694054.4 | I15: =SUMIFS(Calc_Actuals!$N$2:$N$865,Calc_Actuals!$F$2:$F$865,$A15,Calc_Actuals!$J$2:$J$865,VALUE(LEFT(I$13,4)),Calc_Actuals!$K$2:$K$865,VALUE(RIGHT(I$13,2)),Calc_Actuals!$C$2:$C$865,"Actual") -> 689586.75 | ... V15: =SUMIFS(Calc_Actuals!$N$2:$N$865,Calc_Actuals!$F$2:$F$865,$A15,Calc_Actuals!$J$2:$J$865,VALUE(LEFT(V$13,4)),Calc_Actuals!$K$2:$K$865,VALUE(RIGHT(V$13,2)),Calc_Actuals!$C$2:$C$865,"Actual") -> 526552.47 | W15: =SUM(B15:V15) -> 12412351
A16: South | B16: =SUMIFS(Calc_Actuals!$N$2:$N$865,Calc_Actuals!$F$2:$F$865,$A16,Calc_Actuals!$J$2:$J$865,VALUE(LEFT(B$13,4)),Calc_Actuals!$K$2:$K$865,VALUE(RIGHT(B$13,2)),Calc_Actuals!$C$2:$C$865,"Actual") -> 489873.7 | C16: =SUMIFS(Calc_Actuals!$N$2:$N$865,Calc_Actuals!$F$2:$F$865,$A16,Calc_Actuals!$J$2:$J$865,VALUE(LEFT(C$13,4)),Calc_Actuals!$K$2:$K$865,VALUE(RIGHT(C$13,2)),Calc_Actuals!$C$2:$C$865,"Actual") -> 339462.96 | D16: =SUMIFS(Calc_Actuals!$N$2:$N$865,Calc_Actuals!$F$2:$F$865,$A16,Calc_Actuals!$J$2:$J$865,VALUE(LEFT(D$13,4)),Calc_Actuals!$K$2:$K$865,VALUE(RIGHT(D$13,2)),Calc_Actuals!$C$2:$C$865,"Actual") -> 394147.11 | E16: =SUMIFS(Calc_Actuals!$N$2:$N$865,Calc_Actuals!$F$2:$F$865,$A16,Calc_Actuals!$J$2:$J$865,VALUE(LEFT(E$13,4)),Calc_Actuals!$K$2:$K$865,VALUE(RIGHT(E$13,2)),Calc_Actuals!$C$2:$C$865,"Actual") -> 278867.73 | F16: =SUMIFS(Calc_Actuals!$N$2:$N$865,Calc_Actuals!$F$2:$F$865,$A16,Calc_Actuals!$J$2:$J$865,VALUE(LEFT(F$13,4)),Calc_Actuals!$K$2:$K$865,VALUE(RIGHT(F$13,2)),Calc_Actuals!$C$2:$C$865,"Actual") -> 372684.01 | G16: =SUMIFS(Calc_Actuals!$N$2:$N$865,Calc_Actuals!$F$2:$F$865,$A16,Calc_Actuals!$J$2:$J$865,VALUE(LEFT(G$13,4)),Calc_Actuals!$K$2:$K$865,VALUE(RIGHT(G$13,2)),Calc_Actuals!$C$2:$C$865,"Actual") -> 358368.08 | H16: =SUMIFS(Calc_Actuals!$N$2:$N$865,Calc_Actuals!$F$2:$F$865,$A16,Calc_Actuals!$J$2:$J$865,VALUE(LEFT(H$13,4)),Calc_Actuals!$K$2:$K$865,VALUE(RIGHT(H$13,2)),Calc_Actuals!$C$2:$C$865,"Actual") -> 400129.96 | I16: =SUMIFS(Calc_Actuals!$N$2:$N$865,Calc_Actuals!$F$2:$F$865,$A16,Calc_Actuals!$J$2:$J$865,VALUE(LEFT(I$13,4)),Calc_Actuals!$K$2:$K$865,VALUE(RIGHT(I$13,2)),Calc_Actuals!$C$2:$C$865,"Actual") -> 406776 | ... V16: =SUMIFS(Calc_Actuals!$N$2:$N$865,Calc_Actuals!$F$2:$F$865,$A16,Calc_Actuals!$J$2:$J$865,VALUE(LEFT(V$13,4)),Calc_Actuals!$K$2:$K$865,VALUE(RIGHT(V$13,2)),Calc_Actuals!$C$2:$C$865,"Actual") -> 360347.41 | W16: =SUM(B16:V16) -> 8028818.4
A17: West | B17: =SUMIFS(Calc_Actuals!$N$2:$N$865,Calc_Actuals!$F$2:$F$865,$A17,Calc_Actuals!$J$2:$J$865,VALUE(LEFT(B$13,4)),Calc_Actuals!$K$2:$K$865,VALUE(RIGHT(B$13,2)),Calc_Actuals!$C$2:$C$865,"Actual") -> 573524.26 | C17: =SUMIFS(Calc_Actuals!$N$2:$N$865,Calc_Actuals!$F$2:$F$865,$A17,Calc_Actuals!$J$2:$J$865,VALUE(LEFT(C$13,4)),Calc_Actuals!$K$2:$K$865,VALUE(RIGHT(C$13,2)),Calc_Actuals!$C$2:$C$865,"Actual") -> 695286.49 | D17: =SUMIFS(Calc_Actuals!$N$2:$N$865,Calc_Actuals!$F$2:$F$865,$A17,Calc_Actuals!$J$2:$J$865,VALUE(LEFT(D$13,4)),Calc_Actuals!$K$2:$K$865,VALUE(RIGHT(D$13,2)),Calc_Actuals!$C$2:$C$865,"Actual") -> 462886.6 | E17: =SUMIFS(Calc_Actuals!$N$2:$N$865,Calc_Actuals!$F$2:$F$865,$A17,Calc_Actuals!$J$2:$J$865,VALUE(LEFT(E$13,4)),Calc_Actuals!$K$2:$K$865,VALUE(RIGHT(E$13,2)),Calc_Actuals!$C$2:$C$865,"Actual") -> 571467.85 | F17: =SUMIFS(Calc_Actuals!$N$2:$N$865,Calc_Actuals!$F$2:$F$865,$A17,Calc_Actuals!$J$2:$J$865,VALUE(LEFT(F$13,4)),Calc_Actuals!$K$2:$K$865,VALUE(RIGHT(F$13,2)),Calc_Actuals!$C$2:$C$865,"Actual") -> 564569.62 | G17: =SUMIFS(Calc_Actuals!$N$2:$N$865,Calc_Actuals!$F$2:$F$865,$A17,Calc_Actuals!$J$2:$J$865,VALUE(LEFT(G$13,4)),Calc_Actuals!$K$2:$K$865,VALUE(RIGHT(G$13,2)),Calc_Actuals!$C$2:$C$865,"Actual") -> 589652.25 | H17: =SUMIFS(Calc_Actuals!$N$2:$N$865,Calc_Actuals!$F$2:$F$865,$A17,Calc_Actuals!$J$2:$J$865,VALUE(LEFT(H$13,4)),Calc_Actuals!$K$2:$K$865,VALUE(RIGHT(H$13,2)),Calc_Actuals!$C$2:$C$865,"Actual") -> 506931.27 | I17: =SUMIFS(Calc_Actuals!$N$2:$N$865,Calc_Actuals!$F$2:$F$865,$A17,Calc_Actuals!$J$2:$J$865,VALUE(LEFT(I$13,4)),Calc_Actuals!$K$2:$K$865,VALUE(RIGHT(I$13,2)),Calc_Actuals!$C$2:$C$865,"Actual") -> 576934.89 | ... V17: =SUMIFS(Calc_Actuals!$N$2:$N$865,Calc_Actuals!$F$2:$F$865,$A17,Calc_Actuals!$J$2:$J$865,VALUE(LEFT(V$13,4)),Calc_Actuals!$K$2:$K$865,VALUE(RIGHT(V$13,2)),Calc_Actuals!$C$2:$C$865,"Actual") -> 452011.84 | W17: =SUM(B17:V17) -> 12071510
A18: Total | B18: =SUM(B14:B17) -> 2235970.6 | C18: =SUM(C14:C17) -> 2186134.6 | D18: =SUM(D14:D17) -> 1892456.3 | E18: =SUM(E14:E17) -> 2046367.5 | F18: =SUM(F14:F17) -> 1854769 | G18: =SUM(G14:G17) -> 2022308.5 | H18: =SUM(H14:H17) -> 2118994.9 | I18: =SUM(I14:I17) -> 2077890.7 | ... W18: =SUM(W14:W17) -> 42593025

Sheet Product_Performance
A1: Product-wise Performance - Actuals
A2: Actuals only. INR. Totals reconcile to Monthly_MIS (see Control_Checks). YTD = Jan to latest actual month; prior-year YTD is like-for-like.
A5: Product | B5: Category | C5: Net Revenue (INR) | D5: COGS (INR) | E5: Gross Profit (INR) | F5: GP % | G5: Revenue share | H5: YTD Revenue (current) | I5: YTD Revenue (prior) | J5: YTD Rev YoY % | K5: YTD GP % (current) | L5: YTD GP % (prior) | M5: GP % change (pp) | N5: Regions selling (actual)
A6: Detergent 1kg | B6: Home Care | C6: =SUMIFS(Calc_Actuals!$N$2:$N$865,Calc_Actuals!$I$2:$I$865,$A6,Calc_Actuals!$C$2:$C$865,"Actual") -> 5329802.4 | D6: =SUMIFS(Calc_Actuals!$O$2:$O$865,Calc_Actuals!$I$2:$I$865,$A6,Calc_Actuals!$C$2:$C$865,"Actual") -> 3592946 | E6: =C6-D6 -> 1736856.4 | F6: =IF(C6=0,"n/a",E6/C6) -> 0.32587632 | G6: =C6/C$14 -> 0.12513322 | H6: =SUMIFS(Calc_Actuals!$N$2:$N$865,Calc_Actuals!$I$2:$I$865,$A6,Calc_Actuals!$C$2:$C$865,"Actual",Calc_Actuals!$J$2:$J$865,Monthly_MIS!$B$5,Calc_Actuals!$K$2:$K$865,"<="&Monthly_MIS!$B$6) -> 2199515.3 | I6: =SUMIFS(Calc_Actuals!$N$2:$N$865,Calc_Actuals!$I$2:$I$865,$A6,Calc_Actuals!$C$2:$C$865,"Actual",Calc_Actuals!$J$2:$J$865,(Monthly_MIS!$B$5-1),Calc_Actuals!$K$2:$K$865,"<="&Monthly_MIS!$B$6) -> 2271071 | J6: =IF(I6=0,"n/a",H6/I6-1) -> -0.031507439 | K6: =IF(H6=0,"n/a",(SUMIFS(Calc_Actuals!$N$2:$N$865,Calc_Actuals!$I$2:$I$865,$A6,Calc_Actuals!$C$2:$C$865,"Actual",Calc_Actuals!$J$2:$J$865,Monthly_MIS!$B$5,Calc_Actuals!$K$2:$K$865,"<="&Monthly_MIS!$B$6)-SUMIFS(Calc_Actuals!$O$2:$O$865,Calc_Actuals!$I$2:$I$865,$A6,Calc_Actuals!$C$2:$C$865,"Actual",Calc_Actuals!$J$2:$J$865,Monthly_MIS!$B$5,Calc_Actuals!$K$2:$K$865,"<="&Monthly_MIS!$B$6))/H6) -> 0.33089589 | L6: =IF(I6=0,"n/a",(SUMIFS(Calc_Actuals!$N$2:$N$865,Calc_Actuals!$I$2:$I$865,$A6,Calc_Actuals!$C$2:$C$865,"Actual",Calc_Actuals!$J$2:$J$865,(Monthly_MIS!$B$5-1),Calc_Actuals!$K$2:$K$865,"<="&Monthly_MIS!$B$6)-SUMIFS(Calc_Actuals!$O$2:$O$865,Calc_Actuals!$I$2:$I$865,$A6,Calc_Actuals!$C$2:$C$865,"Actual",Calc_Actuals!$J$2:$J$865,(Monthly_MIS!$B$5-1),Calc_Actuals!$K$2:$K$865,"<="&Monthly_MIS!$B$6))/I6) -> 0.32311368 | M6: =IFERROR((K6-L6)*100,"n/a") -> 0.77822067 | N6: =SUMPRODUCT(--(COUNTIFS(Calc_Actuals!$I$2:$I$865,$A6,Calc_Actuals!$F$2:$F$865,Region_Performance!$A$6:$A$9,Calc_Actuals!$C$2:$C$865,"Actual")>0)) -> 1
A7: Dishwash Gel | B7: Home Care | C7: =SUMIFS(Calc_Actuals!$N$2:$N$865,Calc_Actuals!$I$2:$I$865,$A7,Calc_Actuals!$C$2:$C$865,"Actual") -> 3716909.9 | D7: =SUMIFS(Calc_Actuals!$O$2:$O$865,Calc_Actuals!$I$2:$I$865,$A7,Calc_Actuals!$C$2:$C$865,"Actual") -> 2250619.4 | E7: =C7-D7 -> 1466290.5 | F7: =IF(C7=0,"n/a",E7/C7) -> 0.3944918 | G7: =C7/C$14 -> 0.087265694 | H7: =SUMIFS(Calc_Actuals!$N$2:$N$865,Calc_Actuals!$I$2:$I$865,$A7,Calc_Actuals!$C$2:$C$865,"Actual",Calc_Actuals!$J$2:$J$865,Monthly_MIS!$B$5,Calc_Actuals!$K$2:$K$865,"<="&Monthly_MIS!$B$6) -> 1565993.1 | I7: =SUMIFS(Calc_Actuals!$N$2:$N$865,Calc_Actuals!$I$2:$I$865,$A7,Calc_Actuals!$C$2:$C$865,"Actual",Calc_Actuals!$J$2:$J$865,(Monthly_MIS!$B$5-1),Calc_Actuals!$K$2:$K$865,"<="&Monthly_MIS!$B$6) -> 1598048.1 | J7: =IF(I7=0,"n/a",H7/I7-1) -> -0.020058846 | K7: =IF(H7=0,"n/a",(SUMIFS(Calc_Actuals!$N$2:$N$865,Calc_Actuals!$I$2:$I$865,$A7,Calc_Actuals!$C$2:$C$865,"Actual",Calc_Actuals!$J$2:$J$865,Monthly_MIS!$B$5,Calc_Actuals!$K$2:$K$865,"<="&Monthly_MIS!$B$6)-SUMIFS(Calc_Actuals!$O$2:$O$865,Calc_Actuals!$I$2:$I$865,$A7,Calc_Actuals!$C$2:$C$865,"Actual",Calc_Actuals!$J$2:$J$865,Monthly_MIS!$B$5,Calc_Actuals!$K$2:$K$865,"<="&Monthly_MIS!$B$6))/H7) -> 0.39172969 | L7: =IF(I7=0,"n/a",(SUMIFS(Calc_Actuals!$N$2:$N$865,Calc_Actuals!$I$2:$I$865,$A7,Calc_Actuals!$C$2:$C$865,"Actual",Calc_Actuals!$J$2:$J$865,(Monthly_MIS!$B$5-1),Calc_Actuals!$K$2:$K$865,"<="&Monthly_MIS!$B$6)-SUMIFS(Calc_Actuals!$O$2:$O$865,Calc_Actuals!$I$2:$I$865,$A7,Calc_Actuals!$C$2:$C$865,"Actual",Calc_Actuals!$J$2:$J$865,(Monthly_MIS!$B$5-1),Calc_Actuals!$K$2:$K$865,"<="&Monthly_MIS!$B$6))/I7) -> 0.39886388 | M7: =IFERROR((K7-L7)*100,"n/a") -> -0.71341813 | N7: =SUMPRODUCT(--(COUNTIFS(Calc_Actuals!$I$2:$I$865,$A7,Calc_Actuals!$F$2:$F$865,Region_Performance!$A$6:$A$9,Calc_Actuals!$C$2:$C$865,"Actual")>0)) -> 1
A8: Shampoo 400ml | B8: Personal Care | C8: =SUMIFS(Calc_Actuals!$N$2:$N$865,Calc_Actuals!$I$2:$I$865,$A8,Calc_Actuals!$C$2:$C$865,"Actual") -> 7438401 | D8: =SUMIFS(Calc_Actuals!$O$2:$O$865,Calc_Actuals!$I$2:$I$865,$A8,Calc_Actuals!$C$2:$C$865,"Actual") -> 4831935.2 | E8: =C8-D8 -> 2606465.9 | F8: =IF(C8=0,"n/a",E8/C8) -> 0.35040674 | G8: =C8/C$14 -> 0.17463895 | H8: =SUMIFS(Calc_Actuals!$N$2:$N$865,Calc_Actuals!$I$2:$I$865,$A8,Calc_Actuals!$C$2:$C$865,"Actual",Calc_Actuals!$J$2:$J$865,Monthly_MIS!$B$5,Calc_Actuals!$K$2:$K$865,"<="&Monthly_MIS!$B$6) -> 3312413.2 | I8: =SUMIFS(Calc_Actuals!$N$2:$N$865,Calc_Actuals!$I$2:$I$865,$A8,Calc_Actuals!$C$2:$C$865,"Actual",Calc_Actuals!$J$2:$J$865,(Monthly_MIS!$B$5-1),Calc_Actuals!$K$2:$K$865,"<="&Monthly_MIS!$B$6) -> 3035812.7 | J8: =IF(I8=0,"n/a",H8/I8-1) -> 0.091112526 | K8: =IF(H8=0,"n/a",(SUMIFS(Calc_Actuals!$N$2:$N$865,Calc_Actuals!$I$2:$I$865,$A8,Calc_Actuals!$C$2:$C$865,"Actual",Calc_Actuals!$J$2:$J$865,Monthly_MIS!$B$5,Calc_Actuals!$K$2:$K$865,"<="&Monthly_MIS!$B$6)-SUMIFS(Calc_Actuals!$O$2:$O$865,Calc_Actuals!$I$2:$I$865,$A8,Calc_Actuals!$C$2:$C$865,"Actual",Calc_Actuals!$J$2:$J$865,Monthly_MIS!$B$5,Calc_Actuals!$K$2:$K$865,"<="&Monthly_MIS!$B$6))/H8) -> 0.34466891 | L8: =IF(I8=0,"n/a",(SUMIFS(Calc_Actuals!$N$2:$N$865,Calc_Actuals!$I$2:$I$865,$A8,Calc_Actuals!$C$2:$C$865,"Actual",Calc_Actuals!$J$2:$J$865,(Monthly_MIS!$B$5-1),Calc_Actuals!$K$2:$K$865,"<="&Monthly_MIS!$B$6)-SUMIFS(Calc_Actuals!$O$2:$O$865,Calc_Actuals!$I$2:$I$865,$A8,Calc_Actuals!$C$2:$C$865,"Actual",Calc_Actuals!$J$2:$J$865,(Monthly_MIS!$B$5-1),Calc_Actuals!$K$2:$K$865,"<="&Monthly_MIS!$B$6))/I8) -> 0.35243399 | M8: =IFERROR((K8-L8)*100,"n/a") -> -0.77650755 | N8: =SUMPRODUCT(--(COUNTIFS(Calc_Actuals!$I$2:$I$865,$A8,Calc_Actuals!$F$2:$F$865,Region_Performance!$A$6:$A$9,Calc_Actuals!$C$2:$C$865,"Actual")>0)) -> 1
A9: Soap 4-pack | B9: Personal Care | C9: =SUMIFS(Calc_Actuals!$N$2:$N$865,Calc_Actuals!$I$2:$I$865,$A9,Calc_Actuals!$C$2:$C$865,"Actual") -> 4437357.5 | D9: =SUMIFS(Calc_Actuals!$O$2:$O$865,Calc_Actuals!$I$2:$I$865,$A9,Calc_Actuals!$C$2:$C$865,"Actual") -> 2578870 | E9: =C9-D9 -> 1858487.4 | F9: =IF(C9=0,"n/a",E9/C9) -> 0.41882753 | G9: =C9/C$14 -> 0.10418038 | H9: =SUMIFS(Calc_Actuals!$N$2:$N$865,Calc_Actuals!$I$2:$I$865,$A9,Calc_Actuals!$C$2:$C$865,"Actual",Calc_Actuals!$J$2:$J$865,Monthly_MIS!$B$5,Calc_Actuals!$K$2:$K$865,"<="&Monthly_MIS!$B$6) -> 1972313.7 | I9: =SUMIFS(Calc_Actuals!$N$2:$N$865,Calc_Actuals!$I$2:$I$865,$A9,Calc_Actuals!$C$2:$C$865,"Actual",Calc_Actuals!$J$2:$J$865,(Monthly_MIS!$B$5-1),Calc_Actuals!$K$2:$K$865,"<="&Monthly_MIS!$B$6) -> 1902277.8 | J9: =IF(I9=0,"n/a",H9/I9-1) -> 0.036816863 | K9: =IF(H9=0,"n/a",(SUMIFS(Calc_Actuals!$N$2:$N$865,Calc_Actuals!$I$2:$I$865,$A9,Calc_Actuals!$C$2:$C$865,"Actual",Calc_Actuals!$J$2:$J$865,Monthly_MIS!$B$5,Calc_Actuals!$K$2:$K$865,"<="&Monthly_MIS!$B$6)-SUMIFS(Calc_Actuals!$O$2:$O$865,Calc_Actuals!$I$2:$I$865,$A9,Calc_Actuals!$C$2:$C$865,"Actual",Calc_Actuals!$J$2:$J$865,Monthly_MIS!$B$5,Calc_Actuals!$K$2:$K$865,"<="&Monthly_MIS!$B$6))/H9) -> 0.41103137 | L9: =IF(I9=0,"n/a",(SUMIFS(Calc_Actuals!$N$2:$N$865,Calc_Actuals!$I$2:$I$865,$A9,Calc_Actuals!$C$2:$C$865,"Actual",Calc_Actuals!$J$2:$J$865,(Monthly_MIS!$B$5-1),Calc_Actuals!$K$2:$K$865,"<="&Monthly_MIS!$B$6)-SUMIFS(Calc_Actuals!$O$2:$O$865,Calc_Actuals!$I$2:$I$865,$A9,Calc_Actuals!$C$2:$C$865,"Actual",Calc_Actuals!$J$2:$J$865,(Monthly_MIS!$B$5-1),Calc_Actuals!$K$2:$K$865,"<="&Monthly_MIS!$B$6))/I9) -> 0.4263669 | M9: =IFERROR((K9-L9)*100,"n/a") -> -1.5335527 | N9: =SUMPRODUCT(--(COUNTIFS(Calc_Actuals!$I$2:$I$865,$A9,Calc_Actuals!$F$2:$F$865,Region_Performance!$A$6:$A$9,Calc_Actuals!$C$2:$C$865,"Actual")>0)) -> 1
A10: Biscuits 500g | B10: Foods | C10: =SUMIFS(Calc_Actuals!$N$2:$N$865,Calc_Actuals!$I$2:$I$865,$A10,Calc_Actuals!$C$2:$C$865,"Actual") -> 2699016 | D10: =SUMIFS(Calc_Actuals!$O$2:$O$865,Calc_Actuals!$I$2:$I$865,$A10,Calc_Actuals!$C$2:$C$865,"Actual") -> 1782108 | E10: =C10-D10 -> 916908.08 | F10: =IF(C10=0,"n/a",E10/C10) -> 0.33971939 | G10: =C10/C$14 -> 0.063367559 | H10: =SUMIFS(Calc_Actuals!$N$2:$N$865,Calc_Actuals!$I$2:$I$865,$A10,Calc_Actuals!$C$2:$C$865,"Actual",Calc_Actuals!$J$2:$J$865,Monthly_MIS!$B$5,Calc_Actuals!$K$2:$K$865,"<="&Monthly_MIS!$B$6) -> 1194511.5 | I10: =SUMIFS(Calc_Actuals!$N$2:$N$865,Calc_Actuals!$I$2:$I$865,$A10,Calc_Actuals!$C$2:$C$865,"Actual",Calc_Actuals!$J$2:$J$865,(Monthly_MIS!$B$5-1),Calc_Actuals!$K$2:$K$865,"<="&Monthly_MIS!$B$6) -> 1167460.3 | J10: =IF(I10=0,"n/a",H10/I10-1) -> 0.02317099 | K10: =IF(H10=0,"n/a",(SUMIFS(Calc_Actuals!$N$2:$N$865,Calc_Actuals!$I$2:$I$865,$A10,Calc_Actuals!$C$2:$C$865,"Actual",Calc_Actuals!$J$2:$J$865,Monthly_MIS!$B$5,Calc_Actuals!$K$2:$K$865,"<="&Monthly_MIS!$B$6)-SUMIFS(Calc_Actuals!$O$2:$O$865,Calc_Actuals!$I$2:$I$865,$A10,Calc_Actuals!$C$2:$C$865,"Actual",Calc_Actuals!$J$2:$J$865,Monthly_MIS!$B$5,Calc_Actuals!$K$2:$K$865,"<="&Monthly_MIS!$B$6))/H10) -> 0.3437739 | L10: =IF(I10=0,"n/a",(SUMIFS(Calc_Actuals!$N$2:$N$865,Calc_Actuals!$I$2:$I$865,$A10,Calc_Actuals!$C$2:$C$865,"Actual",Calc_Actuals!$J$2:$J$865,(Monthly_MIS!$B$5-1),Calc_Actuals!$K$2:$K$865,"<="&Monthly_MIS!$B$6)-SUMIFS(Calc_Actuals!$O$2:$O$865,Calc_Actuals!$I$2:$I$865,$A10,Calc_Actuals!$C$2:$C$865,"Actual",Calc_Actuals!$J$2:$J$865,(Monthly_MIS!$B$5-1),Calc_Actuals!$K$2:$K$865,"<="&Monthly_MIS!$B$6))/I10) -> 0.33394489 | M10: =IFERROR((K10-L10)*100,"n/a") -> 0.98290112 | N10: =SUMPRODUCT(--(COUNTIFS(Calc_Actuals!$I$2:$I$865,$A10,Calc_Actuals!$F$2:$F$865,Region_Performance!$A$6:$A$9,Calc_Actuals!$C$2:$C$865,"Actual")>0)) -> 1
A11: Breakfast Cereal | B11: Foods | C11: =SUMIFS(Calc_Actuals!$N$2:$N$865,Calc_Actuals!$I$2:$I$865,$A11,Calc_Actuals!$C$2:$C$865,"Actual") -> 6363435.8 | D11: =SUMIFS(Calc_Actuals!$O$2:$O$865,Calc_Actuals!$I$2:$I$865,$A11,Calc_Actuals!$C$2:$C$865,"Actual") -> 4159983.2 | E11: =C11-D11 -> 2203452.5 | F11: =IF(C11=0,"n/a",E11/C11) -> 0.34626774 | G11: =C11/C$14 -> 0.14940089 | H11: =SUMIFS(Calc_Actuals!$N$2:$N$865,Calc_Actuals!$I$2:$I$865,$A11,Calc_Actuals!$C$2:$C$865,"Actual",Calc_Actuals!$J$2:$J$865,Monthly_MIS!$B$5,Calc_Actuals!$K$2:$K$865,"<="&Monthly_MIS!$B$6) -> 2928066.6 | I11: =SUMIFS(Calc_Actuals!$N$2:$N$865,Calc_Actuals!$I$2:$I$865,$A11,Calc_Actuals!$C$2:$C$865,"Actual",Calc_Actuals!$J$2:$J$865,(Monthly_MIS!$B$5-1),Calc_Actuals!$K$2:$K$865,"<="&Monthly_MIS!$B$6) -> 2491255.8 | J11: =IF(I11=0,"n/a",H11/I11-1) -> 0.1753376 | K11: =IF(H11=0,"n/a",(SUMIFS(Calc_Actuals!$N$2:$N$865,Calc_Actuals!$I$2:$I$865,$A11,Calc_Actuals!$C$2:$C$865,"Actual",Calc_Actuals!$J$2:$J$865,Monthly_MIS!$B$5,Calc_Actuals!$K$2:$K$865,"<="&Monthly_MIS!$B$6)-SUMIFS(Calc_Actuals!$O$2:$O$865,Calc_Actuals!$I$2:$I$865,$A11,Calc_Actuals!$C$2:$C$865,"Actual",Calc_Actuals!$J$2:$J$865,Monthly_MIS!$B$5,Calc_Actuals!$K$2:$K$865,"<="&Monthly_MIS!$B$6))/H11) -> 0.35320553 | L11: =IF(I11=0,"n/a",(SUMIFS(Calc_Actuals!$N$2:$N$865,Calc_Actuals!$I$2:$I$865,$A11,Calc_Actuals!$C$2:$C$865,"Actual",Calc_Actuals!$J$2:$J$865,(Monthly_MIS!$B$5-1),Calc_Actuals!$K$2:$K$865,"<="&Monthly_MIS!$B$6)-SUMIFS(Calc_Actuals!$O$2:$O$865,Calc_Actuals!$I$2:$I$865,$A11,Calc_Actuals!$C$2:$C$865,"Actual",Calc_Actuals!$J$2:$J$865,(Monthly_MIS!$B$5-1),Calc_Actuals!$K$2:$K$865,"<="&Monthly_MIS!$B$6))/I11) -> 0.33811202 | M11: =IFERROR((K11-L11)*100,"n/a") -> 1.5093515 | N11: =SUMPRODUCT(--(COUNTIFS(Calc_Actuals!$I$2:$I$865,$A11,Calc_Actuals!$F$2:$F$865,Region_Performance!$A$6:$A$9,Calc_Actuals!$C$2:$C$865,"Actual")>0)) -> 1
A12: Floor Cleaner | B12: Home Care | C12: =SUMIFS(Calc_Actuals!$N$2:$N$865,Calc_Actuals!$I$2:$I$865,$A12,Calc_Actuals!$C$2:$C$865,"Actual") -> 4633109.2 | D12: =SUMIFS(Calc_Actuals!$O$2:$O$865,Calc_Actuals!$I$2:$I$865,$A12,Calc_Actuals!$C$2:$C$865,"Actual") -> 2893839.8 | E12: =C12-D12 -> 1739269.4 | F12: =IF(C12=0,"n/a",E12/C12) -> 0.37540005 | G12: =C12/C$14 -> 0.10877624 | H12: =SUMIFS(Calc_Actuals!$N$2:$N$865,Calc_Actuals!$I$2:$I$865,$A12,Calc_Actuals!$C$2:$C$865,"Actual",Calc_Actuals!$J$2:$J$865,Monthly_MIS!$B$5,Calc_Actuals!$K$2:$K$865,"<="&Monthly_MIS!$B$6) -> 1978588.2 | I12: =SUMIFS(Calc_Actuals!$N$2:$N$865,Calc_Actuals!$I$2:$I$865,$A12,Calc_Actuals!$C$2:$C$865,"Actual",Calc_Actuals!$J$2:$J$865,(Monthly_MIS!$B$5-1),Calc_Actuals!$K$2:$K$865,"<="&Monthly_MIS!$B$6) -> 2076971.1 | J12: =IF(I12=0,"n/a",H12/I12-1) -> -0.047368473 | K12: =IF(H12=0,"n/a",(SUMIFS(Calc_Actuals!$N$2:$N$865,Calc_Actuals!$I$2:$I$865,$A12,Calc_Actuals!$C$2:$C$865,"Actual",Calc_Actuals!$J$2:$J$865,Monthly_MIS!$B$5,Calc_Actuals!$K$2:$K$865,"<="&Monthly_MIS!$B$6)-SUMIFS(Calc_Actuals!$O$2:$O$865,Calc_Actuals!$I$2:$I$865,$A12,Calc_Actuals!$C$2:$C$865,"Actual",Calc_Actuals!$J$2:$J$865,Monthly_MIS!$B$5,Calc_Actuals!$K$2:$K$865,"<="&Monthly_MIS!$B$6))/H12) -> 0.37311973 | L12: =IF(I12=0,"n/a",(SUMIFS(Calc_Actuals!$N$2:$N$865,Calc_Actuals!$I$2:$I$865,$A12,Calc_Actuals!$C$2:$C$865,"Actual",Calc_Actuals!$J$2:$J$865,(Monthly_MIS!$B$5-1),Calc_Actuals!$K$2:$K$865,"<="&Monthly_MIS!$B$6)-SUMIFS(Calc_Actuals!$O$2:$O$865,Calc_Actuals!$I$2:$I$865,$A12,Calc_Actuals!$C$2:$C$865,"Actual",Calc_Actuals!$J$2:$J$865,(Monthly_MIS!$B$5-1),Calc_Actuals!$K$2:$K$865,"<="&Monthly_MIS!$B$6))/I12) -> 0.37895158 | M12: =IFERROR((K12-L12)*100,"n/a") -> -0.58318482 | N12: =SUMPRODUCT(--(COUNTIFS(Calc_Actuals!$I$2:$I$865,$A12,Calc_Actuals!$F$2:$F$865,Region_Performance!$A$6:$A$9,Calc_Actuals!$C$2:$C$865,"Actual")>0)) -> 1
A13: Body Lotion | B13: Personal Care | C13: =SUMIFS(Calc_Actuals!$N$2:$N$865,Calc_Actuals!$I$2:$I$865,$A13,Calc_Actuals!$C$2:$C$865,"Actual") -> 7974993.5 | D13: =SUMIFS(Calc_Actuals!$O$2:$O$865,Calc_Actuals!$I$2:$I$865,$A13,Calc_Actuals!$C$2:$C$865,"Actual") -> 5290293.6 | E13: =C13-D13 -> 2684699.9 | F13: =IF(C13=0,"n/a",E13/C13) -> 0.33663976 | G13: =C13/C$14 -> 0.18723708 | H13: =SUMIFS(Calc_Actuals!$N$2:$N$865,Calc_Actuals!$I$2:$I$865,$A13,Calc_Actuals!$C$2:$C$865,"Actual",Calc_Actuals!$J$2:$J$865,Monthly_MIS!$B$5,Calc_Actuals!$K$2:$K$865,"<="&Monthly_MIS!$B$6) -> 2942572.3 | I13: =SUMIFS(Calc_Actuals!$N$2:$N$865,Calc_Actuals!$I$2:$I$865,$A13,Calc_Actuals!$C$2:$C$865,"Actual",Calc_Actuals!$J$2:$J$865,(Monthly_MIS!$B$5-1),Calc_Actuals!$K$2:$K$865,"<="&Monthly_MIS!$B$6) -> 3879733.8 | J13: =IF(I13=0,"n/a",H13/I13-1) -> -0.24155305 | K13: =IF(H13=0,"n/a",(SUMIFS(Calc_Actuals!$N$2:$N$865,Calc_Actuals!$I$2:$I$865,$A13,Calc_Actuals!$C$2:$C$865,"Actual",Calc_Actuals!$J$2:$J$865,Monthly_MIS!$B$5,Calc_Actuals!$K$2:$K$865,"<="&Monthly_MIS!$B$6)-SUMIFS(Calc_Actuals!$O$2:$O$865,Calc_Actuals!$I$2:$I$865,$A13,Calc_Actuals!$C$2:$C$865,"Actual",Calc_Actuals!$J$2:$J$865,Monthly_MIS!$B$5,Calc_Actuals!$K$2:$K$865,"<="&Monthly_MIS!$B$6))/H13) -> 0.33464071 | L13: =IF(I13=0,"n/a",(SUMIFS(Calc_Actuals!$N$2:$N$865,Calc_Actuals!$I$2:$I$865,$A13,Calc_Actuals!$C$2:$C$865,"Actual",Calc_Actuals!$J$2:$J$865,(Monthly_MIS!$B$5-1),Calc_Actuals!$K$2:$K$865,"<="&Monthly_MIS!$B$6)-SUMIFS(Calc_Actuals!$O$2:$O$865,Calc_Actuals!$I$2:$I$865,$A13,Calc_Actuals!$C$2:$C$865,"Actual",Calc_Actuals!$J$2:$J$865,(Monthly_MIS!$B$5-1),Calc_Actuals!$K$2:$K$865,"<="&Monthly_MIS!$B$6))/I13) -> 0.34221464 | M13: =IFERROR((K13-L13)*100,"n/a") -> -0.75739324 | N13: =SUMPRODUCT(--(COUNTIFS(Calc_Actuals!$I$2:$I$865,$A13,Calc_Actuals!$F$2:$F$865,Region_Performance!$A$6:$A$9,Calc_Actuals!$C$2:$C$865,"Actual")>0)) -> 1
A14: Total | C14: =SUM(C6:C13) -> 42593025 | D14: =SUM(D6:D13) -> 27380595 | E14: =SUM(E6:E13) -> 15212430 | F14: =E14/C14 -> 0.35715777 | G14: =SUM(G6:G13) -> 1 | H14: =SUM(H6:H13) -> 18093974 | I14: =SUM(I6:I13) -> 18422630 | J14: =H14/I14-1 -> -0.017839831 | K14: =Monthly_MIS!H34 -> 0.35710404 | L14: =Monthly_MIS!H35 -> 0.35821018 | M14: =(K14-L14)*100 -> -0.11061348
A16: Monthly net revenue by product (INR, actuals)
A17: Product | B17: 2025-01 | C17: 2025-02 | D17: 2025-03 | E17: 2025-04 | F17: 2025-05 | G17: 2025-06 | H17: 2025-07 | I17: 2025-08 | J17: 2025-09 | K17: 2025-10 | L17: 2025-11 | M17: 2025-12 | N17: 2026-01 | O17: 2026-02 | P17: 2026-03 | Q17: 2026-04 | R17: 2026-05 | S17: 2026-06 | T17: 2026-07 | U17: 2026-08 | V17: 2026-09 | W17: Total
A18: Detergent 1kg | B18: =SUMIFS(Calc_Actuals!$N$2:$N$865,Calc_Actuals!$I$2:$I$865,$A18,Calc_Actuals!$J$2:$J$865,VALUE(LEFT(B$17,4)),Calc_Actuals!$K$2:$K$865,VALUE(RIGHT(B$17,2)),Calc_Actuals!$C$2:$C$865,"Actual") -> 334532.4 | C18: =SUMIFS(Calc_Actuals!$N$2:$N$865,Calc_Actuals!$I$2:$I$865,$A18,Calc_Actuals!$J$2:$J$865,VALUE(LEFT(C$17,4)),Calc_Actuals!$K$2:$K$865,VALUE(RIGHT(C$17,2)),Calc_Actuals!$C$2:$C$865,"Actual") -> 258067.7 | D18: =SUMIFS(Calc_Actuals!$N$2:$N$865,Calc_Actuals!$I$2:$I$865,$A18,Calc_Actuals!$J$2:$J$865,VALUE(LEFT(D$17,4)),Calc_Actuals!$K$2:$K$865,VALUE(RIGHT(D$17,2)),Calc_Actuals!$C$2:$C$865,"Actual") -> 241196.46 | E18: =SUMIFS(Calc_Actuals!$N$2:$N$865,Calc_Actuals!$I$2:$I$865,$A18,Calc_Actuals!$J$2:$J$865,VALUE(LEFT(E$17,4)),Calc_Actuals!$K$2:$K$865,VALUE(RIGHT(E$17,2)),Calc_Actuals!$C$2:$C$865,"Actual") -> 192535.28 | F18: =SUMIFS(Calc_Actuals!$N$2:$N$865,Calc_Actuals!$I$2:$I$865,$A18,Calc_Actuals!$J$2:$J$865,VALUE(LEFT(F$17,4)),Calc_Actuals!$K$2:$K$865,VALUE(RIGHT(F$17,2)),Calc_Actuals!$C$2:$C$865,"Actual") -> 229355.85 | G18: =SUMIFS(Calc_Actuals!$N$2:$N$865,Calc_Actuals!$I$2:$I$865,$A18,Calc_Actuals!$J$2:$J$865,VALUE(LEFT(G$17,4)),Calc_Actuals!$K$2:$K$865,VALUE(RIGHT(G$17,2)),Calc_Actuals!$C$2:$C$865,"Actual") -> 210958.7 | H18: =SUMIFS(Calc_Actuals!$N$2:$N$865,Calc_Actuals!$I$2:$I$865,$A18,Calc_Actuals!$J$2:$J$865,VALUE(LEFT(H$17,4)),Calc_Actuals!$K$2:$K$865,VALUE(RIGHT(H$17,2)),Calc_Actuals!$C$2:$C$865,"Actual") -> 299637.52 | I18: =SUMIFS(Calc_Actuals!$N$2:$N$865,Calc_Actuals!$I$2:$I$865,$A18,Calc_Actuals!$J$2:$J$865,VALUE(LEFT(I$17,4)),Calc_Actuals!$K$2:$K$865,VALUE(RIGHT(I$17,2)),Calc_Actuals!$C$2:$C$865,"Actual") -> 215998.56 | ... V18: =SUMIFS(Calc_Actuals!$N$2:$N$865,Calc_Actuals!$I$2:$I$865,$A18,Calc_Actuals!$J$2:$J$865,VALUE(LEFT(V$17,4)),Calc_Actuals!$K$2:$K$865,VALUE(RIGHT(V$17,2)),Calc_Actuals!$C$2:$C$865,"Actual") -> 195578.31 | W18: =SUM(B18:V18) -> 5329802.4
A19: Dishwash Gel | B19: =SUMIFS(Calc_Actuals!$N$2:$N$865,Calc_Actuals!$I$2:$I$865,$A19,Calc_Actuals!$J$2:$J$865,VALUE(LEFT(B$17,4)),Calc_Actuals!$K$2:$K$865,VALUE(RIGHT(B$17,2)),Calc_Actuals!$C$2:$C$865,"Actual") -> 196945.92 | C19: =SUMIFS(Calc_Actuals!$N$2:$N$865,Calc_Actuals!$I$2:$I$865,$A19,Calc_Actuals!$J$2:$J$865,VALUE(LEFT(C$17,4)),Calc_Actuals!$K$2:$K$865,VALUE(RIGHT(C$17,2)),Calc_Actuals!$C$2:$C$865,"Actual") -> 214023.76 | D19: =SUMIFS(Calc_Actuals!$N$2:$N$865,Calc_Actuals!$I$2:$I$865,$A19,Calc_Actuals!$J$2:$J$865,VALUE(LEFT(D$17,4)),Calc_Actuals!$K$2:$K$865,VALUE(RIGHT(D$17,2)),Calc_Actuals!$C$2:$C$865,"Actual") -> 192219.8 | E19: =SUMIFS(Calc_Actuals!$N$2:$N$865,Calc_Actuals!$I$2:$I$865,$A19,Calc_Actuals!$J$2:$J$865,VALUE(LEFT(E$17,4)),Calc_Actuals!$K$2:$K$865,VALUE(RIGHT(E$17,2)),Calc_Actuals!$C$2:$C$865,"Actual") -> 152922.98 | F19: =SUMIFS(Calc_Actuals!$N$2:$N$865,Calc_Actuals!$I$2:$I$865,$A19,Calc_Actuals!$J$2:$J$865,VALUE(LEFT(F$17,4)),Calc_Actuals!$K$2:$K$865,VALUE(RIGHT(F$17,2)),Calc_Actuals!$C$2:$C$865,"Actual") -> 156641.66 | G19: =SUMIFS(Calc_Actuals!$N$2:$N$865,Calc_Actuals!$I$2:$I$865,$A19,Calc_Actuals!$J$2:$J$865,VALUE(LEFT(G$17,4)),Calc_Actuals!$K$2:$K$865,VALUE(RIGHT(G$17,2)),Calc_Actuals!$C$2:$C$865,"Actual") -> 188587.97 | H19: =SUMIFS(Calc_Actuals!$N$2:$N$865,Calc_Actuals!$I$2:$I$865,$A19,Calc_Actuals!$J$2:$J$865,VALUE(LEFT(H$17,4)),Calc_Actuals!$K$2:$K$865,VALUE(RIGHT(H$17,2)),Calc_Actuals!$C$2:$C$865,"Actual") -> 123535 | I19: =SUMIFS(Calc_Actuals!$N$2:$N$865,Calc_Actuals!$I$2:$I$865,$A19,Calc_Actuals!$J$2:$J$865,VALUE(LEFT(I$17,4)),Calc_Actuals!$K$2:$K$865,VALUE(RIGHT(I$17,2)),Calc_Actuals!$C$2:$C$865,"Actual") -> 192148.97 | ... V19: =SUMIFS(Calc_Actuals!$N$2:$N$865,Calc_Actuals!$I$2:$I$865,$A19,Calc_Actuals!$J$2:$J$865,VALUE(LEFT(V$17,4)),Calc_Actuals!$K$2:$K$865,VALUE(RIGHT(V$17,2)),Calc_Actuals!$C$2:$C$865,"Actual") -> 213746.51 | W19: =SUM(B19:V19) -> 3716909.9
A20: Shampoo 400ml | B20: =SUMIFS(Calc_Actuals!$N$2:$N$865,Calc_Actuals!$I$2:$I$865,$A20,Calc_Actuals!$J$2:$J$865,VALUE(LEFT(B$17,4)),Calc_Actuals!$K$2:$K$865,VALUE(RIGHT(B$17,2)),Calc_Actuals!$C$2:$C$865,"Actual") -> 326794.66 | C20: =SUMIFS(Calc_Actuals!$N$2:$N$865,Calc_Actuals!$I$2:$I$865,$A20,Calc_Actuals!$J$2:$J$865,VALUE(LEFT(C$17,4)),Calc_Actuals!$K$2:$K$865,VALUE(RIGHT(C$17,2)),Calc_Actuals!$C$2:$C$865,"Actual") -> 360089.25 | D20: =SUMIFS(Calc_Actuals!$N$2:$N$865,Calc_Actuals!$I$2:$I$865,$A20,Calc_Actuals!$J$2:$J$865,VALUE(LEFT(D$17,4)),Calc_Actuals!$K$2:$K$865,VALUE(RIGHT(D$17,2)),Calc_Actuals!$C$2:$C$865,"Actual") -> 257443.87 | E20: =SUMIFS(Calc_Actuals!$N$2:$N$865,Calc_Actuals!$I$2:$I$865,$A20,Calc_Actuals!$J$2:$J$865,VALUE(LEFT(E$17,4)),Calc_Actuals!$K$2:$K$865,VALUE(RIGHT(E$17,2)),Calc_Actuals!$C$2:$C$865,"Actual") -> 417325.8 | F20: =SUMIFS(Calc_Actuals!$N$2:$N$865,Calc_Actuals!$I$2:$I$865,$A20,Calc_Actuals!$J$2:$J$865,VALUE(LEFT(F$17,4)),Calc_Actuals!$K$2:$K$865,VALUE(RIGHT(F$17,2)),Calc_Actuals!$C$2:$C$865,"Actual") -> 354669.71 | G20: =SUMIFS(Calc_Actuals!$N$2:$N$865,Calc_Actuals!$I$2:$I$865,$A20,Calc_Actuals!$J$2:$J$865,VALUE(LEFT(G$17,4)),Calc_Actuals!$K$2:$K$865,VALUE(RIGHT(G$17,2)),Calc_Actuals!$C$2:$C$865,"Actual") -> 346156.59 | H20: =SUMIFS(Calc_Actuals!$N$2:$N$865,Calc_Actuals!$I$2:$I$865,$A20,Calc_Actuals!$J$2:$J$865,VALUE(LEFT(H$17,4)),Calc_Actuals!$K$2:$K$865,VALUE(RIGHT(H$17,2)),Calc_Actuals!$C$2:$C$865,"Actual") -> 269049.49 | I20: =SUMIFS(Calc_Actuals!$N$2:$N$865,Calc_Actuals!$I$2:$I$865,$A20,Calc_Actuals!$J$2:$J$865,VALUE(LEFT(I$17,4)),Calc_Actuals!$K$2:$K$865,VALUE(RIGHT(I$17,2)),Calc_Actuals!$C$2:$C$865,"Actual") -> 336894.25 | ... V20: =SUMIFS(Calc_Actuals!$N$2:$N$865,Calc_Actuals!$I$2:$I$865,$A20,Calc_Actuals!$J$2:$J$865,VALUE(LEFT(V$17,4)),Calc_Actuals!$K$2:$K$865,VALUE(RIGHT(V$17,2)),Calc_Actuals!$C$2:$C$865,"Actual") -> 304199.96 | W20: =SUM(B20:V20) -> 7438401
A21: Soap 4-pack | B21: =SUMIFS(Calc_Actuals!$N$2:$N$865,Calc_Actuals!$I$2:$I$865,$A21,Calc_Actuals!$J$2:$J$865,VALUE(LEFT(B$17,4)),Calc_Actuals!$K$2:$K$865,VALUE(RIGHT(B$17,2)),Calc_Actuals!$C$2:$C$865,"Actual") -> 209099.23 | C21: =SUMIFS(Calc_Actuals!$N$2:$N$865,Calc_Actuals!$I$2:$I$865,$A21,Calc_Actuals!$J$2:$J$865,VALUE(LEFT(C$17,4)),Calc_Actuals!$K$2:$K$865,VALUE(RIGHT(C$17,2)),Calc_Actuals!$C$2:$C$865,"Actual") -> 142643.91 | D21: =SUMIFS(Calc_Actuals!$N$2:$N$865,Calc_Actuals!$I$2:$I$865,$A21,Calc_Actuals!$J$2:$J$865,VALUE(LEFT(D$17,4)),Calc_Actuals!$K$2:$K$865,VALUE(RIGHT(D$17,2)),Calc_Actuals!$C$2:$C$865,"Actual") -> 166006.42 | E21: =SUMIFS(Calc_Actuals!$N$2:$N$865,Calc_Actuals!$I$2:$I$865,$A21,Calc_Actuals!$J$2:$J$865,VALUE(LEFT(E$17,4)),Calc_Actuals!$K$2:$K$865,VALUE(RIGHT(E$17,2)),Calc_Actuals!$C$2:$C$865,"Actual") -> 287938.18 | F21: =SUMIFS(Calc_Actuals!$N$2:$N$865,Calc_Actuals!$I$2:$I$865,$A21,Calc_Actuals!$J$2:$J$865,VALUE(LEFT(F$17,4)),Calc_Actuals!$K$2:$K$865,VALUE(RIGHT(F$17,2)),Calc_Actuals!$C$2:$C$865,"Actual") -> 291380.01 | G21: =SUMIFS(Calc_Actuals!$N$2:$N$865,Calc_Actuals!$I$2:$I$865,$A21,Calc_Actuals!$J$2:$J$865,VALUE(LEFT(G$17,4)),Calc_Actuals!$K$2:$K$865,VALUE(RIGHT(G$17,2)),Calc_Actuals!$C$2:$C$865,"Actual") -> 165539.88 | H21: =SUMIFS(Calc_Actuals!$N$2:$N$865,Calc_Actuals!$I$2:$I$865,$A21,Calc_Actuals!$J$2:$J$865,VALUE(LEFT(H$17,4)),Calc_Actuals!$K$2:$K$865,VALUE(RIGHT(H$17,2)),Calc_Actuals!$C$2:$C$865,"Actual") -> 244889.72 | I21: =SUMIFS(Calc_Actuals!$N$2:$N$865,Calc_Actuals!$I$2:$I$865,$A21,Calc_Actuals!$J$2:$J$865,VALUE(LEFT(I$17,4)),Calc_Actuals!$K$2:$K$865,VALUE(RIGHT(I$17,2)),Calc_Actuals!$C$2:$C$865,"Actual") -> 172393.08 | ... V21: =SUMIFS(Calc_Actuals!$N$2:$N$865,Calc_Actuals!$I$2:$I$865,$A21,Calc_Actuals!$J$2:$J$865,VALUE(LEFT(V$17,4)),Calc_Actuals!$K$2:$K$865,VALUE(RIGHT(V$17,2)),Calc_Actuals!$C$2:$C$865,"Actual") -> 247661.21 | W21: =SUM(B21:V21) -> 4437357.5
A22: Biscuits 500g | B22: =SUMIFS(Calc_Actuals!$N$2:$N$865,Calc_Actuals!$I$2:$I$865,$A22,Calc_Actuals!$J$2:$J$865,VALUE(LEFT(B$17,4)),Calc_Actuals!$K$2:$K$865,VALUE(RIGHT(B$17,2)),Calc_Actuals!$C$2:$C$865,"Actual") -> 155341.3 | C22: =SUMIFS(Calc_Actuals!$N$2:$N$865,Calc_Actuals!$I$2:$I$865,$A22,Calc_Actuals!$J$2:$J$865,VALUE(LEFT(C$17,4)),Calc_Actuals!$K$2:$K$865,VALUE(RIGHT(C$17,2)),Calc_Actuals!$C$2:$C$865,"Actual") -> 81395.26 | D22: =SUMIFS(Calc_Actuals!$N$2:$N$865,Calc_Actuals!$I$2:$I$865,$A22,Calc_Actuals!$J$2:$J$865,VALUE(LEFT(D$17,4)),Calc_Actuals!$K$2:$K$865,VALUE(RIGHT(D$17,2)),Calc_Actuals!$C$2:$C$865,"Actual") -> 152950.65 | E22: =SUMIFS(Calc_Actuals!$N$2:$N$865,Calc_Actuals!$I$2:$I$865,$A22,Calc_Actuals!$J$2:$J$865,VALUE(LEFT(E$17,4)),Calc_Actuals!$K$2:$K$865,VALUE(RIGHT(E$17,2)),Calc_Actuals!$C$2:$C$865,"Actual") -> 86332.45 | F22: =SUMIFS(Calc_Actuals!$N$2:$N$865,Calc_Actuals!$I$2:$I$865,$A22,Calc_Actuals!$J$2:$J$865,VALUE(LEFT(F$17,4)),Calc_Actuals!$K$2:$K$865,VALUE(RIGHT(F$17,2)),Calc_Actuals!$C$2:$C$865,"Actual") -> 143328.16 | G22: =SUMIFS(Calc_Actuals!$N$2:$N$865,Calc_Actuals!$I$2:$I$865,$A22,Calc_Actuals!$J$2:$J$865,VALUE(LEFT(G$17,4)),Calc_Actuals!$K$2:$K$865,VALUE(RIGHT(G$17,2)),Calc_Actuals!$C$2:$C$865,"Actual") -> 147409.38 | H22: =SUMIFS(Calc_Actuals!$N$2:$N$865,Calc_Actuals!$I$2:$I$865,$A22,Calc_Actuals!$J$2:$J$865,VALUE(LEFT(H$17,4)),Calc_Actuals!$K$2:$K$865,VALUE(RIGHT(H$17,2)),Calc_Actuals!$C$2:$C$865,"Actual") -> 100492.44 | I22: =SUMIFS(Calc_Actuals!$N$2:$N$865,Calc_Actuals!$I$2:$I$865,$A22,Calc_Actuals!$J$2:$J$865,VALUE(LEFT(I$17,4)),Calc_Actuals!$K$2:$K$865,VALUE(RIGHT(I$17,2)),Calc_Actuals!$C$2:$C$865,"Actual") -> 190777.44 | ... V22: =SUMIFS(Calc_Actuals!$N$2:$N$865,Calc_Actuals!$I$2:$I$865,$A22,Calc_Actuals!$J$2:$J$865,VALUE(LEFT(V$17,4)),Calc_Actuals!$K$2:$K$865,VALUE(RIGHT(V$17,2)),Calc_Actuals!$C$2:$C$865,"Actual") -> 164769.1 | W22: =SUM(B22:V22) -> 2699016
A23: Breakfast Cereal | B23: =SUMIFS(Calc_Actuals!$N$2:$N$865,Calc_Actuals!$I$2:$I$865,$A23,Calc_Actuals!$J$2:$J$865,VALUE(LEFT(B$17,4)),Calc_Actuals!$K$2:$K$865,VALUE(RIGHT(B$17,2)),Calc_Actuals!$C$2:$C$865,"Actual") -> 229961.73 | C23: =SUMIFS(Calc_Actuals!$N$2:$N$865,Calc_Actuals!$I$2:$I$865,$A23,Calc_Actuals!$J$2:$J$865,VALUE(LEFT(C$17,4)),Calc_Actuals!$K$2:$K$865,VALUE(RIGHT(C$17,2)),Calc_Actuals!$C$2:$C$865,"Actual") -> 321823.65 | D23: =SUMIFS(Calc_Actuals!$N$2:$N$865,Calc_Actuals!$I$2:$I$865,$A23,Calc_Actuals!$J$2:$J$865,VALUE(LEFT(D$17,4)),Calc_Actuals!$K$2:$K$865,VALUE(RIGHT(D$17,2)),Calc_Actuals!$C$2:$C$865,"Actual") -> 214770.73 | E23: =SUMIFS(Calc_Actuals!$N$2:$N$865,Calc_Actuals!$I$2:$I$865,$A23,Calc_Actuals!$J$2:$J$865,VALUE(LEFT(E$17,4)),Calc_Actuals!$K$2:$K$865,VALUE(RIGHT(E$17,2)),Calc_Actuals!$C$2:$C$865,"Actual") -> 301493.96 | F23: =SUMIFS(Calc_Actuals!$N$2:$N$865,Calc_Actuals!$I$2:$I$865,$A23,Calc_Actuals!$J$2:$J$865,VALUE(LEFT(F$17,4)),Calc_Actuals!$K$2:$K$865,VALUE(RIGHT(F$17,2)),Calc_Actuals!$C$2:$C$865,"Actual") -> 171094.54 | G23: =SUMIFS(Calc_Actuals!$N$2:$N$865,Calc_Actuals!$I$2:$I$865,$A23,Calc_Actuals!$J$2:$J$865,VALUE(LEFT(G$17,4)),Calc_Actuals!$K$2:$K$865,VALUE(RIGHT(G$17,2)),Calc_Actuals!$C$2:$C$865,"Actual") -> 393967.81 | H23: =SUMIFS(Calc_Actuals!$N$2:$N$865,Calc_Actuals!$I$2:$I$865,$A23,Calc_Actuals!$J$2:$J$865,VALUE(LEFT(H$17,4)),Calc_Actuals!$K$2:$K$865,VALUE(RIGHT(H$17,2)),Calc_Actuals!$C$2:$C$865,"Actual") -> 394344.3 | I23: =SUMIFS(Calc_Actuals!$N$2:$N$865,Calc_Actuals!$I$2:$I$865,$A23,Calc_Actuals!$J$2:$J$865,VALUE(LEFT(I$17,4)),Calc_Actuals!$K$2:$K$865,VALUE(RIGHT(I$17,2)),Calc_Actuals!$C$2:$C$865,"Actual") -> 212444.11 | ... V23: =SUMIFS(Calc_Actuals!$N$2:$N$865,Calc_Actuals!$I$2:$I$865,$A23,Calc_Actuals!$J$2:$J$865,VALUE(LEFT(V$17,4)),Calc_Actuals!$K$2:$K$865,VALUE(RIGHT(V$17,2)),Calc_Actuals!$C$2:$C$865,"Actual") -> 285131.21 | W23: =SUM(B23:V23) -> 6363435.8
A24: Floor Cleaner | B24: =SUMIFS(Calc_Actuals!$N$2:$N$865,Calc_Actuals!$I$2:$I$865,$A24,Calc_Actuals!$J$2:$J$865,VALUE(LEFT(B$17,4)),Calc_Actuals!$K$2:$K$865,VALUE(RIGHT(B$17,2)),Calc_Actuals!$C$2:$C$865,"Actual") -> 246729.6 | C24: =SUMIFS(Calc_Actuals!$N$2:$N$865,Calc_Actuals!$I$2:$I$865,$A24,Calc_Actuals!$J$2:$J$865,VALUE(LEFT(C$17,4)),Calc_Actuals!$K$2:$K$865,VALUE(RIGHT(C$17,2)),Calc_Actuals!$C$2:$C$865,"Actual") -> 335197.24 | D24: =SUMIFS(Calc_Actuals!$N$2:$N$865,Calc_Actuals!$I$2:$I$865,$A24,Calc_Actuals!$J$2:$J$865,VALUE(LEFT(D$17,4)),Calc_Actuals!$K$2:$K$865,VALUE(RIGHT(D$17,2)),Calc_Actuals!$C$2:$C$865,"Actual") -> 205442.73 | E24: =SUMIFS(Calc_Actuals!$N$2:$N$865,Calc_Actuals!$I$2:$I$865,$A24,Calc_Actuals!$J$2:$J$865,VALUE(LEFT(E$17,4)),Calc_Actuals!$K$2:$K$865,VALUE(RIGHT(E$17,2)),Calc_Actuals!$C$2:$C$865,"Actual") -> 154142.05 | F24: =SUMIFS(Calc_Actuals!$N$2:$N$865,Calc_Actuals!$I$2:$I$865,$A24,Calc_Actuals!$J$2:$J$865,VALUE(LEFT(F$17,4)),Calc_Actuals!$K$2:$K$865,VALUE(RIGHT(F$17,2)),Calc_Actuals!$C$2:$C$865,"Actual") -> 209899.91 | G24: =SUMIFS(Calc_Actuals!$N$2:$N$865,Calc_Actuals!$I$2:$I$865,$A24,Calc_Actuals!$J$2:$J$865,VALUE(LEFT(G$17,4)),Calc_Actuals!$K$2:$K$865,VALUE(RIGHT(G$17,2)),Calc_Actuals!$C$2:$C$865,"Actual") -> 243495.66 | H24: =SUMIFS(Calc_Actuals!$N$2:$N$865,Calc_Actuals!$I$2:$I$865,$A24,Calc_Actuals!$J$2:$J$865,VALUE(LEFT(H$17,4)),Calc_Actuals!$K$2:$K$865,VALUE(RIGHT(H$17,2)),Calc_Actuals!$C$2:$C$865,"Actual") -> 237881.78 | I24: =SUMIFS(Calc_Actuals!$N$2:$N$865,Calc_Actuals!$I$2:$I$865,$A24,Calc_Actuals!$J$2:$J$865,VALUE(LEFT(I$17,4)),Calc_Actuals!$K$2:$K$865,VALUE(RIGHT(I$17,2)),Calc_Actuals!$C$2:$C$865,"Actual") -> 240040.64 | ... V24: =SUMIFS(Calc_Actuals!$N$2:$N$865,Calc_Actuals!$I$2:$I$865,$A24,Calc_Actuals!$J$2:$J$865,VALUE(LEFT(V$17,4)),Calc_Actuals!$K$2:$K$865,VALUE(RIGHT(V$17,2)),Calc_Actuals!$C$2:$C$865,"Actual") -> 147811.88 | W24: =SUM(B24:V24) -> 4633109.2
A25: Body Lotion | B25: =SUMIFS(Calc_Actuals!$N$2:$N$865,Calc_Actuals!$I$2:$I$865,$A25,Calc_Actuals!$J$2:$J$865,VALUE(LEFT(B$17,4)),Calc_Actuals!$K$2:$K$865,VALUE(RIGHT(B$17,2)),Calc_Actuals!$C$2:$C$865,"Actual") -> 536565.81 | C25: =SUMIFS(Calc_Actuals!$N$2:$N$865,Calc_Actuals!$I$2:$I$865,$A25,Calc_Actuals!$J$2:$J$865,VALUE(LEFT(C$17,4)),Calc_Actuals!$K$2:$K$865,VALUE(RIGHT(C$17,2)),Calc_Actuals!$C$2:$C$865,"Actual") -> 472893.8 | D25: =SUMIFS(Calc_Actuals!$N$2:$N$865,Calc_Actuals!$I$2:$I$865,$A25,Calc_Actuals!$J$2:$J$865,VALUE(LEFT(D$17,4)),Calc_Actuals!$K$2:$K$865,VALUE(RIGHT(D$17,2)),Calc_Actuals!$C$2:$C$865,"Actual") -> 462425.65 | E25: =SUMIFS(Calc_Actuals!$N$2:$N$865,Calc_Actuals!$I$2:$I$865,$A25,Calc_Actuals!$J$2:$J$865,VALUE(LEFT(E$17,4)),Calc_Actuals!$K$2:$K$865,VALUE(RIGHT(E$17,2)),Calc_Actuals!$C$2:$C$865,"Actual") -> 453676.8 | F25: =SUMIFS(Calc_Actuals!$N$2:$N$865,Calc_Actuals!$I$2:$I$865,$A25,Calc_Actuals!$J$2:$J$865,VALUE(LEFT(F$17,4)),Calc_Actuals!$K$2:$K$865,VALUE(RIGHT(F$17,2)),Calc_Actuals!$C$2:$C$865,"Actual") -> 298399.16 | G25: =SUMIFS(Calc_Actuals!$N$2:$N$865,Calc_Actuals!$I$2:$I$865,$A25,Calc_Actuals!$J$2:$J$865,VALUE(LEFT(G$17,4)),Calc_Actuals!$K$2:$K$865,VALUE(RIGHT(G$17,2)),Calc_Actuals!$C$2:$C$865,"Actual") -> 326192.49 | H25: =SUMIFS(Calc_Actuals!$N$2:$N$865,Calc_Actuals!$I$2:$I$865,$A25,Calc_Actuals!$J$2:$J$865,VALUE(LEFT(H$17,4)),Calc_Actuals!$K$2:$K$865,VALUE(RIGHT(H$17,2)),Calc_Actuals!$C$2:$C$865,"Actual") -> 449164.68 | I25: =SUMIFS(Calc_Actuals!$N$2:$N$865,Calc_Actuals!$I$2:$I$865,$A25,Calc_Actuals!$J$2:$J$865,VALUE(LEFT(I$17,4)),Calc_Actuals!$K$2:$K$865,VALUE(RIGHT(I$17,2)),Calc_Actuals!$C$2:$C$865,"Actual") -> 517193.67 | ... V25: =SUMIFS(Calc_Actuals!$N$2:$N$865,Calc_Actuals!$I$2:$I$865,$A25,Calc_Actuals!$J$2:$J$865,VALUE(LEFT(V$17,4)),Calc_Actuals!$K$2:$K$865,VALUE(RIGHT(V$17,2)),Calc_Actuals!$C$2:$C$865,"Actual") -> 278891.26 | W25: =SUM(B25:V25) -> 7974993.5
A26: Total | B26: =SUM(B18:B25) -> 2235970.6 | C26: =SUM(C18:C25) -> 2186134.6 | D26: =SUM(D18:D25) -> 1892456.3 | E26: =SUM(E18:E25) -> 2046367.5 | F26: =SUM(F18:F25) -> 1854769 | G26: =SUM(G18:G25) -> 2022308.5 | H26: =SUM(H18:H25) -> 2118994.9 | I26: =SUM(I18:I25) -> 2077890.7 | ... W26: =SUM(W18:W25) -> 42593025
A49: Category roll-up (actuals)
A50: Category | C50: Net Revenue (INR) | D50: COGS (INR) | E50: Gross Profit (INR) | F50: GP % | G50: Revenue share
A51: Foods | C51: =SUMIFS(Calc_Actuals!$N$2:$N$865,Calc_Actuals!$H$2:$H$865,$A51,Calc_Actuals!$C$2:$C$865,"Actual") -> 9062451.8 | D51: =SUMIFS(Calc_Actuals!$O$2:$O$865,Calc_Actuals!$H$2:$H$865,$A51,Calc_Actuals!$C$2:$C$865,"Actual") -> 5942091.2 | E51: =C51-D51 -> 3120360.6 | F51: =IF(C51=0,"n/a",E51/C51) -> 0.34431748 | G51: =C51/C$54 -> 0.21276845
A52: Home Care | C52: =SUMIFS(Calc_Actuals!$N$2:$N$865,Calc_Actuals!$H$2:$H$865,$A52,Calc_Actuals!$C$2:$C$865,"Actual") -> 13679821 | D52: =SUMIFS(Calc_Actuals!$O$2:$O$865,Calc_Actuals!$H$2:$H$865,$A52,Calc_Actuals!$C$2:$C$865,"Actual") -> 8737405.2 | E52: =C52-D52 -> 4942416.2 | F52: =IF(C52=0,"n/a",E52/C52) -> 0.36129245 | G52: =C52/C$54 -> 0.32117515
A53: Personal Care | C53: =SUMIFS(Calc_Actuals!$N$2:$N$865,Calc_Actuals!$H$2:$H$865,$A53,Calc_Actuals!$C$2:$C$865,"Actual") -> 19850752 | D53: =SUMIFS(Calc_Actuals!$O$2:$O$865,Calc_Actuals!$H$2:$H$865,$A53,Calc_Actuals!$C$2:$C$865,"Actual") -> 12701099 | E53: =C53-D53 -> 7149653.3 | F53: =IF(C53=0,"n/a",E53/C53) -> 0.3601704 | G53: =C53/C$54 -> 0.4660564
A54: Total | C54: =SUM(C51:C53) -> 42593025 | D54: =SUM(D51:D53) -> 27380595 | E54: =SUM(E51:E53) -> 15212430 | F54: =E54/C54 -> 0.35715777 | G54: =SUM(G51:G53) -> 1

Sheet Budget_vs_Actual_v2
A1: ILLUSTRATIVE ONLY - Variance vs SYNTHETIC calibrated budget v2 (unapproved)
A2: In-scope Region x Category cells only. The original Sales_Budget is not used here. Actuals are the same actual-only figures as Monthly_MIS. See Budget_Integrity for why.
A4: Month | B4: v2 Budget Revenue | C4: Actual Revenue | D4: Variance (INR) | E4: Variance % | F4: v2 Budget GP | G4: Actual GP | H4: GP Variance (INR) | I4: Basis
A5: 2025-01 | B5: =SUMIFS(Budget_v2_Synthetic!$J$13:$J$300,Budget_v2_Synthetic!$G$13:$G$300,VALUE(LEFT($A5,4)),Budget_v2_Synthetic!$O$13:$O$300,VALUE(RIGHT($A5,2)),Budget_v2_Synthetic!$H$13:$H$300,1) -> 2041587.6 | C5: =SUMIFS(Budget_v2_Synthetic!$M$13:$M$300,Budget_v2_Synthetic!$G$13:$G$300,VALUE(LEFT($A5,4)),Budget_v2_Synthetic!$O$13:$O$300,VALUE(RIGHT($A5,2)),Budget_v2_Synthetic!$H$13:$H$300,1) -> 2235970.6 | D5: =C5-B5 -> 194383.03 | E5: =IF(B5=0,"n/a",D5/B5) -> 0.095211702 | F5: =SUMIFS(Budget_v2_Synthetic!$L$13:$L$300,Budget_v2_Synthetic!$G$13:$G$300,VALUE(LEFT($A5,4)),Budget_v2_Synthetic!$O$13:$O$300,VALUE(RIGHT($A5,2)),Budget_v2_Synthetic!$H$13:$H$300,1) -> 775803.29 | G5: =SUMIFS(Budget_v2_Synthetic!$N$13:$N$300,Budget_v2_Synthetic!$G$13:$G$300,VALUE(LEFT($A5,4)),Budget_v2_Synthetic!$O$13:$O$300,VALUE(RIGHT($A5,2)),Budget_v2_Synthetic!$H$13:$H$300,1) -> 785381.64 | H5: =G5-F5 -> 9578.345 | I5: =IF(VALUE(LEFT(A5,4))=Budget_v2_Synthetic!$B$4,"Calibration year (circular)","Out-of-sample") -> Calibration year (circular)
A6: 2025-02 | B6: =SUMIFS(Budget_v2_Synthetic!$J$13:$J$300,Budget_v2_Synthetic!$G$13:$G$300,VALUE(LEFT($A6,4)),Budget_v2_Synthetic!$O$13:$O$300,VALUE(RIGHT($A6,2)),Budget_v2_Synthetic!$H$13:$H$300,1) -> 2041587.6 | C6: =SUMIFS(Budget_v2_Synthetic!$M$13:$M$300,Budget_v2_Synthetic!$G$13:$G$300,VALUE(LEFT($A6,4)),Budget_v2_Synthetic!$O$13:$O$300,VALUE(RIGHT($A6,2)),Budget_v2_Synthetic!$H$13:$H$300,1) -> 2186134.6 | D6: =C6-B6 -> 144546.95 | E6: =IF(B6=0,"n/a",D6/B6) -> 0.070801248 | F6: =SUMIFS(Budget_v2_Synthetic!$L$13:$L$300,Budget_v2_Synthetic!$G$13:$G$300,VALUE(LEFT($A6,4)),Budget_v2_Synthetic!$O$13:$O$300,VALUE(RIGHT($A6,2)),Budget_v2_Synthetic!$H$13:$H$300,1) -> 775803.29 | G6: =SUMIFS(Budget_v2_Synthetic!$N$13:$N$300,Budget_v2_Synthetic!$G$13:$G$300,VALUE(LEFT($A6,4)),Budget_v2_Synthetic!$O$13:$O$300,VALUE(RIGHT($A6,2)),Budget_v2_Synthetic!$H$13:$H$300,1) -> 787006.33 | H6: =G6-F6 -> 11203.035 | I6: =IF(VALUE(LEFT(A6,4))=Budget_v2_Synthetic!$B$4,"Calibration year (circular)","Out-of-sample") -> Calibration year (circular)
A7: 2025-03 | B7: =SUMIFS(Budget_v2_Synthetic!$J$13:$J$300,Budget_v2_Synthetic!$G$13:$G$300,VALUE(LEFT($A7,4)),Budget_v2_Synthetic!$O$13:$O$300,VALUE(RIGHT($A7,2)),Budget_v2_Synthetic!$H$13:$H$300,1) -> 2041587.6 | C7: =SUMIFS(Budget_v2_Synthetic!$M$13:$M$300,Budget_v2_Synthetic!$G$13:$G$300,VALUE(LEFT($A7,4)),Budget_v2_Synthetic!$O$13:$O$300,VALUE(RIGHT($A7,2)),Budget_v2_Synthetic!$H$13:$H$300,1) -> 1892456.3 | D7: =C7-B7 -> -149131.31 | E7: =IF(B7=0,"n/a",D7/B7) -> -0.073046734 | F7: =SUMIFS(Budget_v2_Synthetic!$L$13:$L$300,Budget_v2_Synthetic!$G$13:$G$300,VALUE(LEFT($A7,4)),Budget_v2_Synthetic!$O$13:$O$300,VALUE(RIGHT($A7,2)),Budget_v2_Synthetic!$H$13:$H$300,1) -> 775803.29 | G7: =SUMIFS(Budget_v2_Synthetic!$N$13:$N$300,Budget_v2_Synthetic!$G$13:$G$300,VALUE(LEFT($A7,4)),Budget_v2_Synthetic!$O$13:$O$300,VALUE(RIGHT($A7,2)),Budget_v2_Synthetic!$H$13:$H$300,1) -> 658531.2 | H7: =G7-F7 -> -117272.09 | I7: =IF(VALUE(LEFT(A7,4))=Budget_v2_Synthetic!$B$4,"Calibration year (circular)","Out-of-sample") -> Calibration year (circular)
A8: 2025-04 | B8: =SUMIFS(Budget_v2_Synthetic!$J$13:$J$300,Budget_v2_Synthetic!$G$13:$G$300,VALUE(LEFT($A8,4)),Budget_v2_Synthetic!$O$13:$O$300,VALUE(RIGHT($A8,2)),Budget_v2_Synthetic!$H$13:$H$300,1) -> 2041587.6 | C8: =SUMIFS(Budget_v2_Synthetic!$M$13:$M$300,Budget_v2_Synthetic!$G$13:$G$300,VALUE(LEFT($A8,4)),Budget_v2_Synthetic!$O$13:$O$300,VALUE(RIGHT($A8,2)),Budget_v2_Synthetic!$H$13:$H$300,1) -> 2046367.5 | D8: =C8-B8 -> 4779.8817 | E8: =IF(B8=0,"n/a",D8/B8) -> 0.0023412572 | F8: =SUMIFS(Budget_v2_Synthetic!$L$13:$L$300,Budget_v2_Synthetic!$G$13:$G$300,VALUE(LEFT($A8,4)),Budget_v2_Synthetic!$O$13:$O$300,VALUE(RIGHT($A8,2)),Budget_v2_Synthetic!$H$13:$H$300,1) -> 775803.29 | G8: =SUMIFS(Budget_v2_Synthetic!$N$13:$N$300,Budget_v2_Synthetic!$G$13:$G$300,VALUE(LEFT($A8,4)),Budget_v2_Synthetic!$O$13:$O$300,VALUE(RIGHT($A8,2)),Budget_v2_Synthetic!$H$13:$H$300,1) -> 741588.7 | H8: =G8-F8 -> -34214.595 | I8: =IF(VALUE(LEFT(A8,4))=Budget_v2_Synthetic!$B$4,"Calibration year (circular)","Out-of-sample") -> Calibration year (circular)
A9: 2025-05 | B9: =SUMIFS(Budget_v2_Synthetic!$J$13:$J$300,Budget_v2_Synthetic!$G$13:$G$300,VALUE(LEFT($A9,4)),Budget_v2_Synthetic!$O$13:$O$300,VALUE(RIGHT($A9,2)),Budget_v2_Synthetic!$H$13:$H$300,1) -> 2041587.6 | C9: =SUMIFS(Budget_v2_Synthetic!$M$13:$M$300,Budget_v2_Synthetic!$G$13:$G$300,VALUE(LEFT($A9,4)),Budget_v2_Synthetic!$O$13:$O$300,VALUE(RIGHT($A9,2)),Budget_v2_Synthetic!$H$13:$H$300,1) -> 1854769 | D9: =C9-B9 -> -186818.62 | E9: =IF(B9=0,"n/a",D9/B9) -> -0.09150654 | F9: =SUMIFS(Budget_v2_Synthetic!$L$13:$L$300,Budget_v2_Synthetic!$G$13:$G$300,VALUE(LEFT($A9,4)),Budget_v2_Synthetic!$O$13:$O$300,VALUE(RIGHT($A9,2)),Budget_v2_Synthetic!$H$13:$H$300,1) -> 775803.29 | G9: =SUMIFS(Budget_v2_Synthetic!$N$13:$N$300,Budget_v2_Synthetic!$G$13:$G$300,VALUE(LEFT($A9,4)),Budget_v2_Synthetic!$O$13:$O$300,VALUE(RIGHT($A9,2)),Budget_v2_Synthetic!$H$13:$H$300,1) -> 678309.89 | H9: =G9-F9 -> -97493.405 | I9: =IF(VALUE(LEFT(A9,4))=Budget_v2_Synthetic!$B$4,"Calibration year (circular)","Out-of-sample") -> Calibration year (circular)
A10: 2025-06 | B10: =SUMIFS(Budget_v2_Synthetic!$J$13:$J$300,Budget_v2_Synthetic!$G$13:$G$300,VALUE(LEFT($A10,4)),Budget_v2_Synthetic!$O$13:$O$300,VALUE(RIGHT($A10,2)),Budget_v2_Synthetic!$H$13:$H$300,1) -> 2041587.6 | C10: =SUMIFS(Budget_v2_Synthetic!$M$13:$M$300,Budget_v2_Synthetic!$G$13:$G$300,VALUE(LEFT($A10,4)),Budget_v2_Synthetic!$O$13:$O$300,VALUE(RIGHT($A10,2)),Budget_v2_Synthetic!$H$13:$H$300,1) -> 2022308.5 | D10: =C10-B10 -> -19279.138 | E10: =IF(B10=0,"n/a",D10/B10) -> -0.0094432089 | F10: =SUMIFS(Budget_v2_Synthetic!$L$13:$L$300,Budget_v2_Synthetic!$G$13:$G$300,VALUE(LEFT($A10,4)),Budget_v2_Synthetic!$O$13:$O$300,VALUE(RIGHT($A10,2)),Budget_v2_Synthetic!$H$13:$H$300,1) -> 775803.29 | G10: =SUMIFS(Budget_v2_Synthetic!$N$13:$N$300,Budget_v2_Synthetic!$G$13:$G$300,VALUE(LEFT($A10,4)),Budget_v2_Synthetic!$O$13:$O$300,VALUE(RIGHT($A10,2)),Budget_v2_Synthetic!$H$13:$H$300,1) -> 714708.53 | H10: =G10-F10 -> -61094.765 | I10: =IF(VALUE(LEFT(A10,4))=Budget_v2_Synthetic!$B$4,"Calibration year (circular)","Out-of-sample") -> Calibration year (circular)
A11: 2025-07 | B11: =SUMIFS(Budget_v2_Synthetic!$J$13:$J$300,Budget_v2_Synthetic!$G$13:$G$300,VALUE(LEFT($A11,4)),Budget_v2_Synthetic!$O$13:$O$300,VALUE(RIGHT($A11,2)),Budget_v2_Synthetic!$H$13:$H$300,1) -> 2041587.6 | C11: =SUMIFS(Budget_v2_Synthetic!$M$13:$M$300,Budget_v2_Synthetic!$G$13:$G$300,VALUE(LEFT($A11,4)),Budget_v2_Synthetic!$O$13:$O$300,VALUE(RIGHT($A11,2)),Budget_v2_Synthetic!$H$13:$H$300,1) -> 2118994.9 | D11: =C11-B11 -> 77407.312 | E11: =IF(B11=0,"n/a",D11/B11) -> 0.037915253 | F11: =SUMIFS(Budget_v2_Synthetic!$L$13:$L$300,Budget_v2_Synthetic!$G$13:$G$300,VALUE(LEFT($A11,4)),Budget_v2_Synthetic!$O$13:$O$300,VALUE(RIGHT($A11,2)),Budget_v2_Synthetic!$H$13:$H$300,1) -> 775803.29 | G11: =SUMIFS(Budget_v2_Synthetic!$N$13:$N$300,Budget_v2_Synthetic!$G$13:$G$300,VALUE(LEFT($A11,4)),Budget_v2_Synthetic!$O$13:$O$300,VALUE(RIGHT($A11,2)),Budget_v2_Synthetic!$H$13:$H$300,1) -> 759360.9 | H11: =G11-F11 -> -16442.395 | I11: =IF(VALUE(LEFT(A11,4))=Budget_v2_Synthetic!$B$4,"Calibration year (circular)","Out-of-sample") -> Calibration year (circular)
A12: 2025-08 | B12: =SUMIFS(Budget_v2_Synthetic!$J$13:$J$300,Budget_v2_Synthetic!$G$13:$G$300,VALUE(LEFT($A12,4)),Budget_v2_Synthetic!$O$13:$O$300,VALUE(RIGHT($A12,2)),Budget_v2_Synthetic!$H$13:$H$300,1) -> 2041587.6 | C12: =SUMIFS(Budget_v2_Synthetic!$M$13:$M$300,Budget_v2_Synthetic!$G$13:$G$300,VALUE(LEFT($A12,4)),Budget_v2_Synthetic!$O$13:$O$300,VALUE(RIGHT($A12,2)),Budget_v2_Synthetic!$H$13:$H$300,1) -> 2077890.7 | D12: =C12-B12 -> 36303.102 | E12: =IF(B12=0,"n/a",D12/B12) -> 0.017781799 | F12: =SUMIFS(Budget_v2_Synthetic!$L$13:$L$300,Budget_v2_Synthetic!$G$13:$G$300,VALUE(LEFT($A12,4)),Budget_v2_Synthetic!$O$13:$O$300,VALUE(RIGHT($A12,2)),Budget_v2_Synthetic!$H$13:$H$300,1) -> 775803.29 | G12: =SUMIFS(Budget_v2_Synthetic!$N$13:$N$300,Budget_v2_Synthetic!$G$13:$G$300,VALUE(LEFT($A12,4)),Budget_v2_Synthetic!$O$13:$O$300,VALUE(RIGHT($A12,2)),Budget_v2_Synthetic!$H$13:$H$300,1) -> 747687.24 | H12: =G12-F12 -> -28116.055 | I12: =IF(VALUE(LEFT(A12,4))=Budget_v2_Synthetic!$B$4,"Calibration year (circular)","Out-of-sample") -> Calibration year (circular)
A13: 2025-09 | B13: =SUMIFS(Budget_v2_Synthetic!$J$13:$J$300,Budget_v2_Synthetic!$G$13:$G$300,VALUE(LEFT($A13,4)),Budget_v2_Synthetic!$O$13:$O$300,VALUE(RIGHT($A13,2)),Budget_v2_Synthetic!$H$13:$H$300,1) -> 2041587.6 | C13: =SUMIFS(Budget_v2_Synthetic!$M$13:$M$300,Budget_v2_Synthetic!$G$13:$G$300,VALUE(LEFT($A13,4)),Budget_v2_Synthetic!$O$13:$O$300,VALUE(RIGHT($A13,2)),Budget_v2_Synthetic!$H$13:$H$300,1) -> 1987738.3 | D13: =C13-B13 -> -53849.278 | E13: =IF(B13=0,"n/a",D13/B13) -> -0.026376178 | F13: =SUMIFS(Budget_v2_Synthetic!$L$13:$L$300,Budget_v2_Synthetic!$G$13:$G$300,VALUE(LEFT($A13,4)),Budget_v2_Synthetic!$O$13:$O$300,VALUE(RIGHT($A13,2)),Budget_v2_Synthetic!$H$13:$H$300,1) -> 775803.29 | G13: =SUMIFS(Budget_v2_Synthetic!$N$13:$N$300,Budget_v2_Synthetic!$G$13:$G$300,VALUE(LEFT($A13,4)),Budget_v2_Synthetic!$O$13:$O$300,VALUE(RIGHT($A13,2)),Budget_v2_Synthetic!$H$13:$H$300,1) -> 726599.29 | H13: =G13-F13 -> -49204.005 | I13: =IF(VALUE(LEFT(A13,4))=Budget_v2_Synthetic!$B$4,"Calibration year (circular)","Out-of-sample") -> Calibration year (circular)
A14: 2025-10 | B14: =SUMIFS(Budget_v2_Synthetic!$J$13:$J$300,Budget_v2_Synthetic!$G$13:$G$300,VALUE(LEFT($A14,4)),Budget_v2_Synthetic!$O$13:$O$300,VALUE(RIGHT($A14,2)),Budget_v2_Synthetic!$H$13:$H$300,1) -> 2041587.6 | C14: =SUMIFS(Budget_v2_Synthetic!$M$13:$M$300,Budget_v2_Synthetic!$G$13:$G$300,VALUE(LEFT($A14,4)),Budget_v2_Synthetic!$O$13:$O$300,VALUE(RIGHT($A14,2)),Budget_v2_Synthetic!$H$13:$H$300,1) -> 1869248.2 | D14: =C14-B14 -> -172339.45 | E14: =IF(B14=0,"n/a",D14/B14) -> -0.084414427 | F14: =SUMIFS(Budget_v2_Synthetic!$L$13:$L$300,Budget_v2_Synthetic!$G$13:$G$300,VALUE(LEFT($A14,4)),Budget_v2_Synthetic!$O$13:$O$300,VALUE(RIGHT($A14,2)),Budget_v2_Synthetic!$H$13:$H$300,1) -> 775803.29 | G14: =SUMIFS(Budget_v2_Synthetic!$N$13:$N$300,Budget_v2_Synthetic!$G$13:$G$300,VALUE(LEFT($A14,4)),Budget_v2_Synthetic!$O$13:$O$300,VALUE(RIGHT($A14,2)),Budget_v2_Synthetic!$H$13:$H$300,1) -> 663285.56 | H14: =G14-F14 -> -112517.73 | I14: =IF(VALUE(LEFT(A14,4))=Budget_v2_Synthetic!$B$4,"Calibration year (circular)","Out-of-sample") -> Calibration year (circular)
A15: 2025-11 | B15: =SUMIFS(Budget_v2_Synthetic!$J$13:$J$300,Budget_v2_Synthetic!$G$13:$G$300,VALUE(LEFT($A15,4)),Budget_v2_Synthetic!$O$13:$O$300,VALUE(RIGHT($A15,2)),Budget_v2_Synthetic!$H$13:$H$300,1) -> 2041587.6 | C15: =SUMIFS(Budget_v2_Synthetic!$M$13:$M$300,Budget_v2_Synthetic!$G$13:$G$300,VALUE(LEFT($A15,4)),Budget_v2_Synthetic!$O$13:$O$300,VALUE(RIGHT($A15,2)),Budget_v2_Synthetic!$H$13:$H$300,1) -> 2011362.9 | D15: =C15-B15 -> -30224.698 | E15: =IF(B15=0,"n/a",D15/B15) -> -0.014804507 | F15: =SUMIFS(Budget_v2_Synthetic!$L$13:$L$300,Budget_v2_Synthetic!$G$13:$G$300,VALUE(LEFT($A15,4)),Budget_v2_Synthetic!$O$13:$O$300,VALUE(RIGHT($A15,2)),Budget_v2_Synthetic!$H$13:$H$300,1) -> 775803.29 | G15: =SUMIFS(Budget_v2_Synthetic!$N$13:$N$300,Budget_v2_Synthetic!$G$13:$G$300,VALUE(LEFT($A15,4)),Budget_v2_Synthetic!$O$13:$O$300,VALUE(RIGHT($A15,2)),Budget_v2_Synthetic!$H$13:$H$300,1) -> 699317.88 | H15: =G15-F15 -> -76485.415 | I15: =IF(VALUE(LEFT(A15,4))=Budget_v2_Synthetic!$B$4,"Calibration year (circular)","Out-of-sample") -> Calibration year (circular)
A16: 2025-12 | B16: =SUMIFS(Budget_v2_Synthetic!$J$13:$J$300,Budget_v2_Synthetic!$G$13:$G$300,VALUE(LEFT($A16,4)),Budget_v2_Synthetic!$O$13:$O$300,VALUE(RIGHT($A16,2)),Budget_v2_Synthetic!$H$13:$H$300,1) -> 2041587.6 | C16: =SUMIFS(Budget_v2_Synthetic!$M$13:$M$300,Budget_v2_Synthetic!$G$13:$G$300,VALUE(LEFT($A16,4)),Budget_v2_Synthetic!$O$13:$O$300,VALUE(RIGHT($A16,2)),Budget_v2_Synthetic!$H$13:$H$300,1) -> 2195809.8 | D16: =C16-B16 -> 154222.21 | E16: =IF(B16=0,"n/a",D16/B16) -> 0.075540335 | F16: =SUMIFS(Budget_v2_Synthetic!$L$13:$L$300,Budget_v2_Synthetic!$G$13:$G$300,VALUE(LEFT($A16,4)),Budget_v2_Synthetic!$O$13:$O$300,VALUE(RIGHT($A16,2)),Budget_v2_Synthetic!$H$13:$H$300,1) -> 775803.29 | G16: =SUMIFS(Budget_v2_Synthetic!$N$13:$N$300,Budget_v2_Synthetic!$G$13:$G$300,VALUE(LEFT($A16,4)),Budget_v2_Synthetic!$O$13:$O$300,VALUE(RIGHT($A16,2)),Budget_v2_Synthetic!$H$13:$H$300,1) -> 789221.75 | H16: =G16-F16 -> 13418.455 | I16: =IF(VALUE(LEFT(A16,4))=Budget_v2_Synthetic!$B$4,"Calibration year (circular)","Out-of-sample") -> Calibration year (circular)
... A25: 2026-09 | B25: =SUMIFS(Budget_v2_Synthetic!$J$13:$J$300,Budget_v2_Synthetic!$G$13:$G$300,VALUE(LEFT($A25,4)),Budget_v2_Synthetic!$O$13:$O$300,VALUE(RIGHT($A25,2)),Budget_v2_Synthetic!$H$13:$H$300,1) -> 2204914.6 | C25: =SUMIFS(Budget_v2_Synthetic!$M$13:$M$300,Budget_v2_Synthetic!$G$13:$G$300,VALUE(LEFT($A25,4)),Budget_v2_Synthetic!$O$13:$O$300,VALUE(RIGHT($A25,2)),Budget_v2_Synthetic!$H$13:$H$300,1) -> 1837789.4 | D25: =C25-B25 -> -367125.19 | E25: =IF(B25=0,"n/a",D25/B25) -> -0.16650313 | F25: =SUMIFS(Budget_v2_Synthetic!$L$13:$L$300,Budget_v2_Synthetic!$G$13:$G$300,VALUE(LEFT($A25,4)),Budget_v2_Synthetic!$O$13:$O$300,VALUE(RIGHT($A25,2)),Budget_v2_Synthetic!$H$13:$H$300,1) -> 837867.56 | G25: =SUMIFS(Budget_v2_Synthetic!$N$13:$N$300,Budget_v2_Synthetic!$G$13:$G$300,VALUE(LEFT($A25,4)),Budget_v2_Synthetic!$O$13:$O$300,VALUE(RIGHT($A25,2)),Budget_v2_Synthetic!$H$13:$H$300,1) -> 668945.26 | H25: =G25-F25 -> -168922.3 | I25: =IF(VALUE(LEFT(A25,4))=Budget_v2_Synthetic!$B$4,"Calibration year (circular)","Out-of-sample") -> Out-of-sample
A26: Total | B26: =SUM(B5:B25) -> 44343283 | C26: =SUM(C5:C25) -> 42593025 | D26: =C26-B26 -> -1750257.8 | E26: =IF(B26=0,"n/a",D26/B26) -> -0.03947064 | F26: =SUM(F5:F25) -> 16850448 | G26: =SUM(G5:G25) -> 15212430 | H26: =G26-F26 -> -1638017.5
A28: Period view
A29: Period | B29: v2 Budget Revenue | C29: Actual Revenue | D29: Variance (INR) | E29: Variance % | F29: Reading
A30: ="FY"&Budget_v2_Synthetic!B4&" (calibration year)" -> FY2025 (calibration year) | B30: =SUMIFS(Budget_v2_Synthetic!$J$13:$J$300,Budget_v2_Synthetic!$G$13:$G$300,Budget_v2_Synthetic!$B$4,Budget_v2_Synthetic!$H$13:$H$300,1) -> 24499051 | C30: =SUMIFS(Budget_v2_Synthetic!$M$13:$M$300,Budget_v2_Synthetic!$G$13:$G$300,Budget_v2_Synthetic!$B$4,Budget_v2_Synthetic!$H$13:$H$300,1) -> 24499051 | D30: =C30-B30 -> 0 | E30: =IF(B30=0,"n/a",D30/B30) -> 0 | F30: Variance ~0 by construction - not informative
A31: ="YTD "&Monthly_MIS!B5&" (out-of-sample)" -> YTD 2026 (out-of-sample) | B31: =SUMIFS(Budget_v2_Synthetic!$J$13:$J$300,Budget_v2_Synthetic!$G$13:$G$300,Monthly_MIS!$B$5,Budget_v2_Synthetic!$O$13:$O$300,"<="&Monthly_MIS!$B$6,Budget_v2_Synthetic!$I$13:$I$300,"Actual",Budget_v2_Synthetic!$H$13:$H$300,1) -> 19844232 | C31: =SUMIFS(Budget_v2_Synthetic!$M$13:$M$300,Budget_v2_Synthetic!$G$13:$G$300,Monthly_MIS!$B$5,Budget_v2_Synthetic!$O$13:$O$300,"<="&Monthly_MIS!$B$6,Budget_v2_Synthetic!$H$13:$H$300,1) -> 18093974 | D31: =C31-B31 -> -1750257.8 | E31: =IF(B31=0,"n/a",D31/B31) -> -0.088199826 | F31: Only meaningful comparison; still synthetic and unapproved
A34: ="YTD "&Monthly_MIS!B5&" by Region x Category" -> YTD 2026 by Region x Category
A35: Region | B35: Category | C35: In scope? | D35: YTD v2 Budget Revenue | E35: YTD Actual Revenue | F35: Variance (INR) | G35: Variance % | H35: Note
A36: East | B36: Foods | C36: =IF(COUNTIFS(Calc_Actuals!$F$2:$F$865,A36,Calc_Actuals!$H$2:$H$865,B36,Calc_Actuals!$C$2:$C$865,"Actual")>0,"Yes","No") -> Yes | D36: =SUMIFS(Budget_v2_Synthetic!$J$13:$J$300,Budget_v2_Synthetic!$B$13:$B$300,$A36,Budget_v2_Synthetic!$C$13:$C$300,$B36,Budget_v2_Synthetic!$G$13:$G$300,Monthly_MIS!$B$5,Budget_v2_Synthetic!$O$13:$O$300,"<="&Monthly_MIS!$B$6,Budget_v2_Synthetic!$I$13:$I$300,"Actual") -> 3346475.9 | E36: =SUMIFS(Budget_v2_Synthetic!$M$13:$M$300,Budget_v2_Synthetic!$B$13:$B$300,$A36,Budget_v2_Synthetic!$C$13:$C$300,$B36,Budget_v2_Synthetic!$G$13:$G$300,Monthly_MIS!$B$5,Budget_v2_Synthetic!$O$13:$O$300,"<="&Monthly_MIS!$B$6,Budget_v2_Synthetic!$I$13:$I$300,"Actual") -> 2928066.6 | F36: =IF(C36="Yes",E36-D36,"excluded") -> -418409.29 | G36: =IF(C36="Yes",IF(D36=0,"n/a",F36/D36),"excluded") -> -0.12502982 | H36: =IF(C36="Yes","","No actual sales for this cell in the source - budget excluded from variance")
A37: East | B37: Home Care | C37: =IF(COUNTIFS(Calc_Actuals!$F$2:$F$865,A37,Calc_Actuals!$H$2:$H$865,B37,Calc_Actuals!$C$2:$C$865,"Actual")>0,"Yes","No") -> Yes | D37: =SUMIFS(Budget_v2_Synthetic!$J$13:$J$300,Budget_v2_Synthetic!$B$13:$B$300,$A37,Budget_v2_Synthetic!$C$13:$C$300,$B37,Budget_v2_Synthetic!$G$13:$G$300,Monthly_MIS!$B$5,Budget_v2_Synthetic!$O$13:$O$300,"<="&Monthly_MIS!$B$6,Budget_v2_Synthetic!$I$13:$I$300,"Actual") -> 2976017.3 | E37: =SUMIFS(Budget_v2_Synthetic!$M$13:$M$300,Budget_v2_Synthetic!$B$13:$B$300,$A37,Budget_v2_Synthetic!$C$13:$C$300,$B37,Budget_v2_Synthetic!$G$13:$G$300,Monthly_MIS!$B$5,Budget_v2_Synthetic!$O$13:$O$300,"<="&Monthly_MIS!$B$6,Budget_v2_Synthetic!$I$13:$I$300,"Actual") -> 1565993.1 | F37: =IF(C37="Yes",E37-D37,"excluded") -> -1410024.2 | G37: =IF(C37="Yes",IF(D37=0,"n/a",F37/D37),"excluded") -> -0.47379571 | H37: =IF(C37="Yes","","No actual sales for this cell in the source - budget excluded from variance")
A38: East | B38: Personal Care | C38: =IF(COUNTIFS(Calc_Actuals!$F$2:$F$865,A38,Calc_Actuals!$H$2:$H$865,B38,Calc_Actuals!$C$2:$C$865,"Actual")>0,"Yes","No") -> No | D38: =SUMIFS(Budget_v2_Synthetic!$J$13:$J$300,Budget_v2_Synthetic!$B$13:$B$300,$A38,Budget_v2_Synthetic!$C$13:$C$300,$B38,Budget_v2_Synthetic!$G$13:$G$300,Monthly_MIS!$B$5,Budget_v2_Synthetic!$O$13:$O$300,"<="&Monthly_MIS!$B$6,Budget_v2_Synthetic!$I$13:$I$300,"Actual") -> 3161246.6 | E38: =SUMIFS(Budget_v2_Synthetic!$M$13:$M$300,Budget_v2_Synthetic!$B$13:$B$300,$A38,Budget_v2_Synthetic!$C$13:$C$300,$B38,Budget_v2_Synthetic!$G$13:$G$300,Monthly_MIS!$B$5,Budget_v2_Synthetic!$O$13:$O$300,"<="&Monthly_MIS!$B$6,Budget_v2_Synthetic!$I$13:$I$300,"Actual") -> 0 | F38: =IF(C38="Yes",E38-D38,"excluded") -> excluded | G38: =IF(C38="Yes",IF(D38=0,"n/a",F38/D38),"excluded") -> excluded | H38: =IF(C38="Yes","","No actual sales for this cell in the source - budget excluded from variance") -> No actual sales for this cell in the source - budget excluded from variance
A39: North | B39: Foods | C39: =IF(COUNTIFS(Calc_Actuals!$F$2:$F$865,A39,Calc_Actuals!$H$2:$H$865,B39,Calc_Actuals!$C$2:$C$865,"Actual")>0,"Yes","No") -> No | D39: =SUMIFS(Budget_v2_Synthetic!$J$13:$J$300,Budget_v2_Synthetic!$B$13:$B$300,$A39,Budget_v2_Synthetic!$C$13:$C$300,$B39,Budget_v2_Synthetic!$G$13:$G$300,Monthly_MIS!$B$5,Budget_v2_Synthetic!$O$13:$O$300,"<="&Monthly_MIS!$B$6,Budget_v2_Synthetic!$I$13:$I$300,"Actual") -> 2926622.8 | E39: =SUMIFS(Budget_v2_Synthetic!$M$13:$M$300,Budget_v2_Synthetic!$B$13:$B$300,$A39,Budget_v2_Synthetic!$C$13:$C$300,$B39,Budget_v2_Synthetic!$G$13:$G$300,Monthly_MIS!$B$5,Budget_v2_Synthetic!$O$13:$O$300,"<="&Monthly_MIS!$B$6,Budget_v2_Synthetic!$I$13:$I$300,"Actual") -> 0 | F39: =IF(C39="Yes",E39-D39,"excluded") -> excluded | G39: =IF(C39="Yes",IF(D39=0,"n/a",F39/D39),"excluded") -> excluded | H39: =IF(C39="Yes","","No actual sales for this cell in the source - budget excluded from variance") -> No actual sales for this cell in the source - budget excluded from variance
A40: North | B40: Home Care | C40: =IF(COUNTIFS(Calc_Actuals!$F$2:$F$865,A40,Calc_Actuals!$H$2:$H$865,B40,Calc_Actuals!$C$2:$C$865,"Actual")>0,"Yes","No") -> No | D40: =SUMIFS(Budget_v2_Synthetic!$J$13:$J$300,Budget_v2_Synthetic!$B$13:$B$300,$A40,Budget_v2_Synthetic!$C$13:$C$300,$B40,Budget_v2_Synthetic!$G$13:$G$300,Monthly_MIS!$B$5,Budget_v2_Synthetic!$O$13:$O$300,"<="&Monthly_MIS!$B$6,Budget_v2_Synthetic!$I$13:$I$300,"Actual") -> 2556164.3 | E40: =SUMIFS(Budget_v2_Synthetic!$M$13:$M$300,Budget_v2_Synthetic!$B$13:$B$300,$A40,Budget_v2_Synthetic!$C$13:$C$300,$B40,Budget_v2_Synthetic!$G$13:$G$300,Monthly_MIS!$B$5,Budget_v2_Synthetic!$O$13:$O$300,"<="&Monthly_MIS!$B$6,Budget_v2_Synthetic!$I$13:$I$300,"Actual") -> 0 | F40: =IF(C40="Yes",E40-D40,"excluded") -> excluded | G40: =IF(C40="Yes",IF(D40=0,"n/a",F40/D40),"excluded") -> excluded | H40: =IF(C40="Yes","","No actual sales for this cell in the source - budget excluded from variance") -> No actual sales for this cell in the source - budget excluded from variance
A41: North | B41: Personal Care | C41: =IF(COUNTIFS(Calc_Actuals!$F$2:$F$865,A41,Calc_Actuals!$H$2:$H$865,B41,Calc_Actuals!$C$2:$C$865,"Actual")>0,"Yes","No") -> Yes | D41: =SUMIFS(Budget_v2_Synthetic!$J$13:$J$300,Budget_v2_Synthetic!$B$13:$B$300,$A41,Budget_v2_Synthetic!$C$13:$C$300,$B41,Budget_v2_Synthetic!$G$13:$G$300,Monthly_MIS!$B$5,Budget_v2_Synthetic!$O$13:$O$300,"<="&Monthly_MIS!$B$6,Budget_v2_Synthetic!$I$13:$I$300,"Actual") -> 2741393.5 | E41: =SUMIFS(Budget_v2_Synthetic!$M$13:$M$300,Budget_v2_Synthetic!$B$13:$B$300,$A41,Budget_v2_Synthetic!$C$13:$C$300,$B41,Budget_v2_Synthetic!$G$13:$G$300,Monthly_MIS!$B$5,Budget_v2_Synthetic!$O$13:$O$300,"<="&Monthly_MIS!$B$6,Budget_v2_Synthetic!$I$13:$I$300,"Actual") -> 4914886 | F41: =IF(C41="Yes",E41-D41,"excluded") -> 2173492.4 | G41: =IF(C41="Yes",IF(D41=0,"n/a",F41/D41),"excluded") -> 0.79284218 | H41: =IF(C41="Yes","","No actual sales for this cell in the source - budget excluded from variance")
A42: South | B42: Foods | C42: =IF(COUNTIFS(Calc_Actuals!$F$2:$F$865,A42,Calc_Actuals!$H$2:$H$865,B42,Calc_Actuals!$C$2:$C$865,"Actual")>0,"Yes","No") -> Yes | D42: =SUMIFS(Budget_v2_Synthetic!$J$13:$J$300,Budget_v2_Synthetic!$B$13:$B$300,$A42,Budget_v2_Synthetic!$C$13:$C$300,$B42,Budget_v2_Synthetic!$G$13:$G$300,Monthly_MIS!$B$5,Budget_v2_Synthetic!$O$13:$O$300,"<="&Monthly_MIS!$B$6,Budget_v2_Synthetic!$I$13:$I$300,"Actual") -> 2716696.3 | E42: =SUMIFS(Budget_v2_Synthetic!$M$13:$M$300,Budget_v2_Synthetic!$B$13:$B$300,$A42,Budget_v2_Synthetic!$C$13:$C$300,$B42,Budget_v2_Synthetic!$G$13:$G$300,Monthly_MIS!$B$5,Budget_v2_Synthetic!$O$13:$O$300,"<="&Monthly_MIS!$B$6,Budget_v2_Synthetic!$I$13:$I$300,"Actual") -> 1194511.5 | F42: =IF(C42="Yes",E42-D42,"excluded") -> -1522184.8 | G42: =IF(C42="Yes",IF(D42=0,"n/a",F42/D42),"excluded") -> -0.56030732 | H42: =IF(C42="Yes","","No actual sales for this cell in the source - budget excluded from variance")
A43: South | B43: Home Care | C43: =IF(COUNTIFS(Calc_Actuals!$F$2:$F$865,A43,Calc_Actuals!$H$2:$H$865,B43,Calc_Actuals!$C$2:$C$865,"Actual")>0,"Yes","No") -> Yes | D43: =SUMIFS(Budget_v2_Synthetic!$J$13:$J$300,Budget_v2_Synthetic!$B$13:$B$300,$A43,Budget_v2_Synthetic!$C$13:$C$300,$B43,Budget_v2_Synthetic!$G$13:$G$300,Monthly_MIS!$B$5,Budget_v2_Synthetic!$O$13:$O$300,"<="&Monthly_MIS!$B$6,Budget_v2_Synthetic!$I$13:$I$300,"Actual") -> 2346237.7 | E43: =SUMIFS(Budget_v2_Synthetic!$M$13:$M$300,Budget_v2_Synthetic!$B$13:$B$300,$A43,Budget_v2_Synthetic!$C$13:$C$300,$B43,Budget_v2_Synthetic!$G$13:$G$300,Monthly_MIS!$B$5,Budget_v2_Synthetic!$O$13:$O$300,"<="&Monthly_MIS!$B$6,Budget_v2_Synthetic!$I$13:$I$300,"Actual") -> 2199515.3 | F43: =IF(C43="Yes",E43-D43,"excluded") -> -146722.38 | G43: =IF(C43="Yes",IF(D43=0,"n/a",F43/D43),"excluded") -> -0.062535172 | H43: =IF(C43="Yes","","No actual sales for this cell in the source - budget excluded from variance")
A44: South | B44: Personal Care | C44: =IF(COUNTIFS(Calc_Actuals!$F$2:$F$865,A44,Calc_Actuals!$H$2:$H$865,B44,Calc_Actuals!$C$2:$C$865,"Actual")>0,"Yes","No") -> No | D44: =SUMIFS(Budget_v2_Synthetic!$J$13:$J$300,Budget_v2_Synthetic!$B$13:$B$300,$A44,Budget_v2_Synthetic!$C$13:$C$300,$B44,Budget_v2_Synthetic!$G$13:$G$300,Monthly_MIS!$B$5,Budget_v2_Synthetic!$O$13:$O$300,"<="&Monthly_MIS!$B$6,Budget_v2_Synthetic!$I$13:$I$300,"Actual") -> 2531467 | E44: =SUMIFS(Budget_v2_Synthetic!$M$13:$M$300,Budget_v2_Synthetic!$B$13:$B$300,$A44,Budget_v2_Synthetic!$C$13:$C$300,$B44,Budget_v2_Synthetic!$G$13:$G$300,Monthly_MIS!$B$5,Budget_v2_Synthetic!$O$13:$O$300,"<="&Monthly_MIS!$B$6,Budget_v2_Synthetic!$I$13:$I$300,"Actual") -> 0 | F44: =IF(C44="Yes",E44-D44,"excluded") -> excluded | G44: =IF(C44="Yes",IF(D44=0,"n/a",F44/D44),"excluded") -> excluded | H44: =IF(C44="Yes","","No actual sales for this cell in the source - budget excluded from variance") -> No actual sales for this cell in the source - budget excluded from variance
A45: West | B45: Foods | C45: =IF(COUNTIFS(Calc_Actuals!$F$2:$F$865,A45,Calc_Actuals!$H$2:$H$865,B45,Calc_Actuals!$C$2:$C$865,"Actual")>0,"Yes","No") -> No | D45: =SUMIFS(Budget_v2_Synthetic!$J$13:$J$300,Budget_v2_Synthetic!$B$13:$B$300,$A45,Budget_v2_Synthetic!$C$13:$C$300,$B45,Budget_v2_Synthetic!$G$13:$G$300,Monthly_MIS!$B$5,Budget_v2_Synthetic!$O$13:$O$300,"<="&Monthly_MIS!$B$6,Budget_v2_Synthetic!$I$13:$I$300,"Actual") -> 3136549.4 | E45: =SUMIFS(Budget_v2_Synthetic!$M$13:$M$300,Budget_v2_Synthetic!$B$13:$B$300,$A45,Budget_v2_Synthetic!$C$13:$C$300,$B45,Budget_v2_Synthetic!$G$13:$G$300,Monthly_MIS!$B$5,Budget_v2_Synthetic!$O$13:$O$300,"<="&Monthly_MIS!$B$6,Budget_v2_Synthetic!$I$13:$I$300,"Actual") -> 0 | F45: =IF(C45="Yes",E45-D45,"excluded") -> excluded | G45: =IF(C45="Yes",IF(D45=0,"n/a",F45/D45),"excluded") -> excluded | H45: =IF(C45="Yes","","No actual sales for this cell in the source - budget excluded from variance") -> No actual sales for this cell in the source - budget excluded from variance
A46: West | B46: Home Care | C46: =IF(COUNTIFS(Calc_Actuals!$F$2:$F$865,A46,Calc_Actuals!$H$2:$H$865,B46,Calc_Actuals!$C$2:$C$865,"Actual")>0,"Yes","No") -> Yes | D46: =SUMIFS(Budget_v2_Synthetic!$J$13:$J$300,Budget_v2_Synthetic!$B$13:$B$300,$A46,Budget_v2_Synthetic!$C$13:$C$300,$B46,Budget_v2_Synthetic!$G$13:$G$300,Monthly_MIS!$B$5,Budget_v2_Synthetic!$O$13:$O$300,"<="&Monthly_MIS!$B$6,Budget_v2_Synthetic!$I$13:$I$300,"Actual") -> 2766090.8 | E46: =SUMIFS(Budget_v2_Synthetic!$M$13:$M$300,Budget_v2_Synthetic!$B$13:$B$300,$A46,Budget_v2_Synthetic!$C$13:$C$300,$B46,Budget_v2_Synthetic!$G$13:$G$300,Monthly_MIS!$B$5,Budget_v2_Synthetic!$O$13:$O$300,"<="&Monthly_MIS!$B$6,Budget_v2_Synthetic!$I$13:$I$300,"Actual") -> 1978588.2 | F46: =IF(C46="Yes",E46-D46,"excluded") -> -787502.62 | G46: =IF(C46="Yes",IF(D46=0,"n/a",F46/D46),"excluded") -> -0.28469876 | H46: =IF(C46="Yes","","No actual sales for this cell in the source - budget excluded from variance")
A47: West | B47: Personal Care | C47: =IF(COUNTIFS(Calc_Actuals!$F$2:$F$865,A47,Calc_Actuals!$H$2:$H$865,B47,Calc_Actuals!$C$2:$C$865,"Actual")>0,"Yes","No") -> Yes | D47: =SUMIFS(Budget_v2_Synthetic!$J$13:$J$300,Budget_v2_Synthetic!$B$13:$B$300,$A47,Budget_v2_Synthetic!$C$13:$C$300,$B47,Budget_v2_Synthetic!$G$13:$G$300,Monthly_MIS!$B$5,Budget_v2_Synthetic!$O$13:$O$300,"<="&Monthly_MIS!$B$6,Budget_v2_Synthetic!$I$13:$I$300,"Actual") -> 2951320.1 | E47: =SUMIFS(Budget_v2_Synthetic!$M$13:$M$300,Budget_v2_Synthetic!$B$13:$B$300,$A47,Budget_v2_Synthetic!$C$13:$C$300,$B47,Budget_v2_Synthetic!$G$13:$G$300,Monthly_MIS!$B$5,Budget_v2_Synthetic!$O$13:$O$300,"<="&Monthly_MIS!$B$6,Budget_v2_Synthetic!$I$13:$I$300,"Actual") -> 3312413.2 | F47: =IF(C47="Yes",E47-D47,"excluded") -> 361093.15 | G47: =IF(C47="Yes",IF(D47=0,"n/a",F47/D47),"excluded") -> 0.12234971 | H47: =IF(C47="Yes","","No actual sales for this cell in the source - budget excluded from variance")
A48: In-scope total | D48: =SUMIFS(D36:D47,C36:C47,"Yes") -> 19844232 | E48: =SUMIFS(E36:E47,C36:C47,"Yes") -> 18093974 | F48: =E48-D48 -> -1750257.8 | G48: =IF(D48=0,"n/a",F48/D48) -> -0.088199826
A49: Excluded (no-sales cells) v2 budget | D49: =SUMIFS(D36:D47,C36:C47,"No") -> 14312050

Sheet Budget_Integrity
A1: Budget Integrity Review - Sales_Budget vs actuals
A2: Original Sales_Budget is untouched. Findings are computed from the source at build time (static text); live cross-check cells below recompute the headline ratios from the workbook.
A4: Live cross-check | B4: Value
A5: Budget / actual revenue - all 12 Region x Category cells | B5: =SUMPRODUCT(ISNUMBER(MATCH(Sales_Budget!$A$2:$A$289,Monthly_MIS!$A$9:$A$29,0))*Sales_Budget!$E$2:$E$289)/Monthly_MIS!E30 -> 7.0525068
A6: Budget / actual revenue - only cells that have sales | B6: =SUMPRODUCT(ISNUMBER(MATCH(Budget_v2_Synthetic!$A$13:$A$300,Monthly_MIS!$A$9:$A$29,0))*Budget_v2_Synthetic!$H$13:$H$300*Budget_v2_Synthetic!$D$13:$D$300)/Monthly_MIS!E30 -> 4.0973892
A7: Share of budget in cells with no sales | B7: =1-B6/B5 -> 0.41901663
A9: Test | B9: Method | C9: Finding | D9: Verdict
A10: Reporting periods | B10: Set of Sales_Budget months vs Calendar months | C10: Aligned: same 24 months | D10: NO PERIOD MISMATCH
A11: Aggregation level | B11: Budget rows per month; grain of each table | C11: Budget = Month x Region x Category (12 cells/month, no product or customer dimension). Transactions = invoice x product, aggregated here to the same grain. Product-level budget cannot be derived. | D11: COMPARABLE ONLY AT REGION x CATEGORY
A12: Units / currency / scale factor | B12: Budget/actual ratio for each in-scope Month x Region x Category cell | C12: 147 cell-months: ratio ranges 1.5x to 15.3x (median 4.6x, CV 51%). A uniform unit or currency conversion would give one constant ratio. | D12: RULED OUT as sole cause
A13: Periodicity (annual / quarterly figures) | B13: Budget divided by 12 or by 3 vs actual | C13: Budget/12 = 0.59x actual; Budget/3 = 2.35x. Neither is close to 1.0x. | D13: RULED OUT
A14: Business scope (coverage of Region x Category cells) | B14: Cells with budget but no actual sales in any month | C14: 5 of 12 cells have zero sales in the source (East/Personal Care, North/Foods, North/Home Care, South/Personal Care, West/Foods); they hold 41.9% of budget for the actual months. Cause in the data: each product is sold in one region only, so each region covers only 7/12 of the grid. Restricting budget to cells that have sales reduces the gap from 7.05x to 4.10x. | D14: CONFIRMED (explains part of the gap)
A15: Transaction coverage | B15: Invoices per month, customers invoiced, avg invoice value | C15: 36 invoices/month, avg INR 56,340; 48/48 customers invoiced. Budget of INR 14,304,171/month implies about 254 invoices/month at that average. Cannot tell whether the transaction table is a sample or the budget is overstated. | D15: UNRESOLVED
A16: Data-generation signature | B16: Fit of budget to a closed-form grid | C16: Budget is constant within each year (no seasonality), gross margin is exactly 38% in every row, 2nd-year uplift is exactly 1.08x for every cell, and revenue is additive in Region + Category effects (max residual INR 0.00). It is formula-generated, not built from transactions. | D16: CONFIRMED
A17: Margin and trend consistency | B17: Budget GP % vs actual GP %; budget growth vs actual growth | C17: Budget GP % 38.0% vs actual 35.7%. Budget steps up 8% in year 2; actual YTD revenue moved -1.8%. | D17: INFORMATION
A19: Root-cause conclusion
A20: PARTIALLY DEMONSTRATED. Demonstrated: (1) the budget is a closed-form formula grid with no link to the transaction table; (2) 42% of it sits in 5 Region x Category cells where the source has no sales at all, because each product is sold in one region only. Removing those cells narrows the gap from 7.1x to 4.1x. NOT demonstrated: the remaining 4.1x. It is not a constant factor (1.5x-15.3x), so it is not a unit/currency issue. Most likely the two tables were generated independently without calibration, but that cannot be proven from the data. Status: UNRESOLVED - business confirmation needed.
A22: Controlled correction proposed
A23: Budget_v2_Synthetic applies one uniform factor k = 0.2541 to the original budget (k = FY2025 actual revenue / original FY2025 budget in cells that have sales). Shape, 38% margin and year uplift are unchanged; no-sales cells are excluded from variance. It is SYNTHETIC and UNAPPROVED. It does not resolve the cause; it only makes a like-for-like illustration possible. Human decision needed: confirm the intended budget scale, or supply a corrected budget.

Sheet Budget_v2_Synthetic
A1: SYNTHETIC CALIBRATED BUDGET - VERSION v2 - NOT AN APPROVED BUDGET
A2: Separate version for illustration only. The original Sales_Budget sheet is carried unchanged and is never overwritten. Requires finance approval before any use in reporting.
A4: Calibration year (input) | B4: 2025 | C4: Latest fully-actual year before the current year; avoids calibrating to the period being measured.
A5: Actual net revenue in calibration year | B5: =SUMIFS(Calc_Actuals!$N$2:$N$865,Calc_Actuals!$J$2:$J$865,B4,Calc_Actuals!$C$2:$C$865,"Actual") -> 24499051 | C5: All actual rows (Calc_Actuals).
A6: Original budget revenue, calibration year, in-scope cells | B6: =SUMIFS($D$13:$D$300,$G$13:$G$300,B4,$H$13:$H$300,1) -> 96420000 | C6: In-scope = Region x Category cell that has at least one actual sale in the source.
A7: Calibration factor k = actual / original budget | B7: =IF(B6=0,0,B5/B6) -> 0.25408682 | C7: One uniform factor applied to every cell and month: preserves the original budget shape (regional/category pattern, year uplift, 38% margin).
A8: Original budget GP % (unchanged in v2) | B8: =SUM($F$13:$F$300)/SUM($D$13:$D$300) -> 0.38 | C8: Margin assumption is NOT calibrated to actuals.
A9: ASSUMPTIONS: (1) Business scale of the budget is unknown; v2 assumes the budget should be the same order of magnitude as FY2025 actuals. (2) Budget cells with no actual sales anywhere in the source are retained but flagged out-of-scope and excluded from variance. (3) FY2025 variance is ~0 by construction (circular); only periods after it are out-of-sample. (4) A single k does not fix the non-constant ratio between cells, so cell-level variances remain indicative only.
A12: Month | B12: Region | C12: Category | D12: Orig Revenue (INR) | E12: Orig COGS (INR) | F12: Orig GP (INR) | G12: Year | H12: In scope (1/0) | I12: Calendar status | J12: v2 Revenue (INR) | K12: v2 COGS (INR) | L12: v2 GP (INR) | M12: Actual Revenue (INR) | N12: Actual GP (INR) | O12: Month no. | P12: Key
A13: =Sales_Budget!A2 -> 2025-01 | B13: =Sales_Budget!B2 -> South | C13: =Sales_Budget!C2 -> Home Care | D13: =Sales_Budget!E2 -> 950000 | E13: =Sales_Budget!F2 -> 589000 | F13: =Sales_Budget!G2 -> 361000 | G13: =VALUE(LEFT(A13,4)) -> 2025 | H13: =IF(COUNTIFS(Calc_Actuals!$F$2:$F$865,B13,Calc_Actuals!$H$2:$H$865,C13,Calc_Actuals!$C$2:$C$865,"Actual")>0,1,0) -> 1 | I13: =IFERROR(INDEX(Calendar!$E$2:$E$25,MATCH(A13,Calendar!$A$2:$A$25,0)),"UNMATCHED") -> Actual | J13: =D13*$B$7 -> 241382.48 | K13: =E13*$B$7 -> 149657.14 | L13: =F13*$B$7 -> 91725.343 | M13: =IF(I13="Actual",SUMIFS(Calc_Actuals!$N$2:$N$865,Calc_Actuals!$J$2:$J$865,G13,Calc_Actuals!$K$2:$K$865,O13,Calc_Actuals!$F$2:$F$865,B13,Calc_Actuals!$H$2:$H$865,C13,Calc_Actuals!$C$2:$C$865,"Actual"),0) -> 334532.4 | N13: =IF(I13="Actual",SUMIFS(Calc_Actuals!$P$2:$P$865,Calc_Actuals!$J$2:$J$865,G13,Calc_Actuals!$K$2:$K$865,O13,Calc_Actuals!$F$2:$F$865,B13,Calc_Actuals!$H$2:$H$865,C13,Calc_Actuals!$C$2:$C$865,"Actual"),0) -> 101418.48 | O13: =VALUE(RIGHT(A13,2)) -> 1 | P13: =A13&"|"&B13&"|"&C13 -> 2025-01|South|Home Care
A14: =Sales_Budget!A3 -> 2025-01 | B14: =Sales_Budget!B3 -> South | C14: =Sales_Budget!C3 -> Personal Care | D14: =Sales_Budget!E3 -> 1025000 | E14: =Sales_Budget!F3 -> 635500 | F14: =Sales_Budget!G3 -> 389500 | G14: =VALUE(LEFT(A14,4)) -> 2025 | H14: =IF(COUNTIFS(Calc_Actuals!$F$2:$F$865,B14,Calc_Actuals!$H$2:$H$865,C14,Calc_Actuals!$C$2:$C$865,"Actual")>0,1,0) -> 0 | I14: =IFERROR(INDEX(Calendar!$E$2:$E$25,MATCH(A14,Calendar!$A$2:$A$25,0)),"UNMATCHED") -> Actual | J14: =D14*$B$7 -> 260438.99 | K14: =E14*$B$7 -> 161472.18 | L14: =F14*$B$7 -> 98966.817 | M14: =IF(I14="Actual",SUMIFS(Calc_Actuals!$N$2:$N$865,Calc_Actuals!$J$2:$J$865,G14,Calc_Actuals!$K$2:$K$865,O14,Calc_Actuals!$F$2:$F$865,B14,Calc_Actuals!$H$2:$H$865,C14,Calc_Actuals!$C$2:$C$865,"Actual"),0) -> 0 | N14: =IF(I14="Actual",SUMIFS(Calc_Actuals!$P$2:$P$865,Calc_Actuals!$J$2:$J$865,G14,Calc_Actuals!$K$2:$K$865,O14,Calc_Actuals!$F$2:$F$865,B14,Calc_Actuals!$H$2:$H$865,C14,Calc_Actuals!$C$2:$C$865,"Actual"),0) -> 0 | O14: =VALUE(RIGHT(A14,2)) -> 1 | P14: =A14&"|"&B14&"|"&C14 -> 2025-01|South|Personal Care
A15: =Sales_Budget!A4 -> 2025-01 | B15: =Sales_Budget!B4 -> South | C15: =Sales_Budget!C4 -> Foods | D15: =Sales_Budget!E4 -> 1100000 | E15: =Sales_Budget!F4 -> 682000 | F15: =Sales_Budget!G4 -> 418000 | G15: =VALUE(LEFT(A15,4)) -> 2025 | H15: =IF(COUNTIFS(Calc_Actuals!$F$2:$F$865,B15,Calc_Actuals!$H$2:$H$865,C15,Calc_Actuals!$C$2:$C$865,"Actual")>0,1,0) -> 1 | I15: =IFERROR(INDEX(Calendar!$E$2:$E$25,MATCH(A15,Calendar!$A$2:$A$25,0)),"UNMATCHED") -> Actual | J15: =D15*$B$7 -> 279495.5 | K15: =E15*$B$7 -> 173287.21 | L15: =F15*$B$7 -> 106208.29 | M15: =IF(I15="Actual",SUMIFS(Calc_Actuals!$N$2:$N$865,Calc_Actuals!$J$2:$J$865,G15,Calc_Actuals!$K$2:$K$865,O15,Calc_Actuals!$F$2:$F$865,B15,Calc_Actuals!$H$2:$H$865,C15,Calc_Actuals!$C$2:$C$865,"Actual"),0) -> 155341.3 | N15: =IF(I15="Actual",SUMIFS(Calc_Actuals!$P$2:$P$865,Calc_Actuals!$J$2:$J$865,G15,Calc_Actuals!$K$2:$K$865,O15,Calc_Actuals!$F$2:$F$865,B15,Calc_Actuals!$H$2:$H$865,C15,Calc_Actuals!$C$2:$C$865,"Actual"),0) -> 51116.98 | O15: =VALUE(RIGHT(A15,2)) -> 1 | P15: =A15&"|"&B15&"|"&C15 -> 2025-01|South|Foods
A16: =Sales_Budget!A5 -> 2025-01 | B16: =Sales_Budget!B5 -> North | C16: =Sales_Budget!C5 -> Home Care | D16: =Sales_Budget!E5 -> 1035000 | E16: =Sales_Budget!F5 -> 641700 | F16: =Sales_Budget!G5 -> 393300 | G16: =VALUE(LEFT(A16,4)) -> 2025 | H16: =IF(COUNTIFS(Calc_Actuals!$F$2:$F$865,B16,Calc_Actuals!$H$2:$H$865,C16,Calc_Actuals!$C$2:$C$865,"Actual")>0,1,0) -> 0 | I16: =IFERROR(INDEX(Calendar!$E$2:$E$25,MATCH(A16,Calendar!$A$2:$A$25,0)),"UNMATCHED") -> Actual | J16: =D16*$B$7 -> 262979.86 | K16: =E16*$B$7 -> 163047.51 | L16: =F16*$B$7 -> 99932.347 | M16: =IF(I16="Actual",SUMIFS(Calc_Actuals!$N$2:$N$865,Calc_Actuals!$J$2:$J$865,G16,Calc_Actuals!$K$2:$K$865,O16,Calc_Actuals!$F$2:$F$865,B16,Calc_Actuals!$H$2:$H$865,C16,Calc_Actuals!$C$2:$C$865,"Actual"),0) -> 0 | N16: =IF(I16="Actual",SUMIFS(Calc_Actuals!$P$2:$P$865,Calc_Actuals!$J$2:$J$865,G16,Calc_Actuals!$K$2:$K$865,O16,Calc_Actuals!$F$2:$F$865,B16,Calc_Actuals!$H$2:$H$865,C16,Calc_Actuals!$C$2:$C$865,"Actual"),0) -> 0 | O16: =VALUE(RIGHT(A16,2)) -> 1 | P16: =A16&"|"&B16&"|"&C16 -> 2025-01|North|Home Care
A17: =Sales_Budget!A6 -> 2025-01 | B17: =Sales_Budget!B6 -> North | C17: =Sales_Budget!C6 -> Personal Care | D17: =Sales_Budget!E6 -> 1110000 | E17: =Sales_Budget!F6 -> 688200 | F17: =Sales_Budget!G6 -> 421800 | G17: =VALUE(LEFT(A17,4)) -> 2025 | H17: =IF(COUNTIFS(Calc_Actuals!$F$2:$F$865,B17,Calc_Actuals!$H$2:$H$865,C17,Calc_Actuals!$C$2:$C$865,"Actual")>0,1,0) -> 1 | I17: =IFERROR(INDEX(Calendar!$E$2:$E$25,MATCH(A17,Calendar!$A$2:$A$25,0)),"UNMATCHED") -> Actual | J17: =D17*$B$7 -> 282036.37 | K17: =E17*$B$7 -> 174862.55 | L17: =F17*$B$7 -> 107173.82 | M17: =IF(I17="Actual",SUMIFS(Calc_Actuals!$N$2:$N$865,Calc_Actuals!$J$2:$J$865,G17,Calc_Actuals!$K$2:$K$865,O17,Calc_Actuals!$F$2:$F$865,B17,Calc_Actuals!$H$2:$H$865,C17,Calc_Actuals!$C$2:$C$865,"Actual"),0) -> 745665.04 | N17: =IF(I17="Actual",SUMIFS(Calc_Actuals!$P$2:$P$865,Calc_Actuals!$J$2:$J$865,G17,Calc_Actuals!$K$2:$K$865,O17,Calc_Actuals!$F$2:$F$865,B17,Calc_Actuals!$H$2:$H$865,C17,Calc_Actuals!$C$2:$C$865,"Actual"),0) -> 276602.31 | O17: =VALUE(RIGHT(A17,2)) -> 1 | P17: =A17&"|"&B17&"|"&C17 -> 2025-01|North|Personal Care
A18: =Sales_Budget!A7 -> 2025-01 | B18: =Sales_Budget!B7 -> North | C18: =Sales_Budget!C7 -> Foods | D18: =Sales_Budget!E7 -> 1185000 | E18: =Sales_Budget!F7 -> 734700 | F18: =Sales_Budget!G7 -> 450300 | G18: =VALUE(LEFT(A18,4)) -> 2025 | H18: =IF(COUNTIFS(Calc_Actuals!$F$2:$F$865,B18,Calc_Actuals!$H$2:$H$865,C18,Calc_Actuals!$C$2:$C$865,"Actual")>0,1,0) -> 0 | I18: =IFERROR(INDEX(Calendar!$E$2:$E$25,MATCH(A18,Calendar!$A$2:$A$25,0)),"UNMATCHED") -> Actual | J18: =D18*$B$7 -> 301092.88 | K18: =E18*$B$7 -> 186677.59 | L18: =F18*$B$7 -> 114415.3 | M18: =IF(I18="Actual",SUMIFS(Calc_Actuals!$N$2:$N$865,Calc_Actuals!$J$2:$J$865,G18,Calc_Actuals!$K$2:$K$865,O18,Calc_Actuals!$F$2:$F$865,B18,Calc_Actuals!$H$2:$H$865,C18,Calc_Actuals!$C$2:$C$865,"Actual"),0) -> 0 | N18: =IF(I18="Actual",SUMIFS(Calc_Actuals!$P$2:$P$865,Calc_Actuals!$J$2:$J$865,G18,Calc_Actuals!$K$2:$K$865,O18,Calc_Actuals!$F$2:$F$865,B18,Calc_Actuals!$H$2:$H$865,C18,Calc_Actuals!$C$2:$C$865,"Actual"),0) -> 0 | O18: =VALUE(RIGHT(A18,2)) -> 1 | P18: =A18&"|"&B18&"|"&C18 -> 2025-01|North|Foods
A19: =Sales_Budget!A8 -> 2025-01 | B19: =Sales_Budget!B8 -> West | C19: =Sales_Budget!C8 -> Home Care | D19: =Sales_Budget!E8 -> 1120000 | E19: =Sales_Budget!F8 -> 694400 | F19: =Sales_Budget!G8 -> 425600 | G19: =VALUE(LEFT(A19,4)) -> 2025 | H19: =IF(COUNTIFS(Calc_Actuals!$F$2:$F$865,B19,Calc_Actuals!$H$2:$H$865,C19,Calc_Actuals!$C$2:$C$865,"Actual")>0,1,0) -> 1 | I19: =IFERROR(INDEX(Calendar!$E$2:$E$25,MATCH(A19,Calendar!$A$2:$A$25,0)),"UNMATCHED") -> Actual | J19: =D19*$B$7 -> 284577.24 | K19: =E19*$B$7 -> 176437.89 | L19: =F19*$B$7 -> 108139.35 | M19: =IF(I19="Actual",SUMIFS(Calc_Actuals!$N$2:$N$865,Calc_Actuals!$J$2:$J$865,G19,Calc_Actuals!$K$2:$K$865,O19,Calc_Actuals!$F$2:$F$865,B19,Calc_Actuals!$H$2:$H$865,C19,Calc_Actuals!$C$2:$C$865,"Actual"),0) -> 246729.6 | N19: =IF(I19="Actual",SUMIFS(Calc_Actuals!$P$2:$P$865,Calc_Actuals!$J$2:$J$865,G19,Calc_Actuals!$K$2:$K$865,O19,Calc_Actuals!$F$2:$F$865,B19,Calc_Actuals!$H$2:$H$865,C19,Calc_Actuals!$C$2:$C$865,"Actual"),0) -> 93545.04 | O19: =VALUE(RIGHT(A19,2)) -> 1 | P19: =A19&"|"&B19&"|"&C19 -> 2025-01|West|Home Care
A20: =Sales_Budget!A9 -> 2025-01 | B20: =Sales_Budget!B9 -> West | C20: =Sales_Budget!C9 -> Personal Care | D20: =Sales_Budget!E9 -> 1195000 | E20: =Sales_Budget!F9 -> 740900 | F20: =Sales_Budget!G9 -> 454100 | G20: =VALUE(LEFT(A20,4)) -> 2025 | H20: =IF(COUNTIFS(Calc_Actuals!$F$2:$F$865,B20,Calc_Actuals!$H$2:$H$865,C20,Calc_Actuals!$C$2:$C$865,"Actual")>0,1,0) -> 1 | I20: =IFERROR(INDEX(Calendar!$E$2:$E$25,MATCH(A20,Calendar!$A$2:$A$25,0)),"UNMATCHED") -> Actual | J20: =D20*$B$7 -> 303633.75 | K20: =E20*$B$7 -> 188252.93 | L20: =F20*$B$7 -> 115380.83 | M20: =IF(I20="Actual",SUMIFS(Calc_Actuals!$N$2:$N$865,Calc_Actuals!$J$2:$J$865,G20,Calc_Actuals!$K$2:$K$865,O20,Calc_Actuals!$F$2:$F$865,B20,Calc_Actuals!$H$2:$H$865,C20,Calc_Actuals!$C$2:$C$865,"Actual"),0) -> 326794.66 | N20: =IF(I20="Actual",SUMIFS(Calc_Actuals!$P$2:$P$865,Calc_Actuals!$J$2:$J$865,G20,Calc_Actuals!$K$2:$K$865,O20,Calc_Actuals!$F$2:$F$865,B20,Calc_Actuals!$H$2:$H$865,C20,Calc_Actuals!$C$2:$C$865,"Actual"),0) -> 114691.87 | O20: =VALUE(RIGHT(A20,2)) -> 1 | P20: =A20&"|"&B20&"|"&C20 -> 2025-01|West|Personal Care
A21: =Sales_Budget!A10 -> 2025-01 | B21: =Sales_Budget!B10 -> West | C21: =Sales_Budget!C10 -> Foods | D21: =Sales_Budget!E10 -> 1270000 | E21: =Sales_Budget!F10 -> 787400 | F21: =Sales_Budget!G10 -> 482600 | G21: =VALUE(LEFT(A21,4)) -> 2025 | H21: =IF(COUNTIFS(Calc_Actuals!$F$2:$F$865,B21,Calc_Actuals!$H$2:$H$865,C21,Calc_Actuals!$C$2:$C$865,"Actual")>0,1,0) -> 0 | I21: =IFERROR(INDEX(Calendar!$E$2:$E$25,MATCH(A21,Calendar!$A$2:$A$25,0)),"UNMATCHED") -> Actual | J21: =D21*$B$7 -> 322690.26 | K21: =E21*$B$7 -> 200067.96 | L21: =F21*$B$7 -> 122622.3 | M21: =IF(I21="Actual",SUMIFS(Calc_Actuals!$N$2:$N$865,Calc_Actuals!$J$2:$J$865,G21,Calc_Actuals!$K$2:$K$865,O21,Calc_Actuals!$F$2:$F$865,B21,Calc_Actuals!$H$2:$H$865,C21,Calc_Actuals!$C$2:$C$865,"Actual"),0) -> 0 | N21: =IF(I21="Actual",SUMIFS(Calc_Actuals!$P$2:$P$865,Calc_Actuals!$J$2:$J$865,G21,Calc_Actuals!$K$2:$K$865,O21,Calc_Actuals!$F$2:$F$865,B21,Calc_Actuals!$H$2:$H$865,C21,Calc_Actuals!$C$2:$C$865,"Actual"),0) -> 0 | O21: =VALUE(RIGHT(A21,2)) -> 1 | P21: =A21&"|"&B21&"|"&C21 -> 2025-01|West|Foods
A22: =Sales_Budget!A11 -> 2025-01 | B22: =Sales_Budget!B11 -> East | C22: =Sales_Budget!C11 -> Home Care | D22: =Sales_Budget!E11 -> 1205000 | E22: =Sales_Budget!F11 -> 747100 | F22: =Sales_Budget!G11 -> 457900 | G22: =VALUE(LEFT(A22,4)) -> 2025 | H22: =IF(COUNTIFS(Calc_Actuals!$F$2:$F$865,B22,Calc_Actuals!$H$2:$H$865,C22,Calc_Actuals!$C$2:$C$865,"Actual")>0,1,0) -> 1 | I22: =IFERROR(INDEX(Calendar!$E$2:$E$25,MATCH(A22,Calendar!$A$2:$A$25,0)),"UNMATCHED") -> Actual | J22: =D22*$B$7 -> 306174.62 | K22: =E22*$B$7 -> 189828.27 | L22: =F22*$B$7 -> 116346.36 | M22: =IF(I22="Actual",SUMIFS(Calc_Actuals!$N$2:$N$865,Calc_Actuals!$J$2:$J$865,G22,Calc_Actuals!$K$2:$K$865,O22,Calc_Actuals!$F$2:$F$865,B22,Calc_Actuals!$H$2:$H$865,C22,Calc_Actuals!$C$2:$C$865,"Actual"),0) -> 196945.92 | N22: =IF(I22="Actual",SUMIFS(Calc_Actuals!$P$2:$P$865,Calc_Actuals!$J$2:$J$865,G22,Calc_Actuals!$K$2:$K$865,O22,Calc_Actuals!$F$2:$F$865,B22,Calc_Actuals!$H$2:$H$865,C22,Calc_Actuals!$C$2:$C$865,"Actual"),0) -> 73582.06 | O22: =VALUE(RIGHT(A22,2)) -> 1 | P22: =A22&"|"&B22&"|"&C22 -> 2025-01|East|Home Care
A23: =Sales_Budget!A12 -> 2025-01 | B23: =Sales_Budget!B12 -> East | C23: =Sales_Budget!C12 -> Personal Care | D23: =Sales_Budget!E12 -> 1280000 | E23: =Sales_Budget!F12 -> 793600 | F23: =Sales_Budget!G12 -> 486400 | G23: =VALUE(LEFT(A23,4)) -> 2025 | H23: =IF(COUNTIFS(Calc_Actuals!$F$2:$F$865,B23,Calc_Actuals!$H$2:$H$865,C23,Calc_Actuals!$C$2:$C$865,"Actual")>0,1,0) -> 0 | I23: =IFERROR(INDEX(Calendar!$E$2:$E$25,MATCH(A23,Calendar!$A$2:$A$25,0)),"UNMATCHED") -> Actual | J23: =D23*$B$7 -> 325231.13 | K23: =E23*$B$7 -> 201643.3 | L23: =F23*$B$7 -> 123587.83 | M23: =IF(I23="Actual",SUMIFS(Calc_Actuals!$N$2:$N$865,Calc_Actuals!$J$2:$J$865,G23,Calc_Actuals!$K$2:$K$865,O23,Calc_Actuals!$F$2:$F$865,B23,Calc_Actuals!$H$2:$H$865,C23,Calc_Actuals!$C$2:$C$865,"Actual"),0) -> 0 | N23: =IF(I23="Actual",SUMIFS(Calc_Actuals!$P$2:$P$865,Calc_Actuals!$J$2:$J$865,G23,Calc_Actuals!$K$2:$K$865,O23,Calc_Actuals!$F$2:$F$865,B23,Calc_Actuals!$H$2:$H$865,C23,Calc_Actuals!$C$2:$C$865,"Actual"),0) -> 0 | O23: =VALUE(RIGHT(A23,2)) -> 1 | P23: =A23&"|"&B23&"|"&C23 -> 2025-01|East|Personal Care
A24: =Sales_Budget!A13 -> 2025-01 | B24: =Sales_Budget!B13 -> East | C24: =Sales_Budget!C13 -> Foods | D24: =Sales_Budget!E13 -> 1355000 | E24: =Sales_Budget!F13 -> 840100 | F24: =Sales_Budget!G13 -> 514900 | G24: =VALUE(LEFT(A24,4)) -> 2025 | H24: =IF(COUNTIFS(Calc_Actuals!$F$2:$F$865,B24,Calc_Actuals!$H$2:$H$865,C24,Calc_Actuals!$C$2:$C$865,"Actual")>0,1,0) -> 1 | I24: =IFERROR(INDEX(Calendar!$E$2:$E$25,MATCH(A24,Calendar!$A$2:$A$25,0)),"UNMATCHED") -> Actual | J24: =D24*$B$7 -> 344287.64 | K24: =E24*$B$7 -> 213458.34 | L24: =F24*$B$7 -> 130829.3 | M24: =IF(I24="Actual",SUMIFS(Calc_Actuals!$N$2:$N$865,Calc_Actuals!$J$2:$J$865,G24,Calc_Actuals!$K$2:$K$865,O24,Calc_Actuals!$F$2:$F$865,B24,Calc_Actuals!$H$2:$H$865,C24,Calc_Actuals!$C$2:$C$865,"Actual"),0) -> 229961.73 | N24: =IF(I24="Actual",SUMIFS(Calc_Actuals!$P$2:$P$865,Calc_Actuals!$J$2:$J$865,G24,Calc_Actuals!$K$2:$K$865,O24,Calc_Actuals!$F$2:$F$865,B24,Calc_Actuals!$H$2:$H$865,C24,Calc_Actuals!$C$2:$C$865,"Actual"),0) -> 74424.9 | O24: =VALUE(RIGHT(A24,2)) -> 1 | P24: =A24&"|"&B24&"|"&C24 -> 2025-01|East|Foods
... A300: =Sales_Budget!A289 -> 2026-12 | B300: =Sales_Budget!B289 -> East | C300: =Sales_Budget!C289 -> Foods | D300: =Sales_Budget!E289 -> 1463400 | E300: =Sales_Budget!F289 -> 907308 | F300: =Sales_Budget!G289 -> 556092 | G300: =VALUE(LEFT(A300,4)) -> 2026 | H300: =IF(COUNTIFS(Calc_Actuals!$F$2:$F$865,B300,Calc_Actuals!$H$2:$H$865,C300,Calc_Actuals!$C$2:$C$865,"Actual")>0,1,0) -> 1 | I300: =IFERROR(INDEX(Calendar!$E$2:$E$25,MATCH(A300,Calendar!$A$2:$A$25,0)),"UNMATCHED") -> Forecast | J300: =D300*$B$7 -> 371830.66 | K300: =E300*$B$7 -> 230535.01 | L300: =F300*$B$7 -> 141295.65 | M300: =IF(I300="Actual",SUMIFS(Calc_Actuals!$N$2:$N$865,Calc_Actuals!$J$2:$J$865,G300,Calc_Actuals!$K$2:$K$865,O300,Calc_Actuals!$F$2:$F$865,B300,Calc_Actuals!$H$2:$H$865,C300,Calc_Actuals!$C$2:$C$865,"Actual"),0) -> 0 | N300: =IF(I300="Actual",SUMIFS(Calc_Actuals!$P$2:$P$865,Calc_Actuals!$J$2:$J$865,G300,Calc_Actuals!$K$2:$K$865,O300,Calc_Actuals!$F$2:$F$865,B300,Calc_Actuals!$H$2:$H$865,C300,Calc_Actuals!$C$2:$C$865,"Actual"),0) -> 0 | O300: =VALUE(RIGHT(A300,2)) -> 12 | P300: =A300&"|"&B300&"|"&C300 -> 2026-12|East|Foods

Sheet Control_Checks
A1: Control Checks - Reconciliations & Data Integrity
A2: Live formulas. Blue = hard-coded expected values taken from the source file's own Control_Checks sheet. Tolerance for INR sums = 0.01.
A3: Overall status | C3: =IF(COUNTIF(I6:I56,"FAIL")=0,"ALL "&COUNTIF(I6:I56,"PASS")&" CHECKS PASS",COUNTIF(I6:I56,"FAIL")&" CHECK(S) FAIL") -> ALL 51 CHECKS PASS
A5: # | B5: Group | C5: Control | D5: Method / calculation | E5: Expected | F5: Actual | G5: Difference | H5: Tolerance | I5: Result | J5: Exceptions
A6: 1 | B6: Record counts | C6: Sales_Transactions rows | D6: Expected: source Control_Checks baseline. Actual: COUNTA of Invoice_ID. | E6: 864 | F6: =COUNTA(Sales_Transactions!$A$2:$A$865) -> 864 | G6: =F6-E6 -> 0 | H6: 0 | I6: =IF(ISNUMBER(G6),IF(ABS(G6)<=H6,"PASS","FAIL"),"FAIL") -> PASS | J6: =IF(I6="PASS","None",IF(I6="N/A","No baseline in source","EXCEPTION: difference "&TEXT(G6,"#,##0.00")&" - investigate; see Calc_Actuals filter on col W")) -> None
A7: 2 | B7: Record counts | C7: Actual-status rows | D7: Expected: source baseline. Actual: COUNTIF Status="Actual". | E7: 756 | F7: =COUNTIF(Sales_Transactions!$C$2:$C$865,"Actual") -> 756 | G7: =F7-E7 -> 0 | H7: 0 | I7: =IF(ISNUMBER(G7),IF(ABS(G7)<=H7,"PASS","FAIL"),"FAIL") -> PASS | J7: =IF(I7="PASS","None",IF(I7="N/A","No baseline in source","EXCEPTION: difference "&TEXT(G7,"#,##0.00")&" - investigate; see Calc_Actuals filter on col W")) -> None
A8: 3 | B8: Record counts | C8: Forecast-status rows | D8: Expected: source baseline. Actual: COUNTIF Status="Forecast". | E8: 108 | F8: =COUNTIF(Sales_Transactions!$C$2:$C$865,"Forecast") -> 108 | G8: =F8-E8 -> 0 | H8: 0 | I8: =IF(ISNUMBER(G8),IF(ABS(G8)<=H8,"PASS","FAIL"),"FAIL") -> PASS | J8: =IF(I8="PASS","None",IF(I8="N/A","No baseline in source","EXCEPTION: difference "&TEXT(G8,"#,##0.00")&" - investigate; see Calc_Actuals filter on col W")) -> None
A9: 4 | B9: Record counts | C9: Rows with Status other than Actual/Forecast | D9: Expected 0. Actual: rows - Actual - Forecast. | E9: 0 | F9: =ROWS(Sales_Transactions!$A$2:$A$865)-COUNTIF(Sales_Transactions!$C$2:$C$865,"Actual")-COUNTIF(Sales_Transactions!$C$2:$C$865,"Forecast") -> 0 | G9: =F9-E9 -> 0 | H9: 0 | I9: =IF(ISNUMBER(G9),IF(ABS(G9)<=H9,"PASS","FAIL"),"FAIL") -> PASS | J9: =IF(I9="PASS","None",IF(I9="N/A","No baseline in source","EXCEPTION: difference "&TEXT(G9,"#,##0.00")&" - investigate; see Calc_Actuals filter on col W")) -> None
A10: 5 | B10: Record counts | C10: Blank cells in Sales_Transactions | D10: Expected 0. COUNTBLANK over A:K data range. | E10: 0 | F10: =COUNTBLANK(Sales_Transactions!$A$2:$K$865) -> 0 | G10: =F10-E10 -> 0 | H10: 0 | I10: =IF(ISNUMBER(G10),IF(ABS(G10)<=H10,"PASS","FAIL"),"FAIL") -> PASS | J10: =IF(I10="PASS","None",IF(I10="N/A","No baseline in source","EXCEPTION: difference "&TEXT(G10,"#,##0.00")&" - investigate; see Calc_Actuals filter on col W")) -> None
A11: 6 | B11: Keys | C11: Unique Invoice_IDs | D11: Expected: source baseline. Actual: SUMPRODUCT(1/COUNTIF) distinct count. | E11: 864 | F11: =ROUND(SUMPRODUCT(1/COUNTIF(Sales_Transactions!$A$2:$A$865,Sales_Transactions!$A$2:$A$865)),0) -> 864 | G11: =F11-E11 -> 0 | H11: 0 | I11: =IF(ISNUMBER(G11),IF(ABS(G11)<=H11,"PASS","FAIL"),"FAIL") -> PASS | J11: =IF(I11="PASS","None",IF(I11="N/A","No baseline in source","EXCEPTION: difference "&TEXT(G11,"#,##0.00")&" - investigate; see Calc_Actuals filter on col W")) -> None
A12: 7 | B12: Keys | C12: Duplicate Invoice_ID rows | D12: Expected 0. Rows - distinct Invoice_IDs. | E12: 0 | F12: =ROWS(Sales_Transactions!$A$2:$A$865)-ROUND(SUMPRODUCT(1/COUNTIF(Sales_Transactions!$A$2:$A$865,Sales_Transactions!$A$2:$A$865)),0) -> 0 | G12: =F12-E12 -> 0 | H12: 0 | I12: =IF(ISNUMBER(G12),IF(ABS(G12)<=H12,"PASS","FAIL"),"FAIL") -> PASS | J12: =IF(I12="PASS","None",IF(I12="N/A","No baseline in source","EXCEPTION: difference "&TEXT(G12,"#,##0.00")&" - investigate; see Calc_Actuals filter on col W")) -> None
A13: 8 | B13: Keys | C13: Unmatched Product_ID (Sales -> Product_Master) | D13: Expected: source baseline. Rows whose Product_ID is absent from Product_Master. | E13: 0 | F13: =SUMPRODUCT(--ISNA(MATCH(Sales_Transactions!$E$2:$E$865,Product_Master!$A$2:$A$9,0))) -> 0 | G13: =F13-E13 -> 0 | H13: 0 | I13: =IF(ISNUMBER(G13),IF(ABS(G13)<=H13,"PASS","FAIL"),"FAIL") -> PASS | J13: =IF(I13="PASS","None",IF(I13="N/A","No baseline in source","EXCEPTION: difference "&TEXT(G13,"#,##0.00")&" - investigate; see Calc_Actuals filter on col W")) -> None
A14: 9 | B14: Keys | C14: Unmatched Customer_ID (Sales -> Customer_Master) | D14: Expected: source baseline. Rows whose Customer_ID is absent from Customer_Master. | E14: 0 | F14: =SUMPRODUCT(--ISNA(MATCH(Sales_Transactions!$D$2:$D$865,Customer_Master!$A$2:$A$49,0))) -> 0 | G14: =F14-E14 -> 0 | H14: 0 | I14: =IF(ISNUMBER(G14),IF(ABS(G14)<=H14,"PASS","FAIL"),"FAIL") -> PASS | J14: =IF(I14="PASS","None",IF(I14="N/A","No baseline in source","EXCEPTION: difference "&TEXT(G14,"#,##0.00")&" - investigate; see Calc_Actuals filter on col W")) -> None
A15: 10 | B15: Keys | C15: Unmatched Month (Sales -> Calendar) | D15: Expected 0. Rows whose Month is absent from Calendar. | E15: 0 | F15: =SUMPRODUCT(--ISNA(MATCH(Sales_Transactions!$B$2:$B$865,Calendar!$A$2:$A$25,0))) -> 0 | G15: =F15-E15 -> 0 | H15: 0 | I15: =IF(ISNUMBER(G15),IF(ABS(G15)<=H15,"PASS","FAIL"),"FAIL") -> PASS | J15: =IF(I15="PASS","None",IF(I15="N/A","No baseline in source","EXCEPTION: difference "&TEXT(G15,"#,##0.00")&" - investigate; see Calc_Actuals filter on col W")) -> None
A16: 11 | B16: Keys | C16: Duplicate Product_ID in Product_Master | D16: Expected 0. Rows - distinct IDs. | E16: 0 | F16: =ROWS(Product_Master!$A$2:$A$9)-ROUND(SUMPRODUCT(1/COUNTIF(Product_Master!$A$2:$A$9,Product_Master!$A$2:$A$9)),0) -> 0 | G16: =F16-E16 -> 0 | H16: 0 | I16: =IF(ISNUMBER(G16),IF(ABS(G16)<=H16,"PASS","FAIL"),"FAIL") -> PASS | J16: =IF(I16="PASS","None",IF(I16="N/A","No baseline in source","EXCEPTION: difference "&TEXT(G16,"#,##0.00")&" - investigate; see Calc_Actuals filter on col W")) -> None
A17: 12 | B17: Keys | C17: Duplicate Customer_ID in Customer_Master | D17: Expected 0. Rows - distinct IDs. | E17: 0 | F17: =ROWS(Customer_Master!$A$2:$A$49)-ROUND(SUMPRODUCT(1/COUNTIF(Customer_Master!$A$2:$A$49,Customer_Master!$A$2:$A$49)),0) -> 0 | G17: =F17-E17 -> 0 | H17: 0 | I17: =IF(ISNUMBER(G17),IF(ABS(G17)<=H17,"PASS","FAIL"),"FAIL") -> PASS | J17: =IF(I17="PASS","None",IF(I17="N/A","No baseline in source","EXCEPTION: difference "&TEXT(G17,"#,##0.00")&" - investigate; see Calc_Actuals filter on col W")) -> None
A18: 13 | B18: Status | C18: Transaction Status vs Calendar Reporting_Status mismatches | D18: Expected 0. Count of rows where Status <> Calendar.Reporting_Status (Calc_Actuals col V). | E18: 0 | F18: =SUM(Calc_Actuals!$V$2:$V$865) -> 0 | G18: =F18-E18 -> 0 | H18: 0 | I18: =IF(ISNUMBER(G18),IF(ABS(G18)<=H18,"PASS","FAIL"),"FAIL") -> PASS | J18: =IF(I18="PASS","None",IF(I18="N/A","No baseline in source","EXCEPTION: difference "&TEXT(G18,"#,##0.00")&" - investigate; see Calc_Actuals filter on col W")) -> None
A19: 14 | B19: Row arithmetic | C19: Net_Revenue <> Units x Net_Price (>0.01) | D19: Expected 0 rows. SUMPRODUCT of ABS(F*G-I)>0.01. | E19: 0 | F19: =SUMPRODUCT(--(ABS(Sales_Transactions!$F$2:$F$865*Sales_Transactions!$G$2:$G$865-Sales_Transactions!$I$2:$I$865)>0.01)) -> 0 | G19: =F19-E19 -> 0 | H19: 0 | I19: =IF(ISNUMBER(G19),IF(ABS(G19)<=H19,"PASS","FAIL"),"FAIL") -> PASS | J19: =IF(I19="PASS","None",IF(I19="N/A","No baseline in source","EXCEPTION: difference "&TEXT(G19,"#,##0.00")&" - investigate; see Calc_Actuals filter on col W")) -> None
A20: 15 | B20: Row arithmetic | C20: COGS <> Units x Unit_Cost (>0.01) | D20: Expected 0 rows. SUMPRODUCT of ABS(F*H-J)>0.01. | E20: 0 | F20: =SUMPRODUCT(--(ABS(Sales_Transactions!$F$2:$F$865*Sales_Transactions!$H$2:$H$865-Sales_Transactions!$J$2:$J$865)>0.01)) -> 0 | G20: =F20-E20 -> 0 | H20: 0 | I20: =IF(ISNUMBER(G20),IF(ABS(G20)<=H20,"PASS","FAIL"),"FAIL") -> PASS | J20: =IF(I20="PASS","None",IF(I20="N/A","No baseline in source","EXCEPTION: difference "&TEXT(G20,"#,##0.00")&" - investigate; see Calc_Actuals filter on col W")) -> None
A21: 16 | B21: Row arithmetic | C21: Gross_Profit <> Net_Revenue - COGS (>0.01) | D21: Expected 0 rows. SUMPRODUCT of ABS(I-J-K)>0.01. | E21: 0 | F21: =SUMPRODUCT(--(ABS(Sales_Transactions!$I$2:$I$865-Sales_Transactions!$J$2:$J$865-Sales_Transactions!$K$2:$K$865)>0.01)) -> 0 | G21: =F21-E21 -> 0 | H21: 0 | I21: =IF(ISNUMBER(G21),IF(ABS(G21)<=H21,"PASS","FAIL"),"FAIL") -> PASS | J21: =IF(I21="PASS","None",IF(I21="N/A","No baseline in source","EXCEPTION: difference "&TEXT(G21,"#,##0.00")&" - investigate; see Calc_Actuals filter on col W")) -> None
A22: 17 | B22: Row arithmetic | C22: Non-positive Units / Net_Price / Unit_Cost | D22: Expected 0. COUNTIF <=0 on the three columns. | E22: 0 | F22: =COUNTIF(Sales_Transactions!$F$2:$F$865,"<=0")+COUNTIF(Sales_Transactions!$G$2:$G$865,"<=0")+COUNTIF(Sales_Transactions!$H$2:$H$865,"<=0") -> 0 | G22: =F22-E22 -> 0 | H22: 0 | I22: =IF(ISNUMBER(G22),IF(ABS(G22)<=H22,"PASS","FAIL"),"FAIL") -> PASS | J22: =IF(I22="PASS","None",IF(I22="N/A","No baseline in source","EXCEPTION: difference "&TEXT(G22,"#,##0.00")&" - investigate; see Calc_Actuals filter on col W")) -> None
A23: 18 | B23: Reconciliation | C23: Net revenue: Monthly_MIS total vs raw source (Status=Actual) | D23: Expected: SUMIFS on raw Sales_Transactions col I. Actual: Monthly_MIS total row. | E23: =SUMIFS(Sales_Transactions!$I$2:$I$865,Sales_Transactions!$C$2:$C$865,"Actual") -> 42593025 | F23: =Monthly_MIS!E30 -> 42593025 | G23: =F23-E23 -> 0 | H23: 0.01 | I23: =IF(ISNUMBER(G23),IF(ABS(G23)<=H23,"PASS","FAIL"),"FAIL") -> PASS | J23: =IF(I23="PASS","None",IF(I23="N/A","No baseline in source","EXCEPTION: difference "&TEXT(G23,"#,##0.00")&" - investigate; see Calc_Actuals filter on col W")) -> None
A24: 19 | B24: Reconciliation | C24: Net revenue: Monthly_MIS total vs source-file baseline | D24: Expected: baseline in source Control_Checks sheet (hard-coded). Actual: Monthly_MIS total row. | E24: 42593025 | F24: =Monthly_MIS!E30 -> 42593025 | G24: =F24-E24 -> 0 | H24: 0.01 | I24: =IF(ISNUMBER(G24),IF(ABS(G24)<=H24,"PASS","FAIL"),"FAIL") -> PASS | J24: =IF(I24="PASS","None",IF(I24="N/A","No baseline in source","EXCEPTION: difference "&TEXT(G24,"#,##0.00")&" - investigate; see Calc_Actuals filter on col W")) -> None
A25: 20 | B25: Reconciliation | C25: COGS: Monthly_MIS total vs raw source (Status=Actual) | D25: Expected: SUMIFS on raw Sales_Transactions col J. Actual: Monthly_MIS total row. | E25: =SUMIFS(Sales_Transactions!$J$2:$J$865,Sales_Transactions!$C$2:$C$865,"Actual") -> 27380595 | F25: =Monthly_MIS!F30 -> 27380595 | G25: =F25-E25 -> 0 | H25: 0.01 | I25: =IF(ISNUMBER(G25),IF(ABS(G25)<=H25,"PASS","FAIL"),"FAIL") -> PASS | J25: =IF(I25="PASS","None",IF(I25="N/A","No baseline in source","EXCEPTION: difference "&TEXT(G25,"#,##0.00")&" - investigate; see Calc_Actuals filter on col W")) -> None
A26: 21 | B26: Reconciliation | C26: COGS: Monthly_MIS total vs source-file baseline | D26: Expected: baseline in source Control_Checks sheet (hard-coded). Actual: Monthly_MIS total row. | E26: 27380595 | F26: =Monthly_MIS!F30 -> 27380595 | G26: =F26-E26 -> 0 | H26: 0.01 | I26: =IF(ISNUMBER(G26),IF(ABS(G26)<=H26,"PASS","FAIL"),"FAIL") -> PASS | J26: =IF(I26="PASS","None",IF(I26="N/A","No baseline in source","EXCEPTION: difference "&TEXT(G26,"#,##0.00")&" - investigate; see Calc_Actuals filter on col W")) -> None
A27: 22 | B27: Reconciliation | C27: Gross profit: Monthly_MIS total vs raw source (Status=Actual) | D27: Expected: SUMIFS on raw Sales_Transactions col K. Actual: Monthly_MIS total row. | E27: =SUMIFS(Sales_Transactions!$K$2:$K$865,Sales_Transactions!$C$2:$C$865,"Actual") -> 15212430 | F27: =Monthly_MIS!G30 -> 15212430 | G27: =F27-E27 -> 0 | H27: 0.01 | I27: =IF(ISNUMBER(G27),IF(ABS(G27)<=H27,"PASS","FAIL"),"FAIL") -> PASS | J27: =IF(I27="PASS","None",IF(I27="N/A","No baseline in source","EXCEPTION: difference "&TEXT(G27,"#,##0.00")&" - investigate; see Calc_Actuals filter on col W")) -> None
A28: 23 | B28: Reconciliation | C28: Gross profit: Monthly_MIS total vs source-file baseline | D28: Expected: baseline in source Control_Checks sheet (hard-coded). Actual: Monthly_MIS total row. | E28: 15212430 | F28: =Monthly_MIS!G30 -> 15212430 | G28: =F28-E28 -> 0 | H28: 0.01 | I28: =IF(ISNUMBER(G28),IF(ABS(G28)<=H28,"PASS","FAIL"),"FAIL") -> PASS | J28: =IF(I28="PASS","None",IF(I28="N/A","No baseline in source","EXCEPTION: difference "&TEXT(G28,"#,##0.00")&" - investigate; see Calc_Actuals filter on col W")) -> None
A29: 24 | B29: Reconciliation | C29: Net revenue: months where Monthly_MIS differs from raw SUMIFS by >0.01 | D29: Expected 0 months. Month-by-month comparison to Monthly_MIS cols L/M (SUMPRODUCT directly on raw Sales_Transactions). | E29: 0 | F29: =SUMPRODUCT(--(ABS(Monthly_MIS!$E$9:$E$29-Monthly_MIS!$L$9:$L$29)>0.01)) -> 0 | G29: =F29-E29 -> 0 | H29: 0 | I29: =IF(ISNUMBER(G29),IF(ABS(G29)<=H29,"PASS","FAIL"),"FAIL") -> PASS | J29: =IF(I29="PASS","None",IF(I29="N/A","No baseline in source","EXCEPTION: difference "&TEXT(G29,"#,##0.00")&" - investigate; see Calc_Actuals filter on col W")) -> None
A30: 25 | B30: Reconciliation | C30: COGS: months where Monthly_MIS differs from raw SUMIFS by >0.01 | D30: Expected 0 months. Month-by-month comparison to Monthly_MIS cols L/M (SUMPRODUCT directly on raw Sales_Transactions). | E30: 0 | F30: =SUMPRODUCT(--(ABS(Monthly_MIS!$F$9:$F$29-Monthly_MIS!$M$9:$M$29)>0.01)) -> 0 | G30: =F30-E30 -> 0 | H30: 0 | I30: =IF(ISNUMBER(G30),IF(ABS(G30)<=H30,"PASS","FAIL"),"FAIL") -> PASS | J30: =IF(I30="PASS","None",IF(I30="N/A","No baseline in source","EXCEPTION: difference "&TEXT(G30,"#,##0.00")&" - investigate; see Calc_Actuals filter on col W")) -> None
A31: 26 | B31: Reconciliation | C31: Net revenue: Region_Performance total vs Monthly_MIS | D31: Expected: Monthly_MIS total. Actual: sum of regions. | E31: =Monthly_MIS!E30 -> 42593025 | F31: =Region_Performance!B10 -> 42593025 | G31: =F31-E31 -> 0 | H31: 0.01 | I31: =IF(ISNUMBER(G31),IF(ABS(G31)<=H31,"PASS","FAIL"),"FAIL") -> PASS | J31: =IF(I31="PASS","None",IF(I31="N/A","No baseline in source","EXCEPTION: difference "&TEXT(G31,"#,##0.00")&" - investigate; see Calc_Actuals filter on col W")) -> None
A32: 27 | B32: Reconciliation | C32: Net revenue: Product_Performance total vs Monthly_MIS | D32: Expected: Monthly_MIS total. Actual: sum of products. | E32: =Monthly_MIS!E30 -> 42593025 | F32: =Product_Performance!C14 -> 42593025 | G32: =F32-E32 -> 0 | H32: 0.01 | I32: =IF(ISNUMBER(G32),IF(ABS(G32)<=H32,"PASS","FAIL"),"FAIL") -> PASS | J32: =IF(I32="PASS","None",IF(I32="N/A","No baseline in source","EXCEPTION: difference "&TEXT(G32,"#,##0.00")&" - investigate; see Calc_Actuals filter on col W")) -> None
A33: 28 | B33: Reconciliation | C33: COGS: Region_Performance total vs Monthly_MIS | D33: Expected: Monthly_MIS total. Actual: sum of regions. | E33: =Monthly_MIS!F30 -> 27380595 | F33: =Region_Performance!C10 -> 27380595 | G33: =F33-E33 -> 0 | H33: 0.01 | I33: =IF(ISNUMBER(G33),IF(ABS(G33)<=H33,"PASS","FAIL"),"FAIL") -> PASS | J33: =IF(I33="PASS","None",IF(I33="N/A","No baseline in source","EXCEPTION: difference "&TEXT(G33,"#,##0.00")&" - investigate; see Calc_Actuals filter on col W")) -> None
A34: 29 | B34: Reconciliation | C34: COGS: Product_Performance total vs Monthly_MIS | D34: Expected: Monthly_MIS total. Actual: sum of products. | E34: =Monthly_MIS!F30 -> 27380595 | F34: =Product_Performance!D14 -> 27380595 | G34: =F34-E34 -> 0 | H34: 0.01 | I34: =IF(ISNUMBER(G34),IF(ABS(G34)<=H34,"PASS","FAIL"),"FAIL") -> PASS | J34: =IF(I34="PASS","None",IF(I34="N/A","No baseline in source","EXCEPTION: difference "&TEXT(G34,"#,##0.00")&" - investigate; see Calc_Actuals filter on col W")) -> None
A35: 30 | B35: Reconciliation | C35: Gross profit: Region_Performance total vs Monthly_MIS | D35: Expected: Monthly_MIS total. Actual: sum of regions. | E35: =Monthly_MIS!G30 -> 15212430 | F35: =Region_Performance!D10 -> 15212430 | G35: =F35-E35 -> 0 | H35: 0.01 | I35: =IF(ISNUMBER(G35),IF(ABS(G35)<=H35,"PASS","FAIL"),"FAIL") -> PASS | J35: =IF(I35="PASS","None",IF(I35="N/A","No baseline in source","EXCEPTION: difference "&TEXT(G35,"#,##0.00")&" - investigate; see Calc_Actuals filter on col W")) -> None
A36: 31 | B36: Reconciliation | C36: Gross profit: Product_Performance total vs Monthly_MIS | D36: Expected: Monthly_MIS total. Actual: sum of products. | E36: =Monthly_MIS!G30 -> 15212430 | F36: =Product_Performance!E14 -> 15212430 | G36: =F36-E36 -> 0 | H36: 0.01 | I36: =IF(ISNUMBER(G36),IF(ABS(G36)<=H36,"PASS","FAIL"),"FAIL") -> PASS | J36: =IF(I36="PASS","None",IF(I36="N/A","No baseline in source","EXCEPTION: difference "&TEXT(G36,"#,##0.00")&" - investigate; see Calc_Actuals filter on col W")) -> None
A37: 32 | B37: Reconciliation | C37: YTD current revenue: Region_Performance total vs Monthly_MIS period summary | D37: Expected: Monthly_MIS period summary (SUMIFS by Year/Month_No). Actual: sum of regions. | E37: =Monthly_MIS!E34 -> 18093974 | F37: =SUM(Region_Performance!G6:G9) -> 18093974 | G37: =F37-E37 -> 0 | H37: 0.01 | I37: =IF(ISNUMBER(G37),IF(ABS(G37)<=H37,"PASS","FAIL"),"FAIL") -> PASS | J37: =IF(I37="PASS","None",IF(I37="N/A","No baseline in source","EXCEPTION: difference "&TEXT(G37,"#,##0.00")&" - investigate; see Calc_Actuals filter on col W")) -> None
A38: 33 | B38: Reconciliation | C38: YTD current revenue: Product_Performance total vs Monthly_MIS period summary | D38: Expected: Monthly_MIS period summary. Actual: sum of products. | E38: =Monthly_MIS!E34 -> 18093974 | F38: =SUM(Product_Performance!H6:H13) -> 18093974 | G38: =F38-E38 -> 0 | H38: 0.01 | I38: =IF(ISNUMBER(G38),IF(ABS(G38)<=H38,"PASS","FAIL"),"FAIL") -> PASS | J38: =IF(I38="PASS","None",IF(I38="N/A","No baseline in source","EXCEPTION: difference "&TEXT(G38,"#,##0.00")&" - investigate; see Calc_Actuals filter on col W")) -> None
A39: 34 | B39: Reconciliation | C39: YTD prior-year revenue: Region_Performance total vs Monthly_MIS period summary | D39: Expected: Monthly_MIS period summary (SUMIFS by Year/Month_No). Actual: sum of regions. | E39: =Monthly_MIS!E35 -> 18422630 | F39: =SUM(Region_Performance!H6:H9) -> 18422630 | G39: =F39-E39 -> 0 | H39: 0.01 | I39: =IF(ISNUMBER(G39),IF(ABS(G39)<=H39,"PASS","FAIL"),"FAIL") -> PASS | J39: =IF(I39="PASS","None",IF(I39="N/A","No baseline in source","EXCEPTION: difference "&TEXT(G39,"#,##0.00")&" - investigate; see Calc_Actuals filter on col W")) -> None
A40: 35 | B40: Reconciliation | C40: YTD prior-year revenue: Product_Performance total vs Monthly_MIS period summary | D40: Expected: Monthly_MIS period summary. Actual: sum of products. | E40: =Monthly_MIS!E35 -> 18422630 | F40: =SUM(Product_Performance!I6:I13) -> 18422630 | G40: =F40-E40 -> 0 | H40: 0.01 | I40: =IF(ISNUMBER(G40),IF(ABS(G40)<=H40,"PASS","FAIL"),"FAIL") -> PASS | J40: =IF(I40="PASS","None",IF(I40="N/A","No baseline in source","EXCEPTION: difference "&TEXT(G40,"#,##0.00")&" - investigate; see Calc_Actuals filter on col W")) -> None
A41: 36 | B41: Reconciliation | C41: YTD gross profit (current): sum of region GP% x YTD revenue vs Monthly_MIS | D41: Expected: Monthly_MIS YTD gross profit. Actual: SUMPRODUCT(region YTD GP% x YTD revenue). | E41: =Monthly_MIS!G34 -> 6461431.2 | F41: =SUMPRODUCT(Region_Performance!J6:J9,Region_Performance!G6:G9) -> 6461431.2 | G41: =F41-E41 -> 0 | H41: 0.01 | I41: =IF(ISNUMBER(G41),IF(ABS(G41)<=H41,"PASS","FAIL"),"FAIL") -> PASS | J41: =IF(I41="PASS","None",IF(I41="N/A","No baseline in source","EXCEPTION: difference "&TEXT(G41,"#,##0.00")&" - investigate; see Calc_Actuals filter on col W")) -> None
A42: 37 | B42: Reconciliation | C42: YTD gross profit (current): sum of product GP% x YTD revenue vs Monthly_MIS | D42: Expected: Monthly_MIS YTD gross profit. Actual: SUMPRODUCT(product YTD GP% x YTD revenue). | E42: =Monthly_MIS!G34 -> 6461431.2 | F42: =SUMPRODUCT(Product_Performance!K6:K13,Product_Performance!H6:H13) -> 6461431.2 | G42: =F42-E42 -> 0 | H42: 0.01 | I42: =IF(ISNUMBER(G42),IF(ABS(G42)<=H42,"PASS","FAIL"),"FAIL") -> PASS | J42: =IF(I42="PASS","None",IF(I42="N/A","No baseline in source","EXCEPTION: difference "&TEXT(G42,"#,##0.00")&" - investigate; see Calc_Actuals filter on col W")) -> None
A43: 38 | B43: Reconciliation | C43: Net revenue: Category roll-up vs Monthly_MIS | D43: Expected: Monthly_MIS total. Actual: sum of categories. | E43: =Monthly_MIS!E30 -> 42593025 | F43: =Product_Performance!C54 -> 42593025 | G43: =F43-E43 -> 0 | H43: 0.01 | I43: =IF(ISNUMBER(G43),IF(ABS(G43)<=H43,"PASS","FAIL"),"FAIL") -> PASS | J43: =IF(I43="PASS","None",IF(I43="N/A","No baseline in source","EXCEPTION: difference "&TEXT(G43,"#,##0.00")&" - investigate; see Calc_Actuals filter on col W")) -> None
A44: 39 | B44: Reconciliation | C44: Gross profit identity on Monthly_MIS | D44: Expected: sum of raw Gross_Profit_INR (Actual). Actual: Revenue - COGS from Monthly_MIS total. | E44: =SUMIFS(Sales_Transactions!$K$2:$K$865,Sales_Transactions!$C$2:$C$865,"Actual") -> 15212430 | F44: =Monthly_MIS!E30-Monthly_MIS!F30 -> 15212430 | G44: =F44-E44 -> 0 | H44: 0.01 | I44: =IF(ISNUMBER(G44),IF(ABS(G44)<=H44,"PASS","FAIL"),"FAIL") -> PASS | J44: =IF(I44="PASS","None",IF(I44="N/A","No baseline in source","EXCEPTION: difference "&TEXT(G44,"#,##0.00")&" - investigate; see Calc_Actuals filter on col W")) -> None
A45: 40 | B45: Scope | C45: Forecast excluded: Monthly_MIS + Forecast revenue = all source revenue | D45: Expected: SUM of all raw Net_Revenue_INR. Actual: Monthly total + Forecast-status revenue. | E45: =SUM(Sales_Transactions!$I$2:$I$865) -> 48526724 | F45: =Monthly_MIS!E30+SUMIFS(Sales_Transactions!$I$2:$I$865,Sales_Transactions!$C$2:$C$865,"Forecast") -> 48526724 | G45: =F45-E45 -> 0 | H45: 0.01 | I45: =IF(ISNUMBER(G45),IF(ABS(G45)<=H45,"PASS","FAIL"),"FAIL") -> PASS | J45: =IF(I45="PASS","None",IF(I45="N/A","No baseline in source","EXCEPTION: difference "&TEXT(G45,"#,##0.00")&" - investigate; see Calc_Actuals filter on col W")) -> None
A46: 41 | B46: Scope | C46: Forecast months appearing in Monthly_MIS | D46: Expected 0. Calendar months flagged Forecast that are listed in Monthly_MIS. | E46: 0 | F46: =SUMPRODUCT((Calendar!$E$2:$E$25="Forecast")*ISNUMBER(MATCH(Calendar!$A$2:$A$25,Monthly_MIS!$A$9:$A$29,0))) -> 0 | G46: =F46-E46 -> 0 | H46: 0 | I46: =IF(ISNUMBER(G46),IF(ABS(G46)<=H46,"PASS","FAIL"),"FAIL") -> PASS | J46: =IF(I46="PASS","None",IF(I46="N/A","No baseline in source","EXCEPTION: difference "&TEXT(G46,"#,##0.00")&" - investigate; see Calc_Actuals filter on col W")) -> None
A47: 42 | B47: Scope | C47: Calendar Actual months vs months listed in Monthly_MIS | D47: Expected: count of Actual months in Calendar. Actual: months listed. | E47: =COUNTIF(Calendar!$E$2:$E$25,"Actual") -> 21 | F47: =COUNTA(Monthly_MIS!$A$9:$A$29) -> 21 | G47: =F47-E47 -> 0 | H47: 0 | I47: =IF(ISNUMBER(G47),IF(ABS(G47)<=H47,"PASS","FAIL"),"FAIL") -> PASS | J47: =IF(I47="PASS","None",IF(I47="N/A","No baseline in source","EXCEPTION: difference "&TEXT(G47,"#,##0.00")&" - investigate; see Calc_Actuals filter on col W")) -> None
A48: 43 | B48: Scope | C48: Listed months with zero invoices | D48: Expected 0. | E48: 0 | F48: =COUNTIF(Monthly_MIS!$C$9:$C$29,0) -> 0 | G48: =F48-E48 -> 0 | H48: 0 | I48: =IF(ISNUMBER(G48),IF(ABS(G48)<=H48,"PASS","FAIL"),"FAIL") -> PASS | J48: =IF(I48="PASS","None",IF(I48="N/A","No baseline in source","EXCEPTION: difference "&TEXT(G48,"#,##0.00")&" - investigate; see Calc_Actuals filter on col W")) -> None
A49: 44 | B49: Budget v2 | C49: Original Sales_Budget carried unchanged into Budget_v2 (revenue) | D49: Expected: SUM of Sales_Budget revenue. Actual: SUM of original-revenue column in Budget_v2_Synthetic. | E49: =SUM(Sales_Budget!$E$2:$E$289) -> 345196800 | F49: =SUM(Budget_v2_Synthetic!$D$13:$D$300) -> 345196800 | G49: =F49-E49 -> 0 | H49: 0.01 | I49: =IF(ISNUMBER(G49),IF(ABS(G49)<=H49,"PASS","FAIL"),"FAIL") -> PASS | J49: =IF(I49="PASS","None",IF(I49="N/A","No baseline in source","EXCEPTION: difference "&TEXT(G49,"#,##0.00")&" - investigate; see Calc_Actuals filter on col W")) -> None
A50: 45 | B50: Budget v2 | C50: Calibration identity: in-scope v2 budget = actual in calibration year | D50: Expected: actual revenue, calibration year. Actual: SUM of in-scope v2 budget, calibration year. | E50: =Budget_v2_Synthetic!B5 -> 24499051 | F50: =SUMIFS(Budget_v2_Synthetic!$J$13:$J$300,Budget_v2_Synthetic!$G$13:$G$300,Budget_v2_Synthetic!B4,Budget_v2_Synthetic!$H$13:$H$300,1) -> 24499051 | G50: =F50-E50 -> 0 | H50: 0.01 | I50: =IF(ISNUMBER(G50),IF(ABS(G50)<=H50,"PASS","FAIL"),"FAIL") -> PASS | J50: =IF(I50="PASS","None",IF(I50="N/A","No baseline in source","EXCEPTION: difference "&TEXT(G50,"#,##0.00")&" - investigate; see Calc_Actuals filter on col W")) -> None
A51: 46 | B51: Budget v2 | C51: v2 gross profit = v2 revenue - v2 COGS | D51: Expected: SUM v2 revenue - SUM v2 COGS. Actual: SUM v2 GP. | E51: =SUM(Budget_v2_Synthetic!$J$13:$J$300)-SUM(Budget_v2_Synthetic!$K$13:$K$300) -> 33329784 | F51: =SUM(Budget_v2_Synthetic!$L$13:$L$300) -> 33329784 | G51: =F51-E51 -> 0 | H51: 0.01 | I51: =IF(ISNUMBER(G51),IF(ABS(G51)<=H51,"PASS","FAIL"),"FAIL") -> PASS | J51: =IF(I51="PASS","None",IF(I51="N/A","No baseline in source","EXCEPTION: difference "&TEXT(G51,"#,##0.00")&" - investigate; see Calc_Actuals filter on col W")) -> None
A52: 47 | B52: Budget v2 | C52: Variance sheet actuals tie to Monthly_MIS (all actual sales in scope) | D52: Expected: Monthly_MIS total revenue. Actual: Budget_vs_Actual_v2 total actual. | E52: =Monthly_MIS!E30 -> 42593025 | F52: =Budget_vs_Actual_v2!C26 -> 42593025 | G52: =F52-E52 -> 0 | H52: 0.01 | I52: =IF(ISNUMBER(G52),IF(ABS(G52)<=H52,"PASS","FAIL"),"FAIL") -> PASS | J52: =IF(I52="PASS","None",IF(I52="N/A","No baseline in source","EXCEPTION: difference "&TEXT(G52,"#,##0.00")&" - investigate; see Calc_Actuals filter on col W")) -> None
A53: 48 | B53: Budget v2 | C53: Budget months not found in Calendar | D53: Expected 0. | E53: 0 | F53: =COUNTIF(Budget_v2_Synthetic!$I$13:$I$300,"UNMATCHED") -> 0 | G53: =F53-E53 -> 0 | H53: 0 | I53: =IF(ISNUMBER(G53),IF(ABS(G53)<=H53,"PASS","FAIL"),"FAIL") -> PASS | J53: =IF(I53="PASS","None",IF(I53="N/A","No baseline in source","EXCEPTION: difference "&TEXT(G53,"#,##0.00")&" - investigate; see Calc_Actuals filter on col W")) -> None
A54: 49 | B54: Budget v2 | C54: Duplicate Month|Region|Category keys in budget | D54: Expected 0. | E54: 0 | F54: =ROWS(Budget_v2_Synthetic!$P$13:$P$300)-ROUND(SUMPRODUCT(1/COUNTIF(Budget_v2_Synthetic!$P$13:$P$300,Budget_v2_Synthetic!$P$13:$P$300)),0) -> 0 | G54: =F54-E54 -> 0 | H54: 0 | I54: =IF(ISNUMBER(G54),IF(ABS(G54)<=H54,"PASS","FAIL"),"FAIL") -> PASS | J54: =IF(I54="PASS","None",IF(I54="N/A","No baseline in source","EXCEPTION: difference "&TEXT(G54,"#,##0.00")&" - investigate; see Calc_Actuals filter on col W")) -> None
A55: 50 | B55: Integrity | C55: Formula errors in Calc_Actuals / report sheets | D55: Expected 0. ISERROR count across Calc_Actuals and report tables. | E55: 0 | F55: =SUMPRODUCT(--ISERROR(Calc_Actuals!$A$2:$W$865))+SUMPRODUCT(--ISERROR(Monthly_MIS!$A$9:$M$30))+SUMPRODUCT(--ISERROR(Region_Performance!$A$6:$N$10))+SUMPRODUCT(--ISERROR(Product_Performance!$A$6:$N$14))+SUMPRODUCT(--ISERROR(Budget_v2_Synthetic!$A$13:$P$300)) -> 0 | G55: =F55-E55 -> 0 | H55: 0 | I55: =IF(ISNUMBER(G55),IF(ABS(G55)<=H55,"PASS","FAIL"),"FAIL") -> PASS | J55: =IF(I55="PASS","None",IF(I55="N/A","No baseline in source","EXCEPTION: difference "&TEXT(G55,"#,##0.00")&" - investigate; see Calc_Actuals filter on col W")) -> None
A56: 51 | B56: Integrity | C56: Rows flagged in Calc_Actuals (any exception) | D56: Expected 0. Filter Calc_Actuals col W = 1 to list exception invoices. | E56: 0 | F56: =SUM(Calc_Actuals!$W$2:$W$865) -> 0 | G56: =F56-E56 -> 0 | H56: 0 | I56: =IF(ISNUMBER(G56),IF(ABS(G56)<=H56,"PASS","FAIL"),"FAIL") -> PASS | J56: =IF(I56="PASS","None",IF(I56="N/A","No baseline in source","EXCEPTION: difference "&TEXT(G56,"#,##0.00")&" - investigate; see Calc_Actuals filter on col W")) -> None
A58: Observations (information only - not pass/fail)
A59: # | B59: Area | C59: Observation | D59: Calculation | E59: Value | I59: Status | J59: Note
A60: O1 | B60: Budget scale | C60: Sales_Budget revenue for the same actual months vs actual net revenue (ratio) | D60: Sales_Budget revenue for listed actual months / Monthly_MIS total revenue (all 12 Region x Category cells) | E60: =SUMPRODUCT(ISNUMBER(MATCH(Sales_Budget!$A$2:$A$289,Monthly_MIS!$A$9:$A$29,0))*Sales_Budget!$E$2:$E$289)/Monthly_MIS!E30 -> 7.0525068 | I60: =IF(OR(E60>1.5,E60<0.67),"FLAG","OK") -> FLAG | J60: Budget is a separate scenario and is NOT compared with actuals. Scale mismatch needs business confirmation before any variance reporting.
A61: O2 | B61: Scope | C61: Operating_Expenses, Workforce, Inventory, Receivables sheets not used in Day-1 MIS | D61: Outside Day-1 scope (sales & gross profit). Not copied; original file untouched. | I61: INFO | J61: In the source, Operating_Expenses.Actual_INR is blank on all 75 Forecast rows (expected for forecasts).
A62: O3 | B62: Region vs product | C62: Maximum number of regions in which any single product sold (actual) | D62: MAX of Product_Performance col N. If 1, every product sells in one region only, so region and product effects cannot be separated. | E62: =MAX(Product_Performance!N6:N13) -> 1 | I62: =IF(E62<=1,"FLAG","OK") -> FLAG | J62: Region differences in revenue growth and margin are product-mix effects in this dataset; do not read them as regional performance without more data.
A64: Exception detail - build-time snapshot from an independent pandas scan (static; the live counts above are authoritative)
A65: - | C65: No exceptions found at build time.

Sheet Validation_Report
A1: Validation Report - what was actually tested
A2: Written from the test run on this workbook build. Anything not listed here was NOT tested.
A4: # | B4: Test | C4: What was done | D4: Result | E4: Evidence
A5: 1 | B5: Source inspection and schema check | C5: All required sheets/columns validated; Status values validated; source file hashed before and after. | D5: PASS | E5: SHA-256 46de2957611b9534...
A6: 2 | B6: Workbook control checks | C6: Recalculated headlessly in LibreOffice; every Control_Checks row read back. | D6: PASS | E6: ALL 51 CHECKS PASS; PASS=51, FAIL=0 of 51.
A7: 3 | B7: Independent recompute of report figures | C7: Re-derived Monthly_MIS, Region, Product, period summary and budget v2 variance from the source file in a separate pandas code path; compared to workbook values. | D7: PASS | E7: 325 figures compared; 0 differences.
A8: 4 | B8: Formula error scan | C8: Scanned every cell of the recalculated workbook for Excel error values. | D8: PASS | E8: 0 error cells.
A9: 5 | B9: Pipeline self-test record (fault injection, gating, release controls) | C9: Record bound to the combined SHA-256 of run_mis.py + mis_engine.py; must be current and fully passing. A stale or failing record blocks the run and blocks approval. | D9: PASS | E9: 68/68 self-tests passed at 2026-10-17T17:54:33Z; code hash 5afbee66355edddb...
A10: 6 | B10: EXCEL DESKTOP REQUIRED: Open the candidate in Microsoft Excel Desktop (Windows or Mac) | C10: Not performed by this pipeline (no Microsoft Excel available). | D10: NOT DONE | E10: Expected: File opens without a repair prompt or "update links" warning.
A11: 7 | B11: EXCEL DESKTOP REQUIRED: Force a full recalculation (Ctrl+Alt+F9) and read Control_Checks!C3 | C11: Not performed by this pipeline (no Microsoft Excel available). | D11: NOT DONE | E11: Expected: Shows "ALL <n> CHECKS PASS"; no #NAME?/#VALUE!/#N/A anywhere.
A12: 8 | B12: EXCEL DESKTOP REQUIRED: Compare Monthly_MIS totals and Executive_Summary KPIs with the run's validation_report.md | C12: Not performed by this pipeline (no Microsoft Excel available). | D12: NOT DONE | E12: Expected: Values equal the LibreOffice-recalculated values to the rupee.
A13: 9 | B13: EXCEL DESKTOP REQUIRED: Check month-filter formulas (SUMIFS on numeric Year/Month_No; LOOKUP(2,1/...) for latest month) | C13: Not performed by this pipeline (no Microsoft Excel available). | D13: NOT DONE | E13: Expected: Monthly_MIS!B4 shows the latest actual month; monthly rows non-zero.
A14: 10 | B14: EXCEL DESKTOP REQUIRED: Check Indian lakh/crore number format, conditional formatting (PASS green / FAIL red) and chart rendering | C14: Not performed by this pipeline (no Microsoft Excel available). | D14: NOT DONE | E14: Expected: Formats and 5-6 charts display as intended.
A15: 11 | B15: EXCEL DESKTOP REQUIRED: Check calculation time on a normal laptop | C15: Not performed by this pipeline (no Microsoft Excel available). | D15: NOT DONE | E15: Expected: Full recalculation completes in a few seconds (SUMPRODUCT/COUNTIF arrays over ~900 rows).
A16: 12 | B16: Audit trail strength | C16: Hash chain verified at run time. | D16: LIMITED | E16: Edit-detecting only. NOT externally anchored: no anchor record has been stored outside the workspace.
A17: 13 | B17: Not implemented | C17: Scheduling, unattended execution, live data refresh, email distribution, AI-model call, authenticated approver identity, cryptographic release signing. | D17: NOT DONE | E17: Run is started manually; approval is a separate manual step; approver name is typed text.

Sheet Data_Dictionary
A1: Data Dictionary
A2: Source fields used, derived fields and report measures.
A4: Sheet | B4: Field | C4: Type | D4: Description | E4: Derivation / rule
A5: Sales_Transactions | B5: Invoice_ID | C5: Text | D5: Unique invoice identifier (INV-MM-nnn) | E5: Primary key; uniqueness tested
A6: Sales_Transactions | B6: Month | C6: Text YYYY-MM | D6: Reporting month | E6: Links to Calendar.Month
A7: Sales_Transactions | B7: Status | C7: Text | D7: Actual or Forecast | E7: Only "Actual" rows enter the MIS; cross-checked to Calendar.Reporting_Status
A8: Sales_Transactions | B8: Customer_ID / Product_ID | C8: Text | D8: Foreign keys | E8: To Customer_Master / Product_Master; unmatched keys tested
A9: Sales_Transactions | B9: Units | C9: Integer | D9: Units sold | E9: Must be > 0
A10: Sales_Transactions | B10: Net_Price_INR / Unit_Cost_INR | C10: Decimal | D10: Net selling price and unit cost per unit, INR | E10: Must be > 0
A11: Sales_Transactions | B11: Net_Revenue_INR | C11: Decimal | D11: Net revenue, INR | E11: Source rule: Units x Net_Price_INR (re-performed in controls)
A12: Sales_Transactions | B12: COGS_INR | C12: Decimal | D12: Cost of goods sold, INR | E12: Source rule: Units x Unit_Cost_INR (re-performed in controls)
A13: Sales_Transactions | B13: Gross_Profit_INR | C13: Decimal | D13: Gross profit, INR | E13: Source rule: Net_Revenue - COGS (re-performed in controls)
A14: Product_Master | B14: Product_ID, Product_Name, Category | C14: Text | D14: Product attributes | E14: Lookup for product-wise and category analysis
A15: Product_Master | B15: List_Price_INR, Standard_Cost_INR | C15: Decimal | D15: Reference list price / standard cost | E15: Not used in MIS measures
... A33: Region / Product sheets | B33: YTD columns | C33: INR / % | D33: Jan to latest actual month, current vs prior year | E33: Latest actual month read from Calendar (Monthly_MIS!B4)
A34: Region / Product sheets | B34: Revenue share | C34: % | D34: Item revenue / total actual revenue

Sheet Automation_Readme
A1: Automation Readme
A2: How this workbook is produced, how to rerun it, and what it does NOT do.
A4: Source | B4: Single input workbook (Nova CFO MIS synthetic dataset). Required sheets/columns are validated before building; a schema failure stops the run before any workbook is produced. The source file is read-only input and is never modified (SHA-256 recorded before and after). Source tables used are copied unchanged into this workbook (grey tabs).
A5: Actuals definition | B5: Rows with Sales_Transactions.Status = "Actual", cross-checked against Calendar.Reporting_Status (must agree on every row). Forecast and Budget never enter any actual figure.
A6: Formulas | B6: Net revenue = SUMIFS of Net_Revenue_INR; COGS = SUMIFS of COGS_INR; Gross profit = Net revenue - COGS; GP % = Gross profit / Net revenue (ratio of sums). All report cells are live Excel formulas over Calc_Actuals, which references the raw sheets. Month filters use numeric Year / Month_No (not date-like text) for Excel robustness.
A7: Budget handling | B7: Original Sales_Budget is carried unchanged and NOT used for variance because it is not comparable (see Budget_Integrity). Budget_v2_Synthetic is a separate, clearly labelled, UNAPPROVED calibrated version used only for illustration in Budget_vs_Actual_v2.
A8: One-command run | B8: python run_mis.py run --input <dataset.xlsx> -> validates input, builds the workbook, recalculates it, re-derives every figure independently, applies the publication gate, drafts commentary and writes an edit-detecting hash-chained audit log (not tamper-proof; not externally anchored unless you store its final hash elsewhere) under runs/<run_id>/. Candidate files are NOT published.
A9: Publication gate | B9: Any failed critical control (workbook controls, independent recompute, error scan, commentary validation, audit-chain integrity, source-unchanged check, and a current passing self-test record bound to the combined hash of run_mis.py + mis_engine.py) sets status BLOCKED; nothing can be approved. A stale, failing or missing self-test record is critical and cannot be overridden by --ack-warnings. Warnings (budget integrity, restatement of previously published months, region/product overlap) require explicit acknowledgement at approval.
A10: Human approval | B10: python run_mis.py approve --run <run_id> --by "<name>" [--ack-warnings]. Verifies the self-test record, audit chain, candidate manifest, archived input hash and code hash, then copies the candidate into a NEW immutable folder published/<latest-month>/<run_id>/ (never overwrites; prior releases kept; LATEST.json updated only after success). Approval is never automatic. Approver name is typed text, not an authenticated identity. Optional commands: anchor, verify-anchor (external hash record) and verify-release. The script cannot stop files being copied by hand outside the controlled folder: that needs folder permissions or a signed-release process.
A11: Dependencies | B11: Python 3, pandas, numpy, openpyxl, LibreOffice (headless recalculation). Excel Desktop is NOT used by the pipeline.
A12: What is NOT implemented | B12: No scheduling, no unattended trigger, no live data connection, no email/distribution, no authenticated approver identity, no cryptographic signing, no external audit anchoring (optional manual step only). The commentary is rule-based text generated from verified facts (an externally written commentary can be supplied with --commentary-file and is checked against the fact pack); no AI model is called by the script. Variance on an original budget is not implemented (only the flagged-budget v2 path). Behaviour in desktop Excel is untested (see Validation_Report).
A13: Limitations | B13: Commentary and the Budget_Integrity findings table are static text from build time. Revenue excludes GST, returns, rebates and intercompany. The number-grounding check validates magnitudes, not direction or causal wording. Synthetic data only; causes of trends cannot be derived from the dataset.

Sheet Calc_Actuals
A1: Invoice_ID | B1: Month | C1: Status | D1: Customer_ID | E1: Product_ID | F1: Region | G1: Channel | H1: Category | I1: Product_Name | J1: Year | K1: Month_No | L1: Calendar_Status | M1: Units | N1: Net_Revenue_INR | O1: COGS_INR | P1: Gross_Profit_INR | Q1: Flag_Unmatched_Product | R1: Flag_Unmatched_Customer | S1: Flag_Unmatched_Month | T1: Flag_Duplicate_Invoice | U1: Flag_Arithmetic | V1: Flag_Status_vs_Calendar | W1: Any_Exception
A2: =Sales_Transactions!A2 -> INV-01-001 | B2: =Sales_Transactions!B2 -> 2025-01 | C2: =Sales_Transactions!C2 -> Actual | D2: =Sales_Transactions!D2 -> C001 | E2: =Sales_Transactions!E2 -> P001 | F2: =IFERROR(INDEX(Customer_Master!$C$2:$C$49,MATCH(D2,Customer_Master!$A$2:$A$49,0)),"UNMATCHED") -> South | G2: =IFERROR(INDEX(Customer_Master!$D$2:$D$49,MATCH(D2,Customer_Master!$A$2:$A$49,0)),"UNMATCHED") -> Distributor | H2: =IFERROR(INDEX(Product_Master!$C$2:$C$9,MATCH(E2,Product_Master!$A$2:$A$9,0)),"UNMATCHED") -> Home Care | I2: =IFERROR(INDEX(Product_Master!$B$2:$B$9,MATCH(E2,Product_Master!$A$2:$A$9,0)),"UNMATCHED") -> Detergent 1kg | J2: =IFERROR(INDEX(Calendar!$B$2:$B$25,MATCH(B2,Calendar!$A$2:$A$25,0)),0) -> 2025 | K2: =IFERROR(VALUE(RIGHT(B2,2)),0) -> 1 | L2: =IFERROR(INDEX(Calendar!$E$2:$E$25,MATCH(B2,Calendar!$A$2:$A$25,0)),"UNMATCHED") -> Actual | M2: =Sales_Transactions!F2 -> 412 | N2: =Sales_Transactions!I2 -> 78255.28 | O2: =Sales_Transactions!J2 -> 57049.64 | P2: =Sales_Transactions!K2 -> 21205.64 | Q2: =IF(ISNUMBER(MATCH(E2,Product_Master!$A$2:$A$9,0)),0,1) -> 0 | R2: =IF(ISNUMBER(MATCH(D2,Customer_Master!$A$2:$A$49,0)),0,1) -> 0 | S2: =IF(ISNUMBER(MATCH(B2,Calendar!$A$2:$A$25,0)),0,1) -> 0 | T2: =IF(COUNTIF(Sales_Transactions!$A$2:$A$865,A2)>1,1,0) -> 0 | U2: =IF(OR(ABS(Sales_Transactions!F2*Sales_Transactions!G2-Sales_Transactions!I2)>0.01,ABS(Sales_Transactions!F2*Sales_Transactions!H2-Sales_Transactions!J2)>0.01,ABS(Sales_Transactions!I2-Sales_Transactions!J2-Sales_Transactions!K2)>0.01),1,0) -> 0 | V2: =IF(C2<>L2,1,0) -> 0 | W2: =IF(SUM(Q2:V2)>0,1,0) -> 0
A3: =Sales_Transactions!A3 -> INV-01-002 | B3: =Sales_Transactions!B3 -> 2025-01 | C3: =Sales_Transactions!C3 -> Actual | D3: =Sales_Transactions!D3 -> C008 | E3: =Sales_Transactions!E3 -> P006 | F3: =IFERROR(INDEX(Customer_Master!$C$2:$C$49,MATCH(D3,Customer_Master!$A$2:$A$49,0)),"UNMATCHED") -> East | G3: =IFERROR(INDEX(Customer_Master!$D$2:$D$49,MATCH(D3,Customer_Master!$A$2:$A$49,0)),"UNMATCHED") -> Modern Trade | H3: =IFERROR(INDEX(Product_Master!$C$2:$C$9,MATCH(E3,Product_Master!$A$2:$A$9,0)),"UNMATCHED") -> Foods | I3: =IFERROR(INDEX(Product_Master!$B$2:$B$9,MATCH(E3,Product_Master!$A$2:$A$9,0)),"UNMATCHED") -> Breakfast Cereal | J3: =IFERROR(INDEX(Calendar!$B$2:$B$25,MATCH(B3,Calendar!$A$2:$A$25,0)),0) -> 2025 | K3: =IFERROR(VALUE(RIGHT(B3,2)),0) -> 1 | L3: =IFERROR(INDEX(Calendar!$E$2:$E$25,MATCH(B3,Calendar!$A$2:$A$25,0)),"UNMATCHED") -> Actual | M3: =Sales_Transactions!F3 -> 210 | N3: =Sales_Transactions!I3 -> 49213.5 | O3: =Sales_Transactions!J3 -> 34345.5 | P3: =Sales_Transactions!K3 -> 14868 | Q3: =IF(ISNUMBER(MATCH(E3,Product_Master!$A$2:$A$9,0)),0,1) -> 0 | R3: =IF(ISNUMBER(MATCH(D3,Customer_Master!$A$2:$A$49,0)),0,1) -> 0 | S3: =IF(ISNUMBER(MATCH(B3,Calendar!$A$2:$A$25,0)),0,1) -> 0 | T3: =IF(COUNTIF(Sales_Transactions!$A$2:$A$865,A3)>1,1,0) -> 0 | U3: =IF(OR(ABS(Sales_Transactions!F3*Sales_Transactions!G3-Sales_Transactions!I3)>0.01,ABS(Sales_Transactions!F3*Sales_Transactions!H3-Sales_Transactions!J3)>0.01,ABS(Sales_Transactions!I3-Sales_Transactions!J3-Sales_Transactions!K3)>0.01),1,0) -> 0 | V3: =IF(C3<>L3,1,0) -> 0 | W3: =IF(SUM(Q3:V3)>0,1,0) -> 0
A4: =Sales_Transactions!A4 -> INV-01-003 | B4: =Sales_Transactions!B4 -> 2025-01 | C4: =Sales_Transactions!C4 -> Actual | D4: =Sales_Transactions!D4 -> C015 | E4: =Sales_Transactions!E4 -> P003 | F4: =IFERROR(INDEX(Customer_Master!$C$2:$C$49,MATCH(D4,Customer_Master!$A$2:$A$49,0)),"UNMATCHED") -> West | G4: =IFERROR(INDEX(Customer_Master!$D$2:$D$49,MATCH(D4,Customer_Master!$A$2:$A$49,0)),"UNMATCHED") -> Retail | H4: =IFERROR(INDEX(Product_Master!$C$2:$C$9,MATCH(E4,Product_Master!$A$2:$A$9,0)),"UNMATCHED") -> Personal Care | I4: =IFERROR(INDEX(Product_Master!$B$2:$B$9,MATCH(E4,Product_Master!$A$2:$A$9,0)),"UNMATCHED") -> Shampoo 400ml | J4: =IFERROR(INDEX(Calendar!$B$2:$B$25,MATCH(B4,Calendar!$A$2:$A$25,0)),0) -> 2025 | K4: =IFERROR(VALUE(RIGHT(B4,2)),0) -> 1 | L4: =IFERROR(INDEX(Calendar!$E$2:$E$25,MATCH(B4,Calendar!$A$2:$A$25,0)),"UNMATCHED") -> Actual | M4: =Sales_Transactions!F4 -> 431 | N4: =Sales_Transactions!I4 -> 119024.96 | O4: =Sales_Transactions!J4 -> 75575.85 | P4: =Sales_Transactions!K4 -> 43449.11 | Q4: =IF(ISNUMBER(MATCH(E4,Product_Master!$A$2:$A$9,0)),0,1) -> 0 | R4: =IF(ISNUMBER(MATCH(D4,Customer_Master!$A$2:$A$49,0)),0,1) -> 0 | S4: =IF(ISNUMBER(MATCH(B4,Calendar!$A$2:$A$25,0)),0,1) -> 0 | T4: =IF(COUNTIF(Sales_Transactions!$A$2:$A$865,A4)>1,1,0) -> 0 | U4: =IF(OR(ABS(Sales_Transactions!F4*Sales_Transactions!G4-Sales_Transactions!I4)>0.01,ABS(Sales_Transactions!F4*Sales_Transactions!H4-Sales_Transactions!J4)>0.01,ABS(Sales_Transactions!I4-Sales_Transactions!J4-Sales_Transactions!K4)>0.01),1,0) -> 0 | V4: =IF(C4<>L4,1,0) -> 0 | W4: =IF(SUM(Q4:V4)>0,1,0) -> 0
A5: =Sales_Transactions!A5 -> INV-01-004 | B5: =Sales_Transactions!B5 -> 2025-01 | C5: =Sales_Transactions!C5 -> Actual | D5: =Sales_Transactions!D5 -> C022 | E5: =Sales_Transactions!E5 -> P008 | F5: =IFERROR(INDEX(Customer_Master!$C$2:$C$49,MATCH(D5,Customer_Master!$A$2:$A$49,0)),"UNMATCHED") -> North | G5: =IFERROR(INDEX(Customer_Master!$D$2:$D$49,MATCH(D5,Customer_Master!$A$2:$A$49,0)),"UNMATCHED") -> Distributor | H5: =IFERROR(INDEX(Product_Master!$C$2:$C$9,MATCH(E5,Product_Master!$A$2:$A$9,0)),"UNMATCHED") -> Personal Care | I5: =IFERROR(INDEX(Product_Master!$B$2:$B$9,MATCH(E5,Product_Master!$A$2:$A$9,0)),"UNMATCHED") -> Body Lotion | J5: =IFERROR(INDEX(Calendar!$B$2:$B$25,MATCH(B5,Calendar!$A$2:$A$25,0)),0) -> 2025 | K5: =IFERROR(VALUE(RIGHT(B5,2)),0) -> 1 | L5: =IFERROR(INDEX(Calendar!$E$2:$E$25,MATCH(B5,Calendar!$A$2:$A$25,0)),"UNMATCHED") -> Actual | M5: =Sales_Transactions!F5 -> 387 | N5: =Sales_Transactions!I5 -> 118839.96 | O5: =Sales_Transactions!J5 -> 75325.68 | P5: =Sales_Transactions!K5 -> 43514.28 | Q5: =IF(ISNUMBER(MATCH(E5,Product_Master!$A$2:$A$9,0)),0,1) -> 0 | R5: =IF(ISNUMBER(MATCH(D5,Customer_Master!$A$2:$A$49,0)),0,1) -> 0 | S5: =IF(ISNUMBER(MATCH(B5,Calendar!$A$2:$A$25,0)),0,1) -> 0 | T5: =IF(COUNTIF(Sales_Transactions!$A$2:$A$865,A5)>1,1,0) -> 0 | U5: =IF(OR(ABS(Sales_Transactions!F5*Sales_Transactions!G5-Sales_Transactions!I5)>0.01,ABS(Sales_Transactions!F5*Sales_Transactions!H5-Sales_Transactions!J5)>0.01,ABS(Sales_Transactions!I5-Sales_Transactions!J5-Sales_Transactions!K5)>0.01),1,0) -> 0 | V5: =IF(C5<>L5,1,0) -> 0 | W5: =IF(SUM(Q5:V5)>0,1,0) -> 0
A6: =Sales_Transactions!A6 -> INV-01-005 | B6: =Sales_Transactions!B6 -> 2025-01 | C6: =Sales_Transactions!C6 -> Actual | D6: =Sales_Transactions!D6 -> C029 | E6: =Sales_Transactions!E6 -> P005 | F6: =IFERROR(INDEX(Customer_Master!$C$2:$C$49,MATCH(D6,Customer_Master!$A$2:$A$49,0)),"UNMATCHED") -> South | G6: =IFERROR(INDEX(Customer_Master!$D$2:$D$49,MATCH(D6,Customer_Master!$A$2:$A$49,0)),"UNMATCHED") -> Modern Trade | H6: =IFERROR(INDEX(Product_Master!$C$2:$C$9,MATCH(E6,Product_Master!$A$2:$A$9,0)),"UNMATCHED") -> Foods | I6: =IFERROR(INDEX(Product_Master!$B$2:$B$9,MATCH(E6,Product_Master!$A$2:$A$9,0)),"UNMATCHED") -> Biscuits 500g | J6: =IFERROR(INDEX(Calendar!$B$2:$B$25,MATCH(B6,Calendar!$A$2:$A$25,0)),0) -> 2025 | K6: =IFERROR(VALUE(RIGHT(B6,2)),0) -> 1 | L6: =IFERROR(INDEX(Calendar!$E$2:$E$25,MATCH(B6,Calendar!$A$2:$A$25,0)),"UNMATCHED") -> Actual | M6: =Sales_Transactions!F6 -> 196 | N6: =Sales_Transactions!I6 -> 19841.08 | O6: =Sales_Transactions!J6 -> 13555.36 | P6: =Sales_Transactions!K6 -> 6285.72 | Q6: =IF(ISNUMBER(MATCH(E6,Product_Master!$A$2:$A$9,0)),0,1) -> 0 | R6: =IF(ISNUMBER(MATCH(D6,Customer_Master!$A$2:$A$49,0)),0,1) -> 0 | S6: =IF(ISNUMBER(MATCH(B6,Calendar!$A$2:$A$25,0)),0,1) -> 0 | T6: =IF(COUNTIF(Sales_Transactions!$A$2:$A$865,A6)>1,1,0) -> 0 | U6: =IF(OR(ABS(Sales_Transactions!F6*Sales_Transactions!G6-Sales_Transactions!I6)>0.01,ABS(Sales_Transactions!F6*Sales_Transactions!H6-Sales_Transactions!J6)>0.01,ABS(Sales_Transactions!I6-Sales_Transactions!J6-Sales_Transactions!K6)>0.01),1,0) -> 0 | V6: =IF(C6<>L6,1,0) -> 0 | W6: =IF(SUM(Q6:V6)>0,1,0) -> 0
A7: =Sales_Transactions!A7 -> INV-01-006 | B7: =Sales_Transactions!B7 -> 2025-01 | C7: =Sales_Transactions!C7 -> Actual | D7: =Sales_Transactions!D7 -> C036 | E7: =Sales_Transactions!E7 -> P002 | F7: =IFERROR(INDEX(Customer_Master!$C$2:$C$49,MATCH(D7,Customer_Master!$A$2:$A$49,0)),"UNMATCHED") -> East | G7: =IFERROR(INDEX(Customer_Master!$D$2:$D$49,MATCH(D7,Customer_Master!$A$2:$A$49,0)),"UNMATCHED") -> Retail | H7: =IFERROR(INDEX(Product_Master!$C$2:$C$9,MATCH(E7,Product_Master!$A$2:$A$9,0)),"UNMATCHED") -> Home Care | I7: =IFERROR(INDEX(Product_Master!$B$2:$B$9,MATCH(E7,Product_Master!$A$2:$A$9,0)),"UNMATCHED") -> Dishwash Gel | J7: =IFERROR(INDEX(Calendar!$B$2:$B$25,MATCH(B7,Calendar!$A$2:$A$25,0)),0) -> 2025 | K7: =IFERROR(VALUE(RIGHT(B7,2)),0) -> 1 | L7: =IFERROR(INDEX(Calendar!$E$2:$E$25,MATCH(B7,Calendar!$A$2:$A$25,0)),"UNMATCHED") -> Actual | M7: =Sales_Transactions!F7 -> 372 | N7: =Sales_Transactions!I7 -> 49401.6 | O7: =Sales_Transactions!J7 -> 31660.92 | P7: =Sales_Transactions!K7 -> 17740.68 | Q7: =IF(ISNUMBER(MATCH(E7,Product_Master!$A$2:$A$9,0)),0,1) -> 0 | R7: =IF(ISNUMBER(MATCH(D7,Customer_Master!$A$2:$A$49,0)),0,1) -> 0 | S7: =IF(ISNUMBER(MATCH(B7,Calendar!$A$2:$A$25,0)),0,1) -> 0 | T7: =IF(COUNTIF(Sales_Transactions!$A$2:$A$865,A7)>1,1,0) -> 0 | U7: =IF(OR(ABS(Sales_Transactions!F7*Sales_Transactions!G7-Sales_Transactions!I7)>0.01,ABS(Sales_Transactions!F7*Sales_Transactions!H7-Sales_Transactions!J7)>0.01,ABS(Sales_Transactions!I7-Sales_Transactions!J7-Sales_Transactions!K7)>0.01),1,0) -> 0 | V7: =IF(C7<>L7,1,0) -> 0 | W7: =IF(SUM(Q7:V7)>0,1,0) -> 0
A8: =Sales_Transactions!A8 -> INV-01-007 | B8: =Sales_Transactions!B8 -> 2025-01 | C8: =Sales_Transactions!C8 -> Actual | D8: =Sales_Transactions!D8 -> C043 | E8: =Sales_Transactions!E8 -> P007 | F8: =IFERROR(INDEX(Customer_Master!$C$2:$C$49,MATCH(D8,Customer_Master!$A$2:$A$49,0)),"UNMATCHED") -> West | G8: =IFERROR(INDEX(Customer_Master!$D$2:$D$49,MATCH(D8,Customer_Master!$A$2:$A$49,0)),"UNMATCHED") -> Distributor | H8: =IFERROR(INDEX(Product_Master!$C$2:$C$9,MATCH(E8,Product_Master!$A$2:$A$9,0)),"UNMATCHED") -> Home Care | I8: =IFERROR(INDEX(Product_Master!$B$2:$B$9,MATCH(E8,Product_Master!$A$2:$A$9,0)),"UNMATCHED") -> Floor Cleaner | J8: =IFERROR(INDEX(Calendar!$B$2:$B$25,MATCH(B8,Calendar!$A$2:$A$25,0)),0) -> 2025 | K8: =IFERROR(VALUE(RIGHT(B8,2)),0) -> 1 | L8: =IFERROR(INDEX(Calendar!$E$2:$E$25,MATCH(B8,Calendar!$A$2:$A$25,0)),"UNMATCHED") -> Actual | M8: =Sales_Transactions!F8 -> 364 | N8: =Sales_Transactions!I8 -> 65323.44 | O8: =Sales_Transactions!J8 -> 41335.84 | P8: =Sales_Transactions!K8 -> 23987.6 | Q8: =IF(ISNUMBER(MATCH(E8,Product_Master!$A$2:$A$9,0)),0,1) -> 0 | R8: =IF(ISNUMBER(MATCH(D8,Customer_Master!$A$2:$A$49,0)),0,1) -> 0 | S8: =IF(ISNUMBER(MATCH(B8,Calendar!$A$2:$A$25,0)),0,1) -> 0 | T8: =IF(COUNTIF(Sales_Transactions!$A$2:$A$865,A8)>1,1,0) -> 0 | U8: =IF(OR(ABS(Sales_Transactions!F8*Sales_Transactions!G8-Sales_Transactions!I8)>0.01,ABS(Sales_Transactions!F8*Sales_Transactions!H8-Sales_Transactions!J8)>0.01,ABS(Sales_Transactions!I8-Sales_Transactions!J8-Sales_Transactions!K8)>0.01),1,0) -> 0 | V8: =IF(C8<>L8,1,0) -> 0 | W8: =IF(SUM(Q8:V8)>0,1,0) -> 0
A9: =Sales_Transactions!A9 -> INV-01-008 | B9: =Sales_Transactions!B9 -> 2025-01 | C9: =Sales_Transactions!C9 -> Actual | D9: =Sales_Transactions!D9 -> C002 | E9: =Sales_Transactions!E9 -> P004 | F9: =IFERROR(INDEX(Customer_Master!$C$2:$C$49,MATCH(D9,Customer_Master!$A$2:$A$49,0)),"UNMATCHED") -> North | G9: =IFERROR(INDEX(Customer_Master!$D$2:$D$49,MATCH(D9,Customer_Master!$A$2:$A$49,0)),"UNMATCHED") -> Modern Trade | H9: =IFERROR(INDEX(Product_Master!$C$2:$C$9,MATCH(E9,Product_Master!$A$2:$A$9,0)),"UNMATCHED") -> Personal Care | I9: =IFERROR(INDEX(Product_Master!$B$2:$B$9,MATCH(E9,Product_Master!$A$2:$A$9,0)),"UNMATCHED") -> Soap 4-pack | J9: =IFERROR(INDEX(Calendar!$B$2:$B$25,MATCH(B9,Calendar!$A$2:$A$25,0)),0) -> 2025 | K9: =IFERROR(VALUE(RIGHT(B9,2)),0) -> 1 | L9: =IFERROR(INDEX(Calendar!$E$2:$E$25,MATCH(B9,Calendar!$A$2:$A$25,0)),"UNMATCHED") -> Actual | M9: =Sales_Transactions!F9 -> 227 | N9: =Sales_Transactions!I9 -> 39534.32 | O9: =Sales_Transactions!J9 -> 20936.21 | P9: =Sales_Transactions!K9 -> 18598.11 | Q9: =IF(ISNUMBER(MATCH(E9,Product_Master!$A$2:$A$9,0)),0,1) -> 0 | R9: =IF(ISNUMBER(MATCH(D9,Customer_Master!$A$2:$A$49,0)),0,1) -> 0 | S9: =IF(ISNUMBER(MATCH(B9,Calendar!$A$2:$A$25,0)),0,1) -> 0 | T9: =IF(COUNTIF(Sales_Transactions!$A$2:$A$865,A9)>1,1,0) -> 0 | U9: =IF(OR(ABS(Sales_Transactions!F9*Sales_Transactions!G9-Sales_Transactions!I9)>0.01,ABS(Sales_Transactions!F9*Sales_Transactions!H9-Sales_Transactions!J9)>0.01,ABS(Sales_Transactions!I9-Sales_Transactions!J9-Sales_Transactions!K9)>0.01),1,0) -> 0 | V9: =IF(C9<>L9,1,0) -> 0 | W9: =IF(SUM(Q9:V9)>0,1,0) -> 0
A10: =Sales_Transactions!A10 -> INV-01-009 | B10: =Sales_Transactions!B10 -> 2025-01 | C10: =Sales_Transactions!C10 -> Actual | D10: =Sales_Transactions!D10 -> C009 | E10: =Sales_Transactions!E10 -> P001 | F10: =IFERROR(INDEX(Customer_Master!$C$2:$C$49,MATCH(D10,Customer_Master!$A$2:$A$49,0)),"UNMATCHED") -> South | G10: =IFERROR(INDEX(Customer_Master!$D$2:$D$49,MATCH(D10,Customer_Master!$A$2:$A$49,0)),"UNMATCHED") -> Retail | H10: =IFERROR(INDEX(Product_Master!$C$2:$C$9,MATCH(E10,Product_Master!$A$2:$A$9,0)),"UNMATCHED") -> Home Care | I10: =IFERROR(INDEX(Product_Master!$B$2:$B$9,MATCH(E10,Product_Master!$A$2:$A$9,0)),"UNMATCHED") -> Detergent 1kg | J10: =IFERROR(INDEX(Calendar!$B$2:$B$25,MATCH(B10,Calendar!$A$2:$A$25,0)),0) -> 2025 | K10: =IFERROR(VALUE(RIGHT(B10,2)),0) -> 1 | L10: =IFERROR(INDEX(Calendar!$E$2:$E$25,MATCH(B10,Calendar!$A$2:$A$25,0)),"UNMATCHED") -> Actual | M10: =Sales_Transactions!F10 -> 166 | N10: =Sales_Transactions!I10 -> 34189.36 | O10: =Sales_Transactions!J10 -> 21930.26 | P10: =Sales_Transactions!K10 -> 12259.1 | Q10: =IF(ISNUMBER(MATCH(E10,Product_Master!$A$2:$A$9,0)),0,1) -> 0 | R10: =IF(ISNUMBER(MATCH(D10,Customer_Master!$A$2:$A$49,0)),0,1) -> 0 | S10: =IF(ISNUMBER(MATCH(B10,Calendar!$A$2:$A$25,0)),0,1) -> 0 | T10: =IF(COUNTIF(Sales_Transactions!$A$2:$A$865,A10)>1,1,0) -> 0 | U10: =IF(OR(ABS(Sales_Transactions!F10*Sales_Transactions!G10-Sales_Transactions!I10)>0.01,ABS(Sales_Transactions!F10*Sales_Transactions!H10-Sales_Transactions!J10)>0.01,ABS(Sales_Transactions!I10-Sales_Transactions!J10-Sales_Transactions!K10)>0.01),1,0) -> 0 | V10: =IF(C10<>L10,1,0) -> 0 | W10: =IF(SUM(Q10:V10)>0,1,0) -> 0
A11: =Sales_Transactions!A11 -> INV-01-010 | B11: =Sales_Transactions!B11 -> 2025-01 | C11: =Sales_Transactions!C11 -> Actual | D11: =Sales_Transactions!D11 -> C016 | E11: =Sales_Transactions!E11 -> P006 | F11: =IFERROR(INDEX(Customer_Master!$C$2:$C$49,MATCH(D11,Customer_Master!$A$2:$A$49,0)),"UNMATCHED") -> East | G11: =IFERROR(INDEX(Customer_Master!$D$2:$D$49,MATCH(D11,Customer_Master!$A$2:$A$49,0)),"UNMATCHED") -> Distributor | H11: =IFERROR(INDEX(Product_Master!$C$2:$C$9,MATCH(E11,Product_Master!$A$2:$A$9,0)),"UNMATCHED") -> Foods | I11: =IFERROR(INDEX(Product_Master!$B$2:$B$9,MATCH(E11,Product_Master!$A$2:$A$9,0)),"UNMATCHED") -> Breakfast Cereal | J11: =IFERROR(INDEX(Calendar!$B$2:$B$25,MATCH(B11,Calendar!$A$2:$A$25,0)),0) -> 2025 | K11: =IFERROR(VALUE(RIGHT(B11,2)),0) -> 1 | L11: =IFERROR(INDEX(Calendar!$E$2:$E$25,MATCH(B11,Calendar!$A$2:$A$25,0)),"UNMATCHED") -> Actual | M11: =Sales_Transactions!F11 -> 164 | N11: =Sales_Transactions!I11 -> 38390.76 | O11: =Sales_Transactions!J11 -> 26904.2 | P11: =Sales_Transactions!K11 -> 11486.56 | Q11: =IF(ISNUMBER(MATCH(E11,Product_Master!$A$2:$A$9,0)),0,1) -> 0 | R11: =IF(ISNUMBER(MATCH(D11,Customer_Master!$A$2:$A$49,0)),0,1) -> 0 | S11: =IF(ISNUMBER(MATCH(B11,Calendar!$A$2:$A$25,0)),0,1) -> 0 | T11: =IF(COUNTIF(Sales_Transactions!$A$2:$A$865,A11)>1,1,0) -> 0 | U11: =IF(OR(ABS(Sales_Transactions!F11*Sales_Transactions!G11-Sales_Transactions!I11)>0.01,ABS(Sales_Transactions!F11*Sales_Transactions!H11-Sales_Transactions!J11)>0.01,ABS(Sales_Transactions!I11-Sales_Transactions!J11-Sales_Transactions!K11)>0.01),1,0) -> 0 | V11: =IF(C11<>L11,1,0) -> 0 | W11: =IF(SUM(Q11:V11)>0,1,0) -> 0
A12: =Sales_Transactions!A12 -> INV-01-011 | B12: =Sales_Transactions!B12 -> 2025-01 | C12: =Sales_Transactions!C12 -> Actual | D12: =Sales_Transactions!D12 -> C023 | E12: =Sales_Transactions!E12 -> P003 | F12: =IFERROR(INDEX(Customer_Master!$C$2:$C$49,MATCH(D12,Customer_Master!$A$2:$A$49,0)),"UNMATCHED") -> West | G12: =IFERROR(INDEX(Customer_Master!$D$2:$D$49,MATCH(D12,Customer_Master!$A$2:$A$49,0)),"UNMATCHED") -> Modern Trade | H12: =IFERROR(INDEX(Product_Master!$C$2:$C$9,MATCH(E12,Product_Master!$A$2:$A$9,0)),"UNMATCHED") -> Personal Care | I12: =IFERROR(INDEX(Product_Master!$B$2:$B$9,MATCH(E12,Product_Master!$A$2:$A$9,0)),"UNMATCHED") -> Shampoo 400ml | J12: =IFERROR(INDEX(Calendar!$B$2:$B$25,MATCH(B12,Calendar!$A$2:$A$25,0)),0) -> 2025 | K12: =IFERROR(VALUE(RIGHT(B12,2)),0) -> 1 | L12: =IFERROR(INDEX(Calendar!$E$2:$E$25,MATCH(B12,Calendar!$A$2:$A$25,0)),"UNMATCHED") -> Actual | M12: =Sales_Transactions!F12 -> 137 | N12: =Sales_Transactions!I12 -> 34603.46 | O12: =Sales_Transactions!J12 -> 22761.18 | P12: =Sales_Transactions!K12 -> 11842.28 | Q12: =IF(ISNUMBER(MATCH(E12,Product_Master!$A$2:$A$9,0)),0,1) -> 0 | R12: =IF(ISNUMBER(MATCH(D12,Customer_Master!$A$2:$A$49,0)),0,1) -> 0 | S12: =IF(ISNUMBER(MATCH(B12,Calendar!$A$2:$A$25,0)),0,1) -> 0 | T12: =IF(COUNTIF(Sales_Transactions!$A$2:$A$865,A12)>1,1,0) -> 0 | U12: =IF(OR(ABS(Sales_Transactions!F12*Sales_Transactions!G12-Sales_Transactions!I12)>0.01,ABS(Sales_Transactions!F12*Sales_Transactions!H12-Sales_Transactions!J12)>0.01,ABS(Sales_Transactions!I12-Sales_Transactions!J12-Sales_Transactions!K12)>0.01),1,0) -> 0 | V12: =IF(C12<>L12,1,0) -> 0 | W12: =IF(SUM(Q12:V12)>0,1,0) -> 0
A13: =Sales_Transactions!A13 -> INV-01-012 | B13: =Sales_Transactions!B13 -> 2025-01 | C13: =Sales_Transactions!C13 -> Actual | D13: =Sales_Transactions!D13 -> C030 | E13: =Sales_Transactions!E13 -> P008 | F13: =IFERROR(INDEX(Customer_Master!$C$2:$C$49,MATCH(D13,Customer_Master!$A$2:$A$49,0)),"UNMATCHED") -> North | G13: =IFERROR(INDEX(Customer_Master!$D$2:$D$49,MATCH(D13,Customer_Master!$A$2:$A$49,0)),"UNMATCHED") -> Retail | H13: =IFERROR(INDEX(Product_Master!$C$2:$C$9,MATCH(E13,Product_Master!$A$2:$A$9,0)),"UNMATCHED") -> Personal Care | I13: =IFERROR(INDEX(Product_Master!$B$2:$B$9,MATCH(E13,Product_Master!$A$2:$A$9,0)),"UNMATCHED") -> Body Lotion | J13: =IFERROR(INDEX(Calendar!$B$2:$B$25,MATCH(B13,Calendar!$A$2:$A$25,0)),0) -> 2025 | K13: =IFERROR(VALUE(RIGHT(B13,2)),0) -> 1 | L13: =IFERROR(INDEX(Calendar!$E$2:$E$25,MATCH(B13,Calendar!$A$2:$A$25,0)),"UNMATCHED") -> Actual | M13: =Sales_Transactions!F13 -> 261 | N13: =Sales_Transactions!I13 -> 82152.36 | O13: =Sales_Transactions!J13 -> 55718.28 | P13: =Sales_Transactions!K13 -> 26434.08 | Q13: =IF(ISNUMBER(MATCH(E13,Product_Master!$A$2:$A$9,0)),0,1) -> 0 | R13: =IF(ISNUMBER(MATCH(D13,Customer_Master!$A$2:$A$49,0)),0,1) -> 0 | S13: =IF(ISNUMBER(MATCH(B13,Calendar!$A$2:$A$25,0)),0,1) -> 0 | T13: =IF(COUNTIF(Sales_Transactions!$A$2:$A$865,A13)>1,1,0) -> 0 | U13: =IF(OR(ABS(Sales_Transactions!F13*Sales_Transactions!G13-Sales_Transactions!I13)>0.01,ABS(Sales_Transactions!F13*Sales_Transactions!H13-Sales_Transactions!J13)>0.01,ABS(Sales_Transactions!I13-Sales_Transactions!J13-Sales_Transactions!K13)>0.01),1,0) -> 0 | V13: =IF(C13<>L13,1,0) -> 0 | W13: =IF(SUM(Q13:V13)>0,1,0) -> 0
... A865: =Sales_Transactions!A865 -> INV-24-036 | B865: =Sales_Transactions!B865 -> 2026-12 | C865: =Sales_Transactions!C865 -> Forecast | D865: =Sales_Transactions!D865 -> C027 | E865: =Sales_Transactions!E865 -> P007 | F865: =IFERROR(INDEX(Customer_Master!$C$2:$C$49,MATCH(D865,Customer_Master!$A$2:$A$49,0)),"UNMATCHED") -> West | G865: =IFERROR(INDEX(Customer_Master!$D$2:$D$49,MATCH(D865,Customer_Master!$A$2:$A$49,0)),"UNMATCHED") -> Retail | H865: =IFERROR(INDEX(Product_Master!$C$2:$C$9,MATCH(E865,Product_Master!$A$2:$A$9,0)),"UNMATCHED") -> Home Care | I865: =IFERROR(INDEX(Product_Master!$B$2:$B$9,MATCH(E865,Product_Master!$A$2:$A$9,0)),"UNMATCHED") -> Floor Cleaner | J865: =IFERROR(INDEX(Calendar!$B$2:$B$25,MATCH(B865,Calendar!$A$2:$A$25,0)),0) -> 2026 | K865: =IFERROR(VALUE(RIGHT(B865,2)),0) -> 12 | L865: =IFERROR(INDEX(Calendar!$E$2:$E$25,MATCH(B865,Calendar!$A$2:$A$25,0)),"UNMATCHED") -> Forecast | M865: =Sales_Transactions!F865 -> 457 | N865: =Sales_Transactions!I865 -> 82488.5 | O865: =Sales_Transactions!J865 -> 53487.28 | P865: =Sales_Transactions!K865 -> 29001.22 | Q865: =IF(ISNUMBER(MATCH(E865,Product_Master!$A$2:$A$9,0)),0,1) -> 0 | R865: =IF(ISNUMBER(MATCH(D865,Customer_Master!$A$2:$A$49,0)),0,1) -> 0 | S865: =IF(ISNUMBER(MATCH(B865,Calendar!$A$2:$A$25,0)),0,1) -> 0 | T865: =IF(COUNTIF(Sales_Transactions!$A$2:$A$865,A865)>1,1,0) -> 0 | U865: =IF(OR(ABS(Sales_Transactions!F865*Sales_Transactions!G865-Sales_Transactions!I865)>0.01,ABS(Sales_Transactions!F865*Sales_Transactions!H865-Sales_Transactions!J865)>0.01,ABS(Sales_Transactions!I865-Sales_Transactions!J865-Sales_Transactions!K865)>0.01),1,0) -> 0 | V865: =IF(C865<>L865,1,0) -> 0 | W865: =IF(SUM(Q865:V865)>0,1,0) -> 0

Sheet Sales_Transactions
A1: Invoice_ID | B1: Month | C1: Status | D1: Customer_ID | E1: Product_ID | F1: Units | G1: Net_Price_INR | H1: Unit_Cost_INR | I1: Net_Revenue_INR | J1: COGS_INR | K1: Gross_Profit_INR
A2: INV-01-001 | B2: 2025-01 | C2: Actual | D2: C001 | E2: P001 | F2: 412 | G2: 189.94 | H2: 138.47 | I2: 78255.28 | J2: 57049.64 | K2: 21205.64
A3: INV-01-002 | B3: 2025-01 | C3: Actual | D3: C008 | E3: P006 | F3: 210 | G3: 234.35 | H3: 163.55 | I3: 49213.5 | J3: 34345.5 | K3: 14868
A4: INV-01-003 | B4: 2025-01 | C4: Actual | D4: C015 | E4: P003 | F4: 431 | G4: 276.16 | H4: 175.35 | I4: 119024.96 | J4: 75575.85 | K4: 43449.11
A5: INV-01-004 | B5: 2025-01 | C5: Actual | D5: C022 | E5: P008 | F5: 387 | G5: 307.08 | H5: 194.64 | I5: 118839.96 | J5: 75325.68 | K5: 43514.28
A6: INV-01-005 | B6: 2025-01 | C6: Actual | D6: C029 | E6: P005 | F6: 196 | G6: 101.23 | H6: 69.16 | I6: 19841.08 | J6: 13555.36 | K6: 6285.72
A7: INV-01-006 | B7: 2025-01 | C7: Actual | D7: C036 | E7: P002 | F7: 372 | G7: 132.8 | H7: 85.11 | I7: 49401.6 | J7: 31660.92 | K7: 17740.68
A8: INV-01-007 | B8: 2025-01 | C8: Actual | D8: C043 | E8: P007 | F8: 364 | G8: 179.46 | H8: 113.56 | I8: 65323.44 | J8: 41335.84 | K8: 23987.6
A9: INV-01-008 | B9: 2025-01 | C9: Actual | D9: C002 | E9: P004 | F9: 227 | G9: 174.16 | H9: 92.23 | I9: 39534.32 | J9: 20936.21 | K9: 18598.11
A10: INV-01-009 | B10: 2025-01 | C10: Actual | D10: C009 | E10: P001 | F10: 166 | G10: 205.96 | H10: 132.11 | I10: 34189.36 | J10: 21930.26 | K10: 12259.1
A11: INV-01-010 | B11: 2025-01 | C11: Actual | D11: C016 | E11: P006 | F11: 164 | G11: 234.09 | H11: 164.05 | I11: 38390.76 | J11: 26904.2 | K11: 11486.56
A12: INV-01-011 | B12: 2025-01 | C12: Actual | D12: C023 | E12: P003 | F12: 137 | G12: 252.58 | H12: 166.14 | I12: 34603.46 | J12: 22761.18 | K12: 11842.28
A13: INV-01-012 | B13: 2025-01 | C13: Actual | D13: C030 | E13: P008 | F13: 261 | G13: 314.76 | H13: 213.48 | I13: 82152.36 | J13: 55718.28 | K13: 26434.08
... A865: INV-24-036 | B865: 2026-12 | C865: Forecast | D865: C027 | E865: P007 | F865: 457 | G865: 180.5 | H865: 117.04 | I865: 82488.5 | J865: 53487.28 | K865: 29001.22

Sheet Product_Master
A1: Product_ID | B1: Product_Name | C1: Category | D1: List_Price_INR | E1: Standard_Cost_INR
A2: P001 | B2: Detergent 1kg | C2: Home Care | D2: 210 | E2: 132
A3: P002 | B3: Dishwash Gel | C3: Home Care | D3: 145 | E3: 82
A4: P003 | B4: Shampoo 400ml | C4: Personal Care | D4: 280 | E4: 171
A5: P004 | B5: Soap 4-pack | C5: Personal Care | D5: 175 | E5: 96
A6: P005 | B6: Biscuits 500g | C6: Foods | D6: 110 | E6: 67
A7: P006 | B7: Breakfast Cereal | C7: Foods | D7: 255 | E7: 156
A8: P007 | B8: Floor Cleaner | C8: Home Care | D8: 190 | E8: 112
A9: P008 | B9: Body Lotion | C9: Personal Care | D9: 325 | E9: 202

Sheet Customer_Master
A1: Customer_ID | B1: Customer_Name | C1: Region | D1: Channel
A2: C001 | B2: Synthetic Customer 001 | C2: South | D2: Distributor
A3: C002 | B3: Synthetic Customer 002 | C3: North | D3: Modern Trade
A4: C003 | B4: Synthetic Customer 003 | C4: West | D4: Retail
A5: C004 | B5: Synthetic Customer 004 | C5: East | D5: Distributor
A6: C005 | B6: Synthetic Customer 005 | C6: South | D6: Modern Trade
A7: C006 | B7: Synthetic Customer 006 | C7: North | D7: Retail
A8: C007 | B8: Synthetic Customer 007 | C8: West | D8: Distributor
A9: C008 | B9: Synthetic Customer 008 | C9: East | D9: Modern Trade
A10: C009 | B10: Synthetic Customer 009 | C10: South | D10: Retail
A11: C010 | B11: Synthetic Customer 010 | C11: North | D11: Distributor
A12: C011 | B12: Synthetic Customer 011 | C12: West | D12: Modern Trade
... A49: C048 | B49: Synthetic Customer 048 | C49: East | D49: Retail

Sheet Calendar
A1: Month | B1: Year | C1: Quarter | D1: Month_Name | E1: Reporting_Status
A2: 2025-01 | B2: 2025 | C2: Q1 | D2: Jan | E2: Actual
A3: 2025-02 | B3: 2025 | C3: Q1 | D3: Feb | E3: Actual
A4: 2025-03 | B4: 2025 | C4: Q1 | D4: Mar | E4: Actual
A5: 2025-04 | B5: 2025 | C5: Q2 | D5: Apr | E5: Actual
A6: 2025-05 | B6: 2025 | C6: Q2 | D6: May | E6: Actual
A7: 2025-06 | B7: 2025 | C7: Q2 | D7: Jun | E7: Actual
A8: 2025-07 | B8: 2025 | C8: Q3 | D8: Jul | E8: Actual
A9: 2025-08 | B9: 2025 | C9: Q3 | D9: Aug | E9: Actual
A10: 2025-09 | B10: 2025 | C10: Q3 | D10: Sep | E10: Actual
A11: 2025-10 | B11: 2025 | C11: Q4 | D11: Oct | E11: Actual
A12: 2025-11 | B12: 2025 | C12: Q4 | D12: Nov | E12: Actual
A13: 2025-12 | B13: 2025 | C13: Q4 | D13: Dec | E13: Actual
... A25: 2026-12 | B25: 2026 | C25: Q4 | D25: Dec | E25: Forecast

Sheet Sales_Budget
A1: Month | B1: Region | C1: Category | D1: Scenario | E1: Revenue_Budget_INR | F1: COGS_Budget_INR | G1: Gross_Profit_Budget_INR
A2: 2025-01 | B2: South | C2: Home Care | D2: Budget | E2: 950000 | F2: 589000 | G2: 361000
A3: 2025-01 | B3: South | C3: Personal Care | D3: Budget | E3: 1025000 | F3: 635500 | G3: 389500
A4: 2025-01 | B4: South | C4: Foods | D4: Budget | E4: 1100000 | F4: 682000 | G4: 418000
A5: 2025-01 | B5: North | C5: Home Care | D5: Budget | E5: 1035000 | F5: 641700 | G5: 393300
A6: 2025-01 | B6: North | C6: Personal Care | D6: Budget | E6: 1110000 | F6: 688200 | G6: 421800
A7: 2025-01 | B7: North | C7: Foods | D7: Budget | E7: 1185000 | F7: 734700 | G7: 450300
A8: 2025-01 | B8: West | C8: Home Care | D8: Budget | E8: 1120000 | F8: 694400 | G8: 425600
A9: 2025-01 | B9: West | C9: Personal Care | D9: Budget | E9: 1195000 | F9: 740900 | G9: 454100
A10: 2025-01 | B10: West | C10: Foods | D10: Budget | E10: 1270000 | F10: 787400 | G10: 482600
A11: 2025-01 | B11: East | C11: Home Care | D11: Budget | E11: 1205000 | F11: 747100 | G11: 457900
A12: 2025-01 | B12: East | C12: Personal Care | D12: Budget | E12: 1280000 | F12: 793600 | G12: 486400
A13: 2025-01 | B13: East | C13: Foods | D13: Budget | E13: 1355000 | F13: 840100 | G13: 514900
... A289: 2026-12 | B289: East | C289: Foods | D289: Budget | E289: 1463400 | F289: 907308 | G289: 556092
